Workbook

Sheet 006. Cuadro Comparativo APUs
E1: BUENO FERRO | I1: PABLO ESPINOSA | M1: MUÑOZ FREILE | Q1: RESUMEN
A2: CÓDIGO | B2: DESCRIPCIÓN | C2: UNIDAD | E2: CANTIDAD | F2: PRECIO UNITARIO | G2: PRECIO TOTAL | I2: CANTIDAD | J2: PRECIO UNITARIO | K2: PRECIO TOTAL | M2: CANTIDAD | N2: PRECIO UNITARIO | O2: PRECIO TOTAL | Q2: CANTIDAD x UNIDAD
A4: 01. PRELIMINARES
N5: IVA
A6: 01.01.01 | B6: Replanteo Topográfico Ejes Estructurales y movimiento tierras | C6: Glb | N6: 0
A8: MATERIALES
G9: =+E9*F9 -> 0 | K9: =+I9*J9 -> 0 | O9: =+M9*N9 -> 0
G10: =+E10*F10 -> 0 | K10: =+I10*J10 -> 0 | O10: =+M10*N10 -> 0
A11: MANO DE OBRA
B12: M. Replanteo Topográfico Ejes Estructurales y movimiento tierras | C12: Glb | E12: 1 | F12: 240 | G12: =+E12*F12 -> 240 | I12: 1 | J12: 120 | K12: =+I12*J12 -> 120 | M12: 1 | N12: 120 | O12: =+M12*N12 -> 120
G13: =+E13*F13 -> 0 | K13: =+I13*J13 -> 0 | O13: =+M13*N13 -> 0
A14: EQUIPO
E15: =+E43 -> 325.39 | G15: =+E15*F15 -> 0 | I15: =+I43 -> 249.11 | K15: =+I15*J15 -> 0 | M15: =+M43 -> 951.68 | O15: =+M15*N15 -> 0
G16: =+E16*F16 -> 0 | K16: =+I16*J16 -> 0 | O16: =+M16*N16 -> 0
A18: TOTAL COSTO APU | G18: =SUM(G8:G17) -> 240 | K18: =SUM(K6:K16) -> 120 | O18: =SUM(O6:O16) -> 120
A19: COSTO UNITARIO APU | G19: =+G18/E15 -> 0.73757645 | K19: =+K18/I15 -> 0.48171491 | O19: =+O18/M15 -> 0.1260928
A23: 01.01.02 | B23: Replanteo Y Nivelación | C23: m2
A25: MATERIALES
B26: Alambre galvanizado N 14 (Alambre galvanizado N 14) | C26: rollo | E26: 1 | F26: 83.81 | G26: =+E26*F26 -> 83.81 | K26: =+I26*J26 -> 0 | O26: =+M26*N26 -> 0 | Q26: =+E26/$E$43 -> 0.0030732352
B27: Broca Madera Titanio3/8" (Broca Madera Titanio3/8") | C27: Uni. | G27: =+E27*F27 -> 0 | K27: =+I27*J27 -> 0 | M27: 1 | N27: 1.03 | O27: =+M27*N27 -> 1.03 | Q27: =+M27/M43 -> 0.0010507734
B28: Caoba Roja (Caoba Roja) | C28: lb | E28: 19.5 | F28: 0.532 | G28: =+E28*F28 -> 10.374 | I28: 4.42 | J28: 0.5 | K28: =+I28*J28 -> 2.21 | M28: 8.11 | N28: 0.54 | O28: =+M28*N28 -> 4.3794 | Q28: =+(E28+I28+M28)/($E$43+$I$43+$M$43) -> 0.02098704
B29: Cementina (Cementina) | C29: saco | E29: 7 | F29: 1.488 | G29: =+E29*F29 -> 10.416 | I29: 9 | J29: 1.47 | K29: =+I29*J29 -> 13.23 | M29: 15 | N29: 1.95 | O29: =+M29*N29 -> 29.25 | Q29: =+(E29+I29+M29)/($E$43+$I$43+$M$43) -> 0.020312152
B30: Clavos de acero 2'' (Clavos de acero 2'') | C30: Kg. | E30: 1.5 | F30: 3.41 | G30: =+E30*F30 -> 5.115 | K30: =+I30*J30 -> 0 | O30: =+M30*N30 -> 0 | Q30: =+E30/E43 -> 0.0046098528
B31: Clavos de acero 21/2'' (Clavos de acero 21/2'') | C31: Kg. | E31: 2 | F31: 3.417 | G31: =+E31*F31 -> 6.834 | I31: 1 | J31: 3.94 | K31: =+I31*J31 -> 3.94 | M31: 0.5 | N31: 3.94 | O31: =+M31*N31 -> 1.97 | Q31: =+(E31+I31+M31)/($E$43+$I$43+$M$43) -> 0.0022933075
B32: Clavos galvanizados 2'' (Clavos galvanizados 2'') | C32: Kg. | E32: 3.5 | F32: 1.49 | G32: =+E32*F32 -> 5.215 | I32: 2 | J32: 2.08 | K32: =+I32*J32 -> 4.16 | O32: =+M32*N32 -> 0 | Q32: =+(E32+I32)/($E$43+$I$43) -> 0.0095735422
B33: Clavos galvanizados 2 1/2'' (Clavos galvanizados 2 1/2'') | C33: Kg. | E33: 4 | F33: 1.438 | G33: =+E33*F33 -> 5.752 | K33: =+I33*J33 -> 0 | M33: 0.25 | N33: 2 | O33: =+M33*N33 -> 0.5 | Q33: =+E33/E43 -> 0.012292941
B34: Clavos galvanizados 3" (Clavos galvanizados 3") | C34: Kg. | G34: =+E34*F34 -> 0 | I34: 1 | J34: 2.41 | K34: =+I34*J34 -> 2.41 | O34: =+M34*N34 -> 0 | Q34: =+I34/I43 -> 0.0040142909
B35: Cuartón 6 x 4 de eucalipto (Cuartón 6 x 4 de eucalipto) | C35: Uni. | G35: =+E35*F35 -> 0 | K35: =+I35*J35 -> 0 | M35: 13 | N35: 2.15 | O35: =+M35*N35 -> 27.95 | Q35: =+M35/M43 -> 0.013660054
B36: Manguera transparente (Manguera transparente) | C36: ml | G36: =+E36*F36 -> 0 | I36: 25 | J36: 0.4 | K36: =+I36*J36 -> 10 | O36: =+M36*N36 -> 0 | Q36: =+I36/I43 -> 0.10035727
B37: Pingos de 2.5 mts (Pingos de 2.5 mts) | C37: Uni. | E37: 19 | F37: 1.1275 | G37: =+E37*F37 -> 21.4225 | I37: 10 | J37: 1.1 | K37: =+I37*J37 -> 11 | M37: 3 | N37: 1.1 | O37: =+M37*N37 -> 3.3 | Q37: =+(E37+I37+M37)/($E$43+$I$43+$M$43) -> 0.020967383
B38: Pingos de 3 mts (Pingos de 3 mts) | C38: Uni. | G38: =+E38*F38 -> 0 | I38: 10 | J38: 1.08 | K38: =+I38*J38 -> 10.8 | M38: 5 | N38: 1.2 | O38: =+M38*N38 -> 6 | Q38: =+(I38+M38)/($I$43+$M$43) -> 0.012491776
B39: Riel de eucalipto (Riel de eucalipto) | C39: Uni. | E39: 32 | F39: 1.767 | G39: =+E39*F39 -> 56.544 | I39: 10 | J39: 1.82 | K39: =+I39*J39 -> 18.2 | O39: =+M39*N39 -> 0 | Q39: =+(E39+I39)/($E$43+$I$43) -> 0.07310705
B40: Spray Rojo (Spray Rojo) | C40: Uni. | E40: 3 | F40: 1.4845 | G40: =+E40*F40 -> 4.4535 | I40: 5 | J40: 1.78 | K40: =+I40*J40 -> 8.9 | M40: 2 | N40: 2.22 | O40: =+M40*N40 -> 4.44 | Q40: =+(E40+I40+M40)/($E$43+$I$43+$M$43) -> 0.0065523071
B41: Tablas de Monte (Tablas de Monte) | C41: Uni. | E41: 7 | F41: 2.34 | G41: =+E41*F41 -> 16.38 | I41: 10 | J41: 2.44 | K41: =+I41*J41 -> 24.4 | O41: =+M41*N41 -> 0 | Q41: =+(E41+I41)/($E$43+$I$43) -> 0.029590949
A42: MANO DE OBRA
B43: M. Replanteo Y Nivelación | C43: m2 | E43: 325.39 | F43: 0.72 | G43: =+E43*F43 -> 234.2808 | I43: 249.11 | J43: 0.72 | K43: =+I43*J43 -> 179.3592 | M43: 951.68 | N43: 0.89 | O43: =+M43*N43 -> 846.9952
G44: =+E44*F44 -> 0 | K44: =+I44*J44 -> 0 | O44: =+M44*N44 -> 0
G45: =+E45*F45 -> 0 | K45: =+I45*J45 -> 0 | O45: =+M45*N45 -> 0
A46: EQUIPO
G47: =+E47*F47 -> 0 | K47: =+I47*J47 -> 0 | O47: =+M47*N47 -> 0
G48: =+E48*F48 -> 0 | K48: =+I48*J48 -> 0 | O48: =+M48*N48 -> 0
A50: TOTAL COSTO APU | G50: =SUM(G26:G49) -> 460.5968 | K50: =SUM(K26:K48) -> 288.6092 | O50: =SUM(O23:O48) -> 925.8146
A51: COSTO UNITARIO APU | G51: =+G50/E43 -> 1.4155223 | K51: =+K50/I43 -> 1.1585613 | O51: =+O50/M43 -> 0.97282133
A55: 01.01.03 | B55: Instalaciones eléctricas provisionales | C55: Glb
A57: MATERIALES
G58: =+E58*F58 -> 0 | K58: =+I58*J58 -> 0 | O58: =+M58*N58 -> 0
G59: =+E59*F59 -> 0 | K59: =+I59*J59 -> 0 | O59: =+M59*N59 -> 0
A60: MANO DE OBRA
E61: 1 | F61: 300 | G61: =+E61*F61 -> 300 | I61: 1 | J61: 300 | K61: =+I61*J61 -> 300 | M61: 1 | N61: 300 | O61: =+M61*N61 -> 300
G62: =+E62*F62 -> 0 | K62: =+I62*J62 -> 0 | O62: =+M62*N62 -> 0
A63: EQUIPO
E64: =+E43 -> 325.39 | G64: =+E64*F64 -> 0 | I64: =+I43 -> 249.11 | K64: =+I64*J64 -> 0 | M64: =+M43 -> 951.68 | O64: =+M64*N64 -> 0
G65: =+E65*F65 -> 0 | K65: =+I65*J65 -> 0 | O65: =+M65*N65 -> 0
A67: TOTAL COSTO APU | G67: =SUM(G57:G66) -> 300 | K67: =SUM(K55:K65) -> 300 | O67: =SUM(O55:O65) -> 300
A68: COSTO UNITARIO APU | G68: =+G67/E64 -> 0.92197056 | K68: =+K67/I64 -> 1.2042873 | O68: =+O67/M64 -> 0.31523201
A72: 01.01.04 | B72: Instalaciones hidrosanitarias provisionales | C72: Glb
A74: MATERIALES
G75: =+E75*F75 -> 0 | K75: =+I75*J75 -> 0 | O75: =+M75*N75 -> 0
G76: =+E76*F76 -> 0 | K76: =+I76*J76 -> 0 | O76: =+M76*N76 -> 0
A77: MANO DE OBRA
E78: 1 | F78: 300 | G78: =+E78*F78 -> 300 | I78: 1 | J78: 300 | K78: =+I78*J78 -> 300 | M78: 1 | N78: 300 | O78: =+M78*N78 -> 300
G79: =+E79*F79 -> 0 | K79: =+I79*J79 -> 0 | O79: =+M79*N79 -> 0
A80: EQUIPO
G81: =+E81*F81 -> 0 | K81: =+I81*J81 -> 0 | O81: =+M81*N81 -> 0
A83: TOTAL COSTO APU | G83: =SUM(G74:G82) -> 300 | K83: =SUM(K72:K81) -> 300 | O83: =SUM(O72:O81) -> 300
A84: COSTO UNITARIO APU | G84: =+G83/E78 -> 300 | K84: =+K83/I78 -> 300 | O84: =+O83/M78 -> 300
A88: 01.01.05 | B88: Guachimanía de obra, baños, vestidores de obra y otros provisionales | C88: Glb
A90: MATERIALES
B91: Alambre galvanizado N 14 (Alambre galvanizado N 14) | C91: rollo | E91: 1 | F91: 75.74 | G91: =+E91*F91 -> 75.74 | K91: =+I91*J91 -> 0 | O91: =+M91*N91 -> 0 | Q91: 1
B92: Aldaba Galvanizada 2'' (Aldaba Galvanizada 2'') | C92: Uni. | E92: 1 | F92: 0.32 | G92: =+E92*F92 -> 0.32 | I92: 2 | J92: 1.03 | K92: =+I92*J92 -> 2.06 | O92: =+M92*N92 -> 0 | Q92: 2
B93: Armellas (Par de Armellas) | C93: Uni. | G93: =+E93*F93 -> 0 | I93: 2 | J93: 0.53 | K93: =+I93*J93 -> 1.06 | M93: 4 | N93: 0.57 | O93: =+M93*N93 -> 2.28 | Q93: 4
B94: Bisagra Negra 3" (Bisagra Negra 3") | C94: Uni. | E94: 6 | F94: 0.48 | G94: =+E94*F94 -> 2.88 | I94: 6 | J94: 0.74 | K94: =+I94*J94 -> 4.44 | O94: =+M94*N94 -> 0 | Q94: 6
B95: Bloque alivianado 15x20x40 (Bloque alivianado 15x20x40) | C95: Uni. | E95: 700 | F95: 0.35 | G95: =+E95*F95 -> 245 | K95: =+I95*J95 -> 0 | O95: =+M95*N95 -> 0 | Q95: 700
B96: Candado Viro Fai Anticizalla 70 (Candado Viro Fai Anticizalla 70) | C96: Uni. | G96: =+E96*F96 -> 0 | K96: =+I96*J96 -> 0 | M96: 1 | N96: 27.1 | O96: =+M96*N96 -> 27.1 | Q96: 3
B97: Cemento Campeón (Cemento Campeón) | C97: saco | E97: 12 | F97: 6.662 | G97: =+E97*F97 -> 79.944 | I97: 3 | J97: 6.7 | K97: =+I97*J97 -> 20.1 | M97: 1 | N97: 6.7 | O97: =+M97*N97 -> 6.7 | Q97: 12
B98: Clavos de acero 2.1/2” (Clavos de acero 2.1/2” (1 kilo)) | C98: Kg. | G98: =+E98*F98 -> 0 | K98: =+I98*J98 -> 0 | M98: 0.5 | N98: 3.94 | O98: =+M98*N98 -> 1.97 | Q98: 0.5
B99: Clavos galvanizados 2'' (Clavos galvanizados 2'') | C99: Kg. | E99: 2.5 | F99: 1.495 | G99: =+E99*F99 -> 3.7375 | I99: 1.5 | J99: 2.13 | K99: =+I99*J99 -> 3.195 | M99: 3 | N99: 2.08 | O99: =+M99*N99 -> 6.24 | Q99: 3
B100: Clavos galvanizados 2 1/2'' (Clavos galvanizados 2 1/2'') | C100: Kg. | E100: 2.5 | F100: 1.445 | G100: =+E100*F100 -> 3.6125 | K100: =+I100*J100 -> 0 | M100: 2 | N100: 2.02 | O100: =+M100*N100 -> 4.04 | Q100: 2.5
B101: Clavos Zinc 2 1/2"x9 (Caja 20kg (Clavos Zinc 2 1/2"x9 (Caja 20kg)) | C101: Kg. | G101: =+E101*F101 -> 0 | I101: 0.5 | J101: 3.04 | K101: =+I101*J101 -> 1.52 | M101: 2 | N101: 3.21 | O101: =+M101*N101 -> 6.42 | Q101: 2
B102: Cuartón 6 x 4 de eucalipto (Cuartón 6 x 4 de eucalipto) | C102: Uni. | G102: =+E102*F102 -> 0 | K102: =+I102*J102 -> 0 | M102: 54 | N102: 2.15 | O102: =+M102*N102 -> 116.1 | Q102: 60
B103: Disco diamante segmentado 9" (Disco diamante segmentado 9") | C103: Uni. | E103: 1 | F103: 5.59 | G103: =+E103*F103 -> 5.59 | K103: =+I103*J103 -> 0 | O103: =+M103*N103 -> 0 | Q103: 1
B104: Inodoro Guachimania (Inodoro Guachimania) | C104: Uni. | G104: =+E104*F104 -> 0 | I104: 1 | J104: 42.47 | K104: =+I104*J104 -> 42.47 | M104: 1 | N104: 45.53 | O104: =+M104*N104 -> 45.53 | Q104: 1
B105: Lavabo Guachimania (Lavabo Guachimania ) | C105: Uni. | G105: =+E105*F105 -> 0 | I105: 1 | J105: 42.47 | K105: =+I105*J105 -> 42.47 | M105: 1 | N105: 45.53 | O105: =+M105*N105 -> 45.53 | Q105: 1
B106: Pingos de 2.5 mts (Pingos de 2.5 mts) | C106: Uni. | G106: =+E106*F106 -> 0 | I106: 6 | J106: 1.1 | K106: =+I106*J106 -> 6.6 | M106: 11 | N106: 1.1 | O106: =+M106*N106 -> 12.1 | Q106: 12
B107: Pingos de 3 mts. (Pingos de 3 mts.) | C107: Uni. | G107: =+E107*F107 -> 0 | K107: =+I107*J107 -> 0 | M107: 24 | N107: 1.2 | O107: =+M107*N107 -> 28.8 | Q107: 24
B108: Pingos de 4 mts. (Pingos de 4 mts.) | C108: Uni. | E108: 5 | F108: 6 | G108: =+E108*F108 -> 30 | K108: =+I108*J108 -> 0 | M108: 4 | N108: 4.32 | O108: =+M108*N108 -> 17.28 | Q108: 6
B109: Pingos de 6 mts. (Pingos de 6 mts.) | C109: Uni. | E109: 10 | F109: 7.2 | G109: =+E109*F109 -> 72 | I109: 4 | J109: 6.48 | K109: =+I109*J109 -> 25.92 | M109: 12 | N109: 7.2 | O109: =+M109*N109 -> 86.4 | Q109: 12
B110: Plastico Negro 1.5 mts (Plastico Negro 1.5 mts (2.20 mts x kg) (45 kilos)) | C110: rollo | G110: =+E110*F110 -> 0 | I110: 1.2 | J110: 64.73 | K110: =+I110*J110 -> 77.676 | M110: 0.41 | N110: 72.29 | O110: =+M110*N110 -> 29.6389 | Q110: 1
B111: Riel de eucalipto (Riel de eucalipto) | C111: Uni. | E111: 18 | F111: 1.8025 | G111: =+E111*F111 -> 32.445 | I111: 6 | J111: 1.82 | K111: =+I111*J111 -> 10.92 | M111: 23 | N111: 1.85 | O111: =+M111*N111 -> 42.55 | Q111: 24
B112: Tablas de Monte (Tablas de Monte) | C112: Uni. | E112: 30 | F112: 2.3732 | G112: =+E112*F112 -> 71.196 | I112: 32 | J112: 2.44 | K112: =+I112*J112 -> 78.08 | M112: 42 | N112: 2.39 | O112: =+M112*N112 -> 100.38 | Q112: 36
B113: Tablón Rustico (Tablón Rustico) | C113: Uni. | E113: 2 | F113: 6.35 | G113: =+E113*F113 -> 12.7 | K113: =+I113*J113 -> 0 | O113: =+M113*N113 -> 0 | Q113: 2
B114: Tela Arpillera Verde 1.90m (Tela Arpillera Verde 1.90m (Rollo 100m)) | C114: rollo | E114: 1.3 | F114: 46.92 | G114: =+E114*F114 -> 60.996 | K114: =+I114*J114 -> 0 | O114: =+M114*N114 -> 0 | Q114: 1
B115: Zinc 2.40mts x 0.80 cm Cal.0.20 (Zinc 2.40mts x 0.80 cm Cal.0.20) | C115: Uni. | E115: 2 | F115: 4.185 | G115: =+E115*F115 -> 8.37 | K115: =+I115*J115 -> 0 | O115: =+M115*N115 -> 0 | Q115: 2
B116: Zinc 3.60mts x 0.8mts Cal.0.20 (Zinc 3.60mts x 0.8mts Cal.0.20) | C116: Uni. | E116: 16 | F116: 6.402 | G116: =+E116*F116 -> 102.432 | I116: 12 | J116: 7.91 | K116: =+I116*J116 -> 94.92 | M116: 14 | N116: 8.24 | O116: =+M116*N116 -> 115.36 | Q116: 15
G117: =+E117*F117 -> 0 | K117: =+I117*J117 -> 0 | O117: =+M117*N117 -> 0
A118: MANO DE OBRA
B119: M. Guachimanía de obra, baños, vestidores de obra y otros provisionales | C119: Glb | E119: 1 | F119: 200 | G119: =+E119*F119 -> 200 | I119: 1 | J119: 200 | K119: =+I119*J119 -> 200 | M119: 1 | N119: 200 | O119: =+M119*N119 -> 200
E120: =+E43 -> 325.39 | G120: =+E120*F120 -> 0 | I120: =+I43 -> 249.11 | K120: =+I120*J120 -> 0 | M120: =+M43 -> 951.68 | O120: =+M120*N120 -> 0
A121: EQUIPO
G122: =+E122*F122 -> 0 | K122: =+I122*J122 -> 0 | O122: =+M122*N122 -> 0
...

Sheet Reporte Decisiones Pendientes
A1: REPORTE DE DECISIONES PENDIENTES — Revisión con Ingenieros
A2: Insumos con dispersión de precio entre obras. Marcar 'Valor Adoptado' y firmar.
A4: Categoría | B4: APU | C4: Sección | D4: Insumo | E4: Unidad | F4: PU BUENO FERRO | G4: PU PABLO ESPINOSA | H4: PU MUÑOZ FREILE | I4: Desv % | J4: Valor Adoptado / Observación Ing.
A5: --- A - ERROR DE UNIDAD PROBABLE (5) ---
A6: A - ERROR DE UNIDAD PROBABLE | B6: 13.01.09 | C6: materiales | D6: Cable Gemelo Blanco 2X10 (Cable Gemelo Blanco 2X10) | E6: Rollo | G6: 99.11 | H6: 1.2 | I6: 81.59
A7: A - ERROR DE UNIDAD PROBABLE | B7: 01.01.08 | C7: materiales | D7: Tela Arpillera Verde 1.90m (Tela Arpillera Verde 1.90m (Rollo 100m)) | E7: rollo | F7: 46.93 | H7: 0.61 | I7: 75.93
A8: A - ERROR DE UNIDAD PROBABLE | B8: 13.01.02 | C8: materiales | D8: Detergente (Detergente) | E8: Kg. | F8: 1.77 | H8: 27.18 | I8: 14.36
A9: A - ERROR DE UNIDAD PROBABLE | B9: 03.03.04 | C9: materiales | D9: Disco diamante segmentado 9" (Disco diamante segmentado 9") | E9: Uni. | F9: 5.59 | H9: 71 | I9: 11.7
A10: A - ERROR DE UNIDAD PROBABLE | B10: 02.01.02 | C10: equipo | D10: M. Transporte desalojo de material a botadero | E10: m3 | G10: 36.78 | H10: 3.79 | I10: 8.7
A11: --- B - REQUIERE CRITERIO (17) ---
A12: B - REQUIERE CRITERIO | B12: 03.03.04 | C12: materiales | D12: Hormigón Premez. fc= 210 kg S/B (Hormigón Premezclado fc= 210 kg/cm2) | E12: m3 | F12: 71 | H12: 12.5 | I12: 4.68
A13: B - REQUIERE CRITERIO | B13: 13.01.02 | C13: mano_obra | D13: M. Limpieza Provisional (Durante la obra Material Y Personal) | E13: Glb | F13: 202.61 | G13: 1026.32 | H13: 880 | I13: 4.07
A14: B - REQUIERE CRITERIO | B14: 13.01.05 | C14: equipo | D14: Gafa Transparente Reforzada (Gafa Transparente Reforzada) | E14: Uni. | G14: 1.82 | H14: 0.48 | I14: 2.79
A15: B - REQUIERE CRITERIO | B15: 13.01.09 | C15: materiales | D15: Manguera de Jardin con Acce (Manguera de Jardin con Accesorios) | E15: ml | G15: 0.31 | H15: 1.14 | I15: 2.68
A16: B - REQUIERE CRITERIO | B16: 03.02.02 | C16: materiales | D16: Cemento Campeón (Cemento Campeón) | E16: qq | F16: 6.64 | G16: 1.9366667 | H16: 6.71 | I16: 2.46
A17: B - REQUIERE CRITERIO | B17: 01.01.05 | C17: materiales | D17: Aldaba Galvanizada 2'' (Aldaba Galvanizada 2'') | E17: Uni. | F17: 0.32 | G17: 1.03 | I17: 2.22
A18: B - REQUIERE CRITERIO | B18: 05.01.05 | C18: materiales | D18: Broca Concreto 1/2X30cm (Broca Concreto 1/2X30cm) | E18: Uni. | F18: 5.1 | H18: 1.89 | I18: 1.7
A19: B - REQUIERE CRITERIO | B19: 04.01.08 | C19: materiales | D19: Clavos de acero 2'' (Clavos de acero 2'') | E19: Kg. | F19: 3.02 | G19: 7.2 | I19: 1.38
A20: B - REQUIERE CRITERIO | B20: 04.01.02 | C20: mano_obra | D20: M. Encofrado y Desencofrado de Vigas | E20: m2 | F20: 25.87 | G20: 11 | H20: 11.5 | I20: 1.35
A21: B - REQUIERE CRITERIO | B21: 05.01.06 | C21: materiales | D21: Clavos de acero 2'' (Clavos de acero 2'') | E21: Kg. | F21: 3.06 | G21: 7.2 | I21: 1.35
A22: B - REQUIERE CRITERIO | B22: 13.01.09 | C22: materiales | D22: Sierra Circular Dewalt 71/4 180 (Sierra Circular Dewalt 71/4 1800W DWE575-B3) | E22: Uni. | G22: 278.69 | H22: 118.54 | I22: 1.35
A23: B - REQUIERE CRITERIO | B23: 13.01.09 | C23: materiales | D23: Tanque para combustible 20lts. (Tanque para combustible rojo 20lts.) | E23: Uni. | G23: 17.48 | H23: 7.51 | I23: 1.33
A24: B - REQUIERE CRITERIO | B24: 13.01.05 | C24: equipo | D24: Casco (Casco) | E24: Uni. | F24: 9.52 | G24: 4.13 | H24: 4.12 | I24: 1.31
A25: B - REQUIERE CRITERIO | B25: 05.01.05 | C25: materiales | D25: Disco diamante segmentado 9" (Disco diamante segmentado 9") | E25: Uni. | F25: 5.31 | H25: 2.46 | I25: 1.16
A26: B - REQUIERE CRITERIO | B26: 13.01.09 | C26: materiales | D26: Taipe 3m 3/4 x2 Negro (Taipe 3m 3/4 x2 Negro) | E26: Uni. | F26: 0.906 | G26: 0.44 | H26: 0.85 | I26: 1.06
A27: B - REQUIERE CRITERIO | B27: 01.01.01 | C27: mano_obra | D27: M. Replanteo Topográfico Ejes Estructurales y movimiento tierras | E27: Glb | F27: 240 | G27: 120 | H27: 120 | I27: 1
A28: B - REQUIERE CRITERIO | B28: 03.03.15 | C28: equipo | D28: M. Pruebas De Laboratorio | E28: Glb | F28: 60 | G28: 40 | H28: 80 | I28: 1
A29: --- C - VARIACIÓN MEDIA-ALTA (informativo) (6) ---
A30: C - VARIACIÓN MEDIA-ALTA (informativo) | B30: 13.01.02 | C30: materiales | D30: Escoba de coco (Escoba de coco) | E30: Uni. | F30: 1.525 | G30: 2.89 | H30: 2.95 | I30: 0.93
A31: C - VARIACIÓN MEDIA-ALTA (informativo) | B31: 05.01.10 | C31: materiales | D31: Arena Fina (Arena Fina) | F31: 6.59 | H31: 12.27 | I31: 0.86
A32: C - VARIACIÓN MEDIA-ALTA (informativo) | B32: 03.03.07 | C32: materiales | D32: Ripio (Ripio) | E32: m3 | F32: 21.7 | G32: 11.83 | I32: 0.83
A33: C - VARIACIÓN MEDIA-ALTA (informativo) | B33: 05.01.05 | C33: materiales | D33: Sikadur Primer 32 | E33: Uni. | F33: 52.87 | H33: 87.71 | I33: 0.66
A34: C - VARIACIÓN MEDIA-ALTA (informativo) | B34: 03.02.02 | C34: materiales | D34: Disco Corte Madera 7 (Disco Corte Madera 7) | E34: Uni. | F34: 12.13 | H34: 7.4 | I34: 0.64
A35: C - VARIACIÓN MEDIA-ALTA (informativo) | B35: 13.01.05 | C35: equipo | D35: Cinta amarilla Precaución 200MT (Cinta amarilla Precaución 200MT) | E35: mts. | F35: 0.0164 | G35: 0.0222 | H35: 0.0265 | I35: 0.62

Sheet APU Estándar
A1: PROPUESTA DE APU ESTÁNDAR
A2: Construido a partir del análisis comparativo de 3 obras: BUENO FERRO · PABLO ESPINOSA · MUÑOZ FREILE
A3: Leyenda: 🟡 Fila amarilla = dato de 1 sola obra (cobertura única) | 🟠 Fila naranja = dispersión alta, revisar en hoja 'Reporte Decisiones Pendientes' | 🔴 Rojo = error de unidad probable
A5: 01. PRELIMINARES
A6: 01.01.01 | B6: Replanteo Topográfico Ejes Estructurales y movimiento tierras | C6: Glb | D6: Cant/Rend | E6: P.Unit | F6: Subtotal | G6: Cant BF | H6: PU BF | I6: Cant PE | J6: PU PE | K6: Cant MF | L6: PU MF | M6: Observación
A7: MANO DE OBRA
B8: M. Replanteo Topográfico Ejes Estructurales y movimiento tierras | C8: Glb | D8: =IFERROR(INDEX('BD Rendimientos'!G:G,MATCH("01.01.01|M. Replanteo Topográfico Ejes Estructurales y movimiento tierras|Glb|mano_obra",'BD Rendimientos'!L:L,0)),"") -> 1 | E8: =IFERROR(INDEX('BD Mano de Obra'!D:D,MATCH("M. Replanteo Topográfico Ejes Estructurales y movimiento tierras",'BD Mano de Obra'!B:B,0)),"") -> 160 | F8: =IFERROR(D8*E8,"") -> 160 | G8: 1 | H8: 240 | I8: 1 | J8: 120 | K8: 1 | L8: 120
A9: EQUIPO
B10: COSTO UNITARIO APU ESTÁNDAR | C10: Glb | F10: =SUM(F8) -> 160 | H10: 0.73757645 | J10: 0.48171491 | L10: 0.1260928 | M10: CU observados →
A12: 01.01.02 | B12: Replanteo Y Nivelación | C12: m2 | D12: Cant/Rend | E12: P.Unit | F12: Subtotal | G12: Cant BF | H12: PU BF | I12: Cant PE | J12: PU PE | K12: Cant MF | L12: PU MF | M12: Observación
A13: MATERIALES
B14: Alambre galvanizado N 14 | C14: rollo | D14: =IFERROR(INDEX('BD Rendimientos'!G:G,MATCH("01.01.02|Alambre galvanizado N 14|rollo|materiales",'BD Rendimientos'!L:L,0)),"") -> 0.0030732352 | E14: =IFERROR(INDEX('BD Materiales'!D:D,MATCH("Alambre galvanizado N 14",'BD Materiales'!B:B,0)),"") -> 82.9725 | F14: =IFERROR(D14*E14,"") -> 0.25499401 | G14: 1 | H14: 83.81 | M14: PU: cobertura única
B15: Broca Madera Titanio3/8" | C15: Uni. | D15: =IFERROR(INDEX('BD Rendimientos'!G:G,MATCH("01.01.02|Broca Madera Titanio3/8""|Uni.|materiales",'BD Rendimientos'!L:L,0)),"") -> 0.0010507734 | E15: =IFERROR(INDEX('BD Materiales'!D:D,MATCH("Broca Madera Titanio3/8""",'BD Materiales'!B:B,0)),"") -> 1.02 | F15: =IFERROR(D15*E15,"") -> 0.0010717888 | K15: 1 | L15: 1.03 | M15: PU: cobertura única
B16: Caoba Roja | C16: lb | D16: =IFERROR(INDEX('BD Rendimientos'!G:G,MATCH("01.01.02|Caoba Roja|lb|materiales",'BD Rendimientos'!L:L,0)),"") -> 0.017743166 | E16: =IFERROR(INDEX('BD Materiales'!D:D,MATCH("Caoba Roja",'BD Materiales'!B:B,0)),"") -> 0.517 | F16: =IFERROR(D16*E16,"") -> 0.0091732167 | G16: 19.5 | H16: 0.532 | I16: 4.42 | J16: 0.5 | K16: 8.11 | L16: 0.54 | M16: | Rend: Rendimiento disperso
B17: Cementina | C17: saco | D17: =IFERROR(INDEX('BD Rendimientos'!G:G,MATCH("01.01.02|Cementina|saco|materiales",'BD Rendimientos'!L:L,0)),"") -> 0.024467622 | E17: =IFERROR(INDEX('BD Materiales'!D:D,MATCH("Cementina",'BD Materiales'!B:B,0)),"") -> 1.636 | F17: =IFERROR(D17*E17,"") -> 0.040029029 | G17: 7 | H17: 1.488 | I17: 9 | J17: 1.47 | K17: 15 | L17: 1.95
B18: Clavos de acero 2'' | C18: Kg. | D18: =IFERROR(INDEX('BD Rendimientos'!G:G,MATCH("01.01.02|Clavos de acero 2''|Kg.|materiales",'BD Rendimientos'!L:L,0)),"") -> 0.0046098528 | E18: =IFERROR(INDEX('BD Materiales'!D:D,MATCH("Clavos de acero 2''",'BD Materiales'!B:B,0)),"") -> 3.245 | F18: =IFERROR(D18*E18,"") -> 0.014958972 | G18: 1.5 | H18: 3.41 | M18: PU: cobertura única
B19: Clavos de acero 21/2'' | C19: Kg. | D19: =IFERROR(INDEX('BD Rendimientos'!G:G,MATCH("01.01.02|Clavos de acero 21/2''|Kg.|materiales",'BD Rendimientos'!L:L,0)),"") -> 0.0040142909 | E19: =IFERROR(INDEX('BD Materiales'!D:D,MATCH("Clavos de acero 21/2''",'BD Materiales'!B:B,0)),"") -> 3.5215 | F19: =IFERROR(D19*E19,"") -> 0.014136325 | G19: 2 | H19: 3.417 | I19: 1 | J19: 3.94 | K19: 0.5 | L19: 3.94 | M19: | Rend: Rendimiento disperso
B20: Clavos galvanizados 2'' | C20: Kg. | D20: =IFERROR(INDEX('BD Rendimientos'!G:G,MATCH("01.01.02|Clavos galvanizados 2''|Kg.|materiales",'BD Rendimientos'!L:L,0)),"") -> 0.0093924525 | E20: =IFERROR(INDEX('BD Materiales'!D:D,MATCH("Clavos galvanizados 2''",'BD Materiales'!B:B,0)),"") -> 1.9257895 | F20: =IFERROR(D20*E20,"") -> 0.018087886 | G20: 3.5 | H20: 1.49 | I20: 2 | J20: 2.08
B21: Clavos galvanizados 2 1/2'' | C21: Kg. | D21: =IFERROR(INDEX('BD Rendimientos'!G:G,MATCH("01.01.02|Clavos galvanizados 2 1/2''|Kg.|materiales",'BD Rendimientos'!L:L,0)),"") -> 0.0062778171 | E21: =IFERROR(INDEX('BD Materiales'!D:D,MATCH("Clavos galvanizados 2 1/2''",'BD Materiales'!B:B,0)),"") -> 1.8223333 | F21: =IFERROR(D21*E21,"") -> 0.011440275 | G21: 4 | H21: 1.438 | K21: 0.25 | L21: 2 | M21: | Rend: Rendimiento disperso
B22: Clavos galvanizados 3" | C22: Kg. | D22: =IFERROR(INDEX('BD Rendimientos'!G:G,MATCH("01.01.02|Clavos galvanizados 3""|Kg.|materiales",'BD Rendimientos'!L:L,0)),"") -> 0.0040142909 | E22: =IFERROR(INDEX('BD Materiales'!D:D,MATCH("Clavos galvanizados 3""",'BD Materiales'!B:B,0)),"") -> 2.415 | F22: =IFERROR(D22*E22,"") -> 0.0096945125 | I22: 1 | J22: 2.41 | M22: PU: cobertura única
B23: Cuartón 6 x 4 de eucalipto | C23: Uni. | D23: =IFERROR(INDEX('BD Rendimientos'!G:G,MATCH("01.01.02|Cuartón 6 x 4 de eucalipto|Uni.|materiales",'BD Rendimientos'!L:L,0)),"") -> 0.013660054 | E23: =IFERROR(INDEX('BD Materiales'!D:D,MATCH("Cuartón 6 x 4 de eucalipto",'BD Materiales'!B:B,0)),"") -> 2.15 | F23: =IFERROR(D23*E23,"") -> 0.029369116 | K23: 13 | L23: 2.15 | M23: PU: cobertura única
B24: Manguera transparente | C24: ml | D24: =IFERROR(INDEX('BD Rendimientos'!G:G,MATCH("01.01.02|Manguera transparente|ml|materiales",'BD Rendimientos'!L:L,0)),"") -> 0.10035727 | E24: =IFERROR(INDEX('BD Materiales'!D:D,MATCH("Manguera transparente",'BD Materiales'!B:B,0)),"") -> 0.4 | F24: =IFERROR(D24*E24,"") -> 0.040142909 | I24: 25 | J24: 0.4 | M24: PU: cobertura única
B25: Pingos de 2.5 mts | C25: Uni. | D25: =IFERROR(INDEX('BD Rendimientos'!G:G,MATCH("01.01.02|Pingos de 2.5 mts|Uni.|materiales",'BD Rendimientos'!L:L,0)),"") -> 0.040142909 | E25: =IFERROR(INDEX('BD Materiales'!D:D,MATCH("Pingos de 2.5 mts",'BD Materiales'!B:B,0)),"") -> 1.1206818 | F25: =IFERROR(D25*E25,"") -> 0.044987428 | G25: 19 | H25: 1.1275 | I25: 10 | J25: 1.1 | K25: 3 | L25: 1.1 | M25: | Rend: Rendimiento disperso
B26: Pingos de 3 mts | C26: Uni. | D26: =IFERROR(INDEX('BD Rendimientos'!G:G,MATCH("01.01.02|Pingos de 3 mts|Uni.|materiales",'BD Rendimientos'!L:L,0)),"") -> 0.022698388 | E26: =IFERROR(INDEX('BD Materiales'!D:D,MATCH("Pingos de 3 mts",'BD Materiales'!B:B,0)),"") -> 1.14 | F26: =IFERROR(D26*E26,"") -> 0.025876162 | I26: 10 | J26: 1.08 | K26: 5 | L26: 1.2 | M26: | Rend: Rendimiento disperso
B27: Riel de eucalipto | C27: Uni. | D27: =IFERROR(INDEX('BD Rendimientos'!G:G,MATCH("01.01.02|Riel de eucalipto|Uni.|materiales",'BD Rendimientos'!L:L,0)),"") -> 0.069243217 | E27: =IFERROR(INDEX('BD Materiales'!D:D,MATCH("Riel de eucalipto",'BD Materiales'!B:B,0)),"") -> 1.81825 | F27: =IFERROR(D27*E27,"") -> 0.12590148 | G27: 32 | H27: 1.767 | I27: 10 | J27: 1.82
B28: Spray Rojo | C28: Uni. | D28: =IFERROR(INDEX('BD Rendimientos'!G:G,MATCH("01.01.02|Spray Rojo|Uni.|materiales",'BD Rendimientos'!L:L,0)),"") -> 0.0092197056 | E28: =IFERROR(INDEX('BD Materiales'!D:D,MATCH("Spray Rojo",'BD Materiales'!B:B,0)),"") -> 1.8281667 | F28: =IFERROR(D28*E28,"") -> 0.016855158 | G28: 3 | H28: 1.4845 | I28: 5 | J28: 1.78 | K28: 2 | L28: 2.22 | M28: | Rend: Rendimiento disperso
B29: Tablas de Monte | C29: Uni. | D29: =IFERROR(INDEX('BD Rendimientos'!G:G,MATCH("01.01.02|Tablas de Monte|Uni.|materiales",'BD Rendimientos'!L:L,0)),"") -> 0.030827778 | E29: =IFERROR(INDEX('BD Materiales'!D:D,MATCH("Tablas de Monte",'BD Materiales'!B:B,0)),"") -> 2.4034926 | F29: =IFERROR(D29*E29,"") -> 0.074094335 | G29: 7 | H29: 2.34 | I29: 10 | J29: 2.44
A30: MANO DE OBRA
B31: M. Replanteo Y Nivelación | C31: m2 | D31: =IFERROR(INDEX('BD Rendimientos'!G:G,MATCH("01.01.02|M. Replanteo Y Nivelación|m2|mano_obra",'BD Rendimientos'!L:L,0)),"") -> 1 | E31: =IFERROR(INDEX('BD Mano de Obra'!D:D,MATCH("M. Replanteo Y Nivelación",'BD Mano de Obra'!B:B,0)),"") -> 0.77666667 | F31: =IFERROR(D31*E31,"") -> 0.77666667 | G31: 325.39 | H31: 0.72 | I31: 249.11 | J31: 0.72 | K31: 951.68 | L31: 0.89
B32: COSTO UNITARIO APU ESTÁNDAR | C32: m2 | F32: =SUM(F14,F15,F16,F17,F18,F19,F20,F21,F22,F23,F24,F25,F26,F27,F28,F29,F31) -> 1.5074793 | H32: 1.4155223 | J32: 1.1585613 | L32: 0.97282133 | M32: CU observados →
A34: 01.01.03 | B34: Instalaciones eléctricas provisionales | C34: Glb | D34: Cant/Rend | E34: P.Unit | F34: Subtotal | G34: Cant BF | H34: PU BF | I34: Cant PE | J34: PU PE | K34: Cant MF | L34: PU MF | M34: Observación
A35: MANO DE OBRA
B36: M. Instalaciones eléctricas provisionales | C36: Glb | D36: =IFERROR(INDEX('BD Rendimientos'!G:G,MATCH("01.01.03|M. Instalaciones eléctricas provisionales|Glb|mano_obra",'BD Rendimientos'!L:L,0)),"") -> 1 | E36: =IFERROR(INDEX('BD Mano de Obra'!D:D,MATCH("M. Instalaciones eléctricas provisionales",'BD Mano de Obra'!B:B,0)),"") -> 300 | F36: =IFERROR(D36*E36,"") -> 300 | G36: 300 | H36: 300 | J36: 300 | L36: 300 | M36: MO principal (reconstruida)
A37: EQUIPO
B38: COSTO UNITARIO APU ESTÁNDAR | C38: Glb | F38: =F36 -> 300 | H38: 0.92197056 | J38: 1.2042873 | L38: 0.31523201 | M38: CU observados →
A40: 01.01.04 | B40: Instalaciones hidrosanitarias provisionales | C40: Glb | D40: Cant/Rend | E40: P.Unit | F40: Subtotal | G40: Cant BF | H40: PU BF | I40: Cant PE | J40: PU PE | K40: Cant MF | L40: PU MF | M40: Observación
A41: MANO DE OBRA
B42: M. Instalaciones hidrosanitarias provisionales | C42: Glb | D42: =IFERROR(INDEX('BD Rendimientos'!G:G,MATCH("01.01.04|M. Instalaciones hidrosanitarias provisionales|Glb|mano_obra",'BD Rendimientos'!L:L,0)),"") -> 1 | E42: =IFERROR(INDEX('BD Mano de Obra'!D:D,MATCH("M. Instalaciones hidrosanitarias provisionales",'BD Mano de Obra'!B:B,0)),"") -> 300 | F42: =IFERROR(D42*E42,"") -> 300 | G42: 300 | H42: 300 | J42: 300 | L42: 300 | M42: MO principal (reconstruida)
B43: COSTO UNITARIO APU ESTÁNDAR | C43: Glb | F43: =F42 -> 300 | H43: 300 | J43: 300 | L43: 300 | M43: CU observados →
A45: 01.01.05 | B45: Guachimanía de obra, baños, vestidores de obra y otros provisionales | C45: Glb | D45: Cant/Rend | E45: P.Unit | F45: Subtotal | G45: Cant BF | H45: PU BF | I45: Cant PE | J45: PU PE | K45: Cant MF | L45: PU MF | M45: Observación
A46: MATERIALES
B47: Alambre galvanizado N 14 | C47: rollo | D47: =IFERROR(INDEX('BD Rendimientos'!G:G,MATCH("01.01.05|Alambre galvanizado N 14|rollo|materiales",'BD Rendimientos'!L:L,0)),"") -> 1 | E47: =IFERROR(INDEX('BD Materiales'!D:D,MATCH("Alambre galvanizado N 14",'BD Materiales'!B:B,0)),"") -> 82.9725 | F47: =IFERROR(D47*E47,"") -> 82.9725 | G47: 1 | H47: 75.74 | M47: PU: cobertura única
B48: Aldaba Galvanizada 2'' | C48: Uni. | D48: =IFERROR(INDEX('BD Rendimientos'!G:G,MATCH("01.01.05|Aldaba Galvanizada 2''|Uni.|materiales",'BD Rendimientos'!L:L,0)),"") -> 1.5 | E48: =IFERROR(INDEX('BD Materiales'!D:D,MATCH("Aldaba Galvanizada 2''",'BD Materiales'!B:B,0)),"") -> 0.675 | F48: =IFERROR(D48*E48,"") -> 1.0125 | G48: 1 | H48: 0.32 | I48: 2 | J48: 1.03 | M48: PU: Criterio pendiente — desv 222%
B49: Armellas (Par de Armellas) | C49: Uni. | D49: =IFERROR(INDEX('BD Rendimientos'!G:G,MATCH("01.01.05|Armellas (Par de Armellas)|Uni.|materiales",'BD Rendimientos'!L:L,0)),"") -> 3 | E49: =IFERROR(INDEX('BD Materiales'!D:D,MATCH("Armellas (Par de Armellas)",'BD Materiales'!B:B,0)),"") -> 0.55 | F49: =IFERROR(D49*E49,"") -> 1.65 | I49: 2 | J49: 0.53 | K49: 4 | L49: 0.57
B50: Bisagra Negra 3" | C50: Uni. | D50: =IFERROR(INDEX('BD Rendimientos'!G:G,MATCH("01.01.05|Bisagra Negra 3""|Uni.|materiales",'BD Rendimientos'!L:L,0)),"") -> 6 | E50: =IFERROR(INDEX('BD Materiales'!D:D,MATCH("Bisagra Negra 3""",'BD Materiales'!B:B,0)),"") -> 0.61 | F50: =IFERROR(D50*E50,"") -> 3.66 | G50: 6 | H50: 0.48 | I50: 6 | J50: 0.74
B51: Bloque alivianado 15x20x40 | C51: Uni. | D51: =IFERROR(INDEX('BD Rendimientos'!G:G,MATCH("01.01.05|Bloque alivianado 15x20x40|Uni.|materiales",'BD Rendimientos'!L:L,0)),"") -> 700 | E51: =IFERROR(INDEX('BD Materiales'!D:D,MATCH("Bloque alivianado 15x20x40",'BD Materiales'!B:B,0)),"") -> 0.346 | F51: =IFERROR(D51*E51,"") -> 242.2 | G51: 700 | H51: 0.35 | M51: PU: cobertura única
B52: Candado Viro Fai Anticizalla 70 | C52: Uni. | D52: =IFERROR(INDEX('BD Rendimientos'!G:G,MATCH("01.01.05|Candado Viro Fai Anticizalla 70|Uni.|materiales",'BD Rendimientos'!L:L,0)),"") -> 1 | E52: =IFERROR(INDEX('BD Materiales'!D:D,MATCH("Candado Viro Fai Anticizalla 70",'BD Materiales'!B:B,0)),"") -> 27.1 | F52: =IFERROR(D52*E52,"") -> 27.1 | K52: 1 | L52: 27.1 | M52: PU: cobertura única
B53: Cemento Campeón | C53: saco | D53: =IFERROR(INDEX('BD Rendimientos'!G:G,MATCH("01.01.05|Cemento Campeón|saco|materiales",'BD Rendimientos'!L:L,0)),"") -> 3 | E53: =IFERROR(INDEX('BD Materiales'!D:D,MATCH("Cemento Campeón",'BD Materiales'!B:B,0)),"") -> 6.7 | F53: =IFERROR(D53*E53,"") -> 20.1 | G53: 12 | H53: 6.662 | I53: 3 | J53: 6.7 | K53: 1 | L53: 6.7 | M53: | Rend: Rendimiento disperso
B54: Clavos de acero 2.1/2” (Clavos de acero 2.1/2” (1 kilo)) | C54: Kg. | D54: =IFERROR(INDEX('BD Rendimientos'!G:G,MATCH("01.01.05|Clavos de acero 2.1/2” (Clavos de acero 2.1/2” (1 kilo))|Kg.|materiales",'BD Rendimientos'!L:L,0)),"") -> 0.5 | E54: =IFERROR(INDEX('BD Materiales'!D:D,MATCH("Clavos de acero 2.1/2” (Clavos de acero 2.1/2” (1 kilo))",'BD Materiales'!B:B,0)),"") -> 3.94 | F54: =IFERROR(D54*E54,"") -> 1.97 | K54: 0.5 | L54: 3.94 | M54: PU: cobertura única
B55: Clavos galvanizados 2'' | C55: Kg. | D55: =IFERROR(INDEX('BD Rendimientos'!G:G,MATCH("01.01.05|Clavos galvanizados 2''|Kg.|materiales",'BD Rendimientos'!L:L,0)),"") -> 2.3333333 | E55: =IFERROR(INDEX('BD Materiales'!D:D,MATCH("Clavos galvanizados 2''",'BD Materiales'!B:B,0)),"") -> 1.9257895 | F55: =IFERROR(D55*E55,"") -> 4.4935088 | G55: 2.5 | H55: 1.495 | I55: 1.5 | J55: 2.13 | K55: 3 | L55: 2.08
B56: Clavos galvanizados 2 1/2'' | C56: Kg. | D56: =IFERROR(INDEX('BD Rendimientos'!G:G,MATCH("01.01.05|Clavos galvanizados 2 1/2''|Kg.|materiales",'BD Rendimientos'!L:L,0)),"") -> 2.25 | E56: =IFERROR(INDEX('BD Materiales'!D:D,MATCH("Clavos galvanizados 2 1/2''",'BD Materiales'!B:B,0)),"") -> 1.8223333 | F56: =IFERROR(D56*E56,"") -> 4.10025 | G56: 2.5 | H56: 1.445 | K56: 2 | L56: 2.02
B57: Clavos Zinc 2 1/2"x9 (Caja 20kg (Clavos Zinc 2 1/2"x9 (Caja 20kg)) | C57: Kg. | D57: =IFERROR(INDEX('BD Rendimientos'!G:G,MATCH("01.01.05|Clavos Zinc 2 1/2""x9 (Caja 20kg (Clavos Zinc 2 1/2""x9 (Caja 20kg))|Kg.|materiales",'BD Rendimientos'!L:L,0)),"") -> 1.25 | E57: =IFERROR(INDEX('BD Materiales'!D:D,MATCH("Clavos Zinc 2 1/2""x9 (Caja 20kg (Clavos Zinc 2 1/2""x9 (Caja 20kg))",'BD Materiales'!B:B,0)),"") -> 3.125 | F57: =IFERROR(D57*E57,"") -> 3.90625 | I57: 0.5 | J57: 3.04 | K57: 2 | L57: 3.21 | M57: | Rend: Rendimiento disperso
B58: Cuartón 6 x 4 de eucalipto | C58: Uni. | D58: =IFERROR(INDEX('BD Rendimientos'!G:G,MATCH("01.01.05|Cuartón 6 x 4 de eucalipto|Uni.|materiales",'BD Rendimientos'!L:L,0)),"") -> 54 | E58: =IFERROR(INDEX('BD Materiales'!D:D,MATCH("Cuartón 6 x 4 de eucalipto",'BD Materiales'!B:B,0)),"") -> 2.15 | F58: =IFERROR(D58*E58,"") -> 116.1 | K58: 54 | L58: 2.15 | M58: PU: cobertura única
B59: Disco diamante segmentado 9" | C59: Uni. | D59: =IFERROR(INDEX('BD Rendimientos'!G:G,MATCH("01.01.05|Disco diamante segmentado 9""|Uni.|materiales",'BD Rendimientos'!L:L,0)),"") -> 1 | E59: =IFERROR(INDEX('BD Materiales'!D:D,MATCH("Disco diamante segmentado 9""",'BD Materiales'!B:B,0)),"") -> 5.35 | F59: =IFERROR(D59*E59,"") -> 5.35 | G59: 1 | H59: 5.59 | M59: PU: cobertura única
B60: Inodoro Guachimania | C60: Uni. | D60: =IFERROR(INDEX('BD Rendimientos'!G:G,MATCH("01.01.05|Inodoro Guachimania|Uni.|materiales",'BD Rendimientos'!L:L,0)),"") -> 1 | E60: =IFERROR(INDEX('BD Materiales'!D:D,MATCH("Inodoro Guachimania",'BD Materiales'!B:B,0)),"") -> 44 | F60: =IFERROR(D60*E60,"") -> 44 | I60: 1 | J60: 42.47 | K60: 1 | L60: 45.53
B61: Lavabo Guachimania | C61: Uni. | D61: =IFERROR(INDEX('BD Rendimientos'!G:G,MATCH("01.01.05|Lavabo Guachimania|Uni.|materiales",'BD Rendimientos'!L:L,0)),"") -> 1 | E61: =IFERROR(INDEX('BD Materiales'!D:D,MATCH("Lavabo Guachimania",'BD Materiales'!B:B,0)),"") -> 44 | F61: =IFERROR(D61*E61,"") -> 44 | I61: 1 | J61: 42.47 | K61: 1 | L61: 45.53
B62: Pingos de 2.5 mts | C62: Uni. | D62: =IFERROR(INDEX('BD Rendimientos'!G:G,MATCH("01.01.05|Pingos de 2.5 mts|Uni.|materiales",'BD Rendimientos'!L:L,0)),"") -> 8.5 | E62: =IFERROR(INDEX('BD Materiales'!D:D,MATCH("Pingos de 2.5 mts",'BD Materiales'!B:B,0)),"") -> 1.1206818 | F62: =IFERROR(D62*E62,"") -> 9.5257955 | I62: 6 | J62: 1.1 | K62: 11 | L62: 1.1
B63: Pingos de 3 mts. | C63: Uni. | D63: =IFERROR(INDEX('BD Rendimientos'!G:G,MATCH("01.01.05|Pingos de 3 mts.|Uni.|materiales",'BD Rendimientos'!L:L,0)),"") -> 24 | E63: =IFERROR(INDEX('BD Materiales'!D:D,MATCH("Pingos de 3 mts.",'BD Materiales'!B:B,0)),"") -> 1.2 | F63: =IFERROR(D63*E63,"") -> 28.8 | K63: 24 | L63: 1.2 | M63: PU: cobertura única
B64: Pingos de 4 mts. | C64: Uni. | D64: =IFERROR(INDEX('BD Rendimientos'!G:G,MATCH("01.01.05|Pingos de 4 mts.|Uni.|materiales",'BD Rendimientos'!L:L,0)),"") -> 4.5 | E64: =IFERROR(INDEX('BD Materiales'!D:D,MATCH("Pingos de 4 mts.",'BD Materiales'!B:B,0)),"") -> 5.16 | F64: =IFERROR(D64*E64,"") -> 23.22 | G64: 5 | H64: 6 | K64: 4 | L64: 4.32
B65: Pingos de 6 mts. | C65: Uni. | D65: =IFERROR(INDEX('BD Rendimientos'!G:G,MATCH("01.01.05|Pingos de 6 mts.|Uni.|materiales",'BD Rendimientos'!L:L,0)),"") -> 8.6666667 | E65: =IFERROR(INDEX('BD Materiales'!D:D,MATCH("Pingos de 6 mts.",'BD Materiales'!B:B,0)),"") -> 6.96 | F65: =IFERROR(D65*E65,"") -> 60.32 | G65: 10 | H65: 7.2 | I65: 4 | J65: 6.48 | K65: 12 | L65: 7.2
B66: Plastico Negro 1.5 mts (Plastico Negro 1.5 mts (2.20 mts x kg) (45 kilos)) | C66: rollo | D66: =IFERROR(INDEX('BD Rendimientos'!G:G,MATCH("01.01.05|Plastico Negro 1.5 mts (Plastico Negro 1.5 mts (2.20 mts x kg) (45 kilos))|rollo|materiales",'BD Rendimientos'!L:L,0)),"") -> 0.805 | E66: =IFERROR(INDEX('BD Materiales'!D:D,MATCH("Plastico Negro 1.5 mts (Plastico Negro 1.5 mts (2.20 mts x kg) (45 kilos))",'BD Materiales'!B:B,0)),"") -> 67.732222 | F66: =IFERROR(D66*E66,"") -> 54.524439 | I66: 1.2 | J66: 64.73 | K66: 0.41 | L66: 72.29
B67: Riel de eucalipto | C67: Uni. | D67: =IFERROR(INDEX('BD Rendimientos'!G:G,MATCH("01.01.05|Riel de eucalipto|Uni.|materiales",'BD Rendimientos'!L:L,0)),"") -> 18 | E67: =IFERROR(INDEX('BD Materiales'!D:D,MATCH("Riel de eucalipto",'BD Materiales'!B:B,0)),"") -> 1.81825 | F67: =IFERROR(D67*E67,"") -> 32.7285 | G67: 18 | H67: 1.8025 | I67: 6 | J67: 1.82 | K67: 23 | L67: 1.85 | M67: | Rend: Rendimiento disperso
B68: Tablas de Monte | C68: Uni. | D68: =IFERROR(INDEX('BD Rendimientos'!G:G,MATCH("01.01.05|Tablas de Monte|Uni.|materiales",'BD Rendimientos'!L:L,0)),"") -> 34.666667 | E68: =IFERROR(INDEX('BD Materiales'!D:D,MATCH("Tablas de Monte",'BD Materiales'!B:B,0)),"") -> 2.4034926 | F68: =IFERROR(D68*E68,"") -> 83.321077 | G68: 30 | H68: 2.3732 | I68: 32 | J68: 2.44 | K68: 42 | L68: 2.39
B69: Tablón Rustico | C69: Uni. | D69: =IFERROR(INDEX('BD Rendimientos'!G:G,MATCH("01.01.05|Tablón Rustico|Uni.|materiales",'BD Rendimientos'!L:L,0)),"") -> 2 | E69: =IFERROR(INDEX('BD Materiales'!D:D,MATCH("Tablón Rustico",'BD Materiales'!B:B,0)),"") -> 6.35 | F69: =IFERROR(D69*E69,"") -> 12.7 | G69: 2 | H69: 6.35 | M69: PU: cobertura única
B70: Tela Arpillera Verde 1.90m (Tela Arpillera Verde 1.90m (Rollo 100m)) | C70: rollo | D70: =IFERROR(INDEX('BD Rendimientos'!G:G,MATCH("01.01.05|Tela Arpillera Verde 1.90m (Tela Arpillera Verde 1.90m (Rollo 100m))|rollo|materiales",'BD Rendimientos'!L:L,0)),"") -> 1.3 | E70: =IFERROR(INDEX('BD Materiales'!D:D,MATCH("Tela Arpillera Verde 1.90m (Tela Arpillera Verde 1.90m (Rollo 100m))",'BD Materiales'!B:B,0)),"") -> 46.92 | F70: =IFERROR(D70*E70,"") -> 60.996 | G70: 1.3 | H70: 46.92 | M70: PU: cobertura única
B71: Zinc 2.40mts x 0.80 cm Cal.0.20 | C71: Uni. | D71: =IFERROR(INDEX('BD Rendimientos'!G:G,MATCH("01.01.05|Zinc 2.40mts x 0.80 cm Cal.0.20|Uni.|materiales",'BD Rendimientos'!L:L,0)),"") -> 2 | E71: =IFERROR(INDEX('BD Materiales'!D:D,MATCH("Zinc 2.40mts x 0.80 cm Cal.0.20",'BD Materiales'!B:B,0)),"") -> 4.185 | F71: =IFERROR(D71*E71,"") -> 8.37 | G71: 2 | H71: 4.185 | M71: PU: cobertura única
B72: Zinc 3.60mts x 0.8mts Cal.0.20 | C72: Uni. | D72: =IFERROR(INDEX('BD Rendimientos'!G:G,MATCH("01.01.05|Zinc 3.60mts x 0.8mts Cal.0.20|Uni.|materiales",'BD Rendimientos'!L:L,0)),"") -> 14 | E72: =IFERROR(INDEX('BD Materiales'!D:D,MATCH("Zinc 3.60mts x 0.8mts Cal.0.20",'BD Materiales'!B:B,0)),"") -> 7.5173333 | F72: =IFERROR(D72*E72,"") -> 105.24267 | G72: 16 | H72: 6.402 | I72: 12 | J72: 7.91 | K72: 14 | L72: 8.24
A73: MANO DE OBRA
B74: M. Guachimanía de obra, baños, vestidores de obra y otros provisionales | C74: Glb | D74: =IFERROR(INDEX('BD Rendimientos'!G:G,MATCH("01.01.05|M. Guachimanía de obra, baños, vestidores de obra y otros provisionales|Glb|mano_obra",'BD Rendimientos'!L:L,0)),"") -> 1 | E74: =IFERROR(INDEX('BD Mano de Obra'!D:D,MATCH("M. Guachimanía de obra, baños, vestidores de obra y otros provisionales",'BD Mano de Obra'!B:B,0)),"") -> 200 | F74: =IFERROR(D74*E74,"") -> 200 | G74: 1 | H74: 200 | I74: 1 | J74: 200 | K74: 1 | L74: 200
B75: COSTO UNITARIO APU ESTÁNDAR | C75: Glb | F75: =SUM(F47,F48,F49,F50,F51,F52,F53,F54,F55,F56,F57,F58,F59,F60,F61,F62,F63,F64,F65,F66,F67,F68,F69,F70,F71,F72,F74) -> 1282.3635 | H75: 3.0946341 | J75: 2.4544619 | L75: 0.93983156 | M75: CU observados →
A77: 01.01.08 | B77: Cerramiento provisional de zaram y pingos | C77: ml | D77: Cant/Rend | E77: P.Unit | F77: Subtotal | G77: Cant BF | H77: PU BF | I77: Cant PE | J77: PU PE | K77: Cant MF | L77: PU MF | M77: Observación
A78: MATERIALES
B79: Cemento Campeon HS 50KG | C79: qq | D79: =IFERROR(INDEX('BD Rendimientos'!G:G,MATCH("01.01.08|Cemento Campeon HS 50KG|qq|materiales",'BD Rendimientos'!L:L,0)),"") -> 0.0049920128 | E79: =IFERROR(INDEX('BD Materiales'!D:D,MATCH("Cemento Campeon HS 50KG",'BD Materiales'!B:B,0)),"") -> 6.7489473 | F79: =IFERROR(D79*E79,"") -> 0.033690831 | K79: 1 | L79: 6.76 | M79: PU: cobertura única
B80: Clavos galvanizados 2'' | C80: Kg. | D80: =IFERROR(INDEX('BD Rendimientos'!G:G,MATCH("01.01.08|Clavos galvanizados 2''|Kg.|materiales",'BD Rendimientos'!L:L,0)),"") -> 0.030673839 | E80: =IFERROR(INDEX('BD Materiales'!D:D,MATCH("Clavos galvanizados 2''",'BD Materiales'!B:B,0)),"") -> 1.9257895 | F80: =IFERROR(D80*E80,"") -> 0.059071357 | G80: 7.9 | H80: 1.59 | I80: 0.5 | J80: 2.3 | M80: | Rend: Rendimiento disperso
B81: Clavos galvanizados 2 1/2'' | C81: Kg. | D81: =IFERROR(INDEX('BD Rendimientos'!G:G,MATCH("01.01.08|Clavos galvanizados 2 1/2''|Kg.|materiales",'BD Rendimientos'!L:L,0)),"") -> 0.010940919 | E81: =IFERROR(INDEX('BD Materiales'!D:D,MATCH("Clavos galvanizados 2 1/2''",'BD Materiales'!B:B,0)),"") -> 1.8223333 | F81: =IFERROR(D81*E81,"") -> 0.019938001 | G81: 1.5 | H81: 1.71 | I81: 5 | J81: 1.94 | K81: 1.5 | L81: 1.96 | M81: | Rend: Rendimiento disperso
B82: Cuartón 6 x 4 de eucalipto | C82: Uni. | D82: =IFERROR(INDEX('BD Rendimientos'!G:G,MATCH("01.01.08|Cuartón 6 x 4 de eucalipto|Uni.|materiales",'BD Rendimientos'!L:L,0)),"") -> 0.38657914 | E82: =IFERROR(INDEX('BD Materiales'!D:D,MATCH("Cuartón 6 x 4 de eucalipto",'BD Materiales'!B:B,0)),"") -> 2.15 | F82: =IFERROR(D82*E82,"") -> 0.83114515 | G82: 53 | H82: 2.15 | M82: PU: cobertura única
B83: Pingos de 2.5 mts | C83: Uni. | D83: =IFERROR(INDEX('BD Rendimientos'!G:G,MATCH("01.01.08|Pingos de 2.5 mts|Uni.|materiales",'BD Rendimientos'!L:L,0)),"") -> 0.16046681 | E83: =IFERROR(INDEX('BD Materiales'!D:D,MATCH("Pingos de 2.5 mts",'BD Materiales'!B:B,0)),"") -> 1.1206818 | F83: =IFERROR(D83*E83,"") -> 0.17983224 | G83: 22 | H83: 1.17 | I83: 35 | J83: 1.1 | K83: 15 | L83: 1.1 | M83: | Rend: Rendimiento disperso
B84: Pingos de 3 mts. | C84: Uni. | D84: =IFERROR(INDEX('BD Rendimientos'!G:G,MATCH("01.01.08|Pingos de 3 mts.|Uni.|materiales",'BD Rendimientos'!L:L,0)),"") -> 0.21479673 | E84: =IFERROR(INDEX('BD Materiales'!D:D,MATCH("Pingos de 3 mts.",'BD Materiales'!B:B,0)),"") -> 1.2 | F84: =IFERROR(D84*E84,"") -> 0.25775608 | G84: 50 | H84: 1.2 | K84: 13 | L84: 1.2 | M84: | Rend: Rendimiento disperso
B85: Tela Arpillera Verde 1.90m (Tela Arpillera Verde 1.90m (Rollo 100m)) | C85: rollo | D85: =IFERROR(INDEX('BD Rendimientos'!G:G,MATCH("01.01.08|Tela Arpillera Verde 1.90m (Tela Arpillera Verde 1.90m (Rollo 100m))|rollo|materiales",'BD Rendimientos'!L:L,0)),"") -> 0.45183403 | E85: =IFERROR(INDEX('BD Materiales'!D:D,MATCH("Tela Arpillera Verde 1.90m (Tela Arpillera Verde 1.90m (Rollo 100m))",'BD Materiales'!B:B,0)),"") -> 46.92 | F85: =IFERROR(D85*E85,"") -> 21.200053 | G85: 0.7 | H85: 46.93 | K85: 180 | L85: 0.61 | M85: PU: Revisar — desv 7593% | Rend: Rendimiento disperso
B86: Tela Verde UV 2.00 mts. (Tela Verde UV 2.00 mts) | C86: mts. | D86: =IFERROR(INDEX('BD Rendimientos'!G:G,MATCH("01.01.08|Tela Verde UV 2.00 mts. (Tela Verde UV 2.00 mts)|mts.|materiales",'BD Rendimientos'!L:L,0)),"") -> 0.34944089 | E86: =IFERROR(INDEX('BD Materiales'!D:D,MATCH("Tela Verde UV 2.00 mts. (Tela Verde UV 2.00 mts)",'BD Materiales'!B:B,0)),"") -> 0.56 | F86: =IFERROR(D86*E86,"") -> 0.1956869 | K86: 70 | L86: 0.56 | M86: PU: cobertura única
B87: Tela Zaran Verde 2.10m (Tela Zaran Verde 2.10m (Rollo 100m)) | C87: ml | D87: =IFERROR(INDEX('BD Rendimientos'!G:G,MATCH("01.01.08|Tela Zaran Verde 2.10m (Tela Zaran Verde 2.10m (Rollo 100m))|ml|materiales",'BD Rendimientos'!L:L,0)),"") -> 1.1176514 | E87: =IFERROR(INDEX('BD Materiales'!D:D,MATCH("Tela Zaran Verde 2.10m (Tela Zaran Verde 2.10m (Rollo 100m))",'BD Materiales'!B:B,0)),"") -> 0.64426667 | F87: =IFERROR(D87*E87,"") -> 0.72006557 | I87: 150 | J87: 0.64426667 | M87: PU: cobertura única
B88: Tiras de 3x3 | C88: Uni. | D88: =IFERROR(INDEX('BD Rendimientos'!G:G,MATCH("01.01.08|Tiras de 3x3|Uni.|materiales",'BD Rendimientos'!L:L,0)),"") -> 0.27627159 | E88: =IFERROR(INDEX('BD Materiales'!D:D,MATCH("Tiras de 3x3",'BD Materiales'!B:B,0)),"") -> 1.535 | F88: =IFERROR(D88*E88,"") -> 0.42407689 | G88: 40 | H88: 1.68 | I88: 35 | J88: 1.39
A89: MANO DE OBRA
B90: M. Cerramiento provisional de zaram y pingos | C90: ml | D90: =IFERROR(INDEX('BD Rendimientos'!G:G,MATCH("01.01.08|M. Cerramiento provisional de zaram y pingos|ml|mano_obra",'BD Rendimientos'!L:L,0)),"") -> 1 | E90: =IFERROR(INDEX('BD Mano de Obra'!D:D,MATCH("M. Cerramiento provisional de zaram y pingos",'BD Mano de Obra'!B:B,0)),"") -> 2.14 | F90: =IFERROR(D90*E90,"") -> 2.14 | G90: 137.1 | H90: 2.14 | I90: 134.21 | J90: 2.14 | K90: 200.32 | L90: 2.14
B91: COSTO UNITARIO APU ESTÁNDAR | C91: ml | F91: =SUM(F79,F80,F81,F82,F83,F84,F85,F86,F87,F88,F90) -> 26.061316 | H91: 4.4366229 | J91: 3.5902645 | L91: 3.092476 | M91: CU observados →
A93: 01.01.09 | B93: Desmontaje de guachimanía de obra, baños, vestidores de obra y otros provisionales | C93: Glb | D93: Cant/Rend | E93: P.Unit | F93: Subtotal | G93: Cant BF | H93: PU BF | I93: Cant PE | J93: PU PE | K93: Cant MF | L93: PU MF | M93: Rubro con cobertura única
A94: MANO DE OBRA
B95: M. Desmontaje de guachimanía de obra, baños, vestidores de obra y otros provisionales | C95: Glb | D95: =IFERROR(INDEX('BD Rendimientos'!G:G,MATCH("01.01.09|M. Desmontaje de guachimanía de obra, baños, vestidores de obra y otros provisionales|Glb|mano_obra",'BD Rendimientos'!L:L,0)),"") -> 1 | E95: =IFERROR(INDEX('BD Mano de Obra'!D:D,MATCH("M. Desmontaje de guachimanía de obra, baños, vestidores de obra y otros provisionales",'BD Mano de Obra'!B:B,0)),"") -> 89.29 | F95: =IFERROR(D95*E95,"") -> 89.29 | K95: 1 | L95: 89.29 | M95: PU: cobertura única
B96: COSTO UNITARIO APU ESTÁNDAR | C96: Glb | F96: =SUM(F95) -> 89.29 | L96: 89.29 | M96: CU observados →
A98: 02. MOVIMIENTOS DE TIERRA
A99: a) PLATAFORMAS
A100: 02.01.01 | B100: Excavación mecánica en banco para conformación de plataforma | C100: m3 | D100: Cant/Rend | E100: P.Unit | F100: Subtotal | G100: Cant BF | H100: PU BF | I100: Cant PE | J100: PU PE | K100: Cant MF | L100: PU MF | M100: Observación
A101: EQUIPO
B102: M. Excavación mecánica en banco para conformación de plataforma | C102: m3 | D102: =IFERROR(INDEX('BD Rendimientos'!G:G,MATCH("02.01.01|M. Excavación mecánica en banco para conformación de plataforma|m3|equipo",'BD Rendimientos'!L:L,0)),"") -> 1 | E102: =IFERROR(INDEX('BD Equipo'!D:D,MATCH("M. Excavación mecánica en banco para conformación de plataforma",'BD Equipo'!B:B,0)),"") -> 1.16 | F102: =IFERROR(D102*E102,"") -> 1.16 | I102: 618 | J102: 1.25 | K102: 3661.87 | L102: 1.07
B103: COSTO UNITARIO APU ESTÁNDAR | C103: m3 | F103: =SUM(F102) -> 1.16 | J103: 1.25 | L103: 1.07 | M103: CU observados →
A105: a) PLATAFORMAS
A106: 02.01.02 | B106: Transporte desalojo de material a botadero | C106: m3 | D106: Cant/Rend | E106: P.Unit | F106: Subtotal | G106: Cant BF | H106: PU BF | I106: Cant PE | J106: PU PE | K106: Cant MF | L106: PU MF | M106: Observación
A107: EQUIPO
B108: M. Transporte desalojo de material a botadero | C108: m3 | D108: =IFERROR(INDEX('BD Rendimientos'!G:G,MATCH("02.01.02|M. Transporte desalojo de material a botadero|m3|equipo",'BD Rendimientos'!L:L,0)),"") -> 1 | E108: =IFERROR(INDEX('BD Equipo'!D:D,MATCH("M. Transporte desalojo de material a botadero",'BD Equipo'!B:B,0)),"") -> 20.285 | F108: =IFERROR(D108*E108,"") -> 20.285 | I108: 48.89 | J108: 36.78 | K108: 912.76 | L108: 3.79 | M108: PU: Revisar — desv 870%
B109: COSTO UNITARIO APU ESTÁNDAR | C109: m3 | F109: =SUM(F108) -> 20.285 | J109: 36.78 | L109: 3.79 | M109: CU observados →
...

Sheet Resumen CU
A1: RESUMEN COMPARATIVO — COSTO UNITARIO POR APU
A2: 106 rubros · CU observado en cada obra vs. CU estándar propuesto
A4: Código | B4: Descripción | C4: Unidad | D4: CU BUENO FERRO | E4: CU PABLO ESPINOSA | F4: CU MUÑOZ FREILE | G4: CU ESTÁNDAR | H4: Cobertura | I4: Desv Max % | J4: Notas
A5: 01. PRELIMINARES
A6: 01.01.01 | B6: Replanteo Topográfico Ejes Estructurales y movimiento tierras | C6: Glb | D6: 0.73757645 | E6: 0.48171491 | F6: 0.1260928 | G6: ='APU Estándar'!F10 -> 160 | H6: 46084 | I6: 4.85 | J6: Tiene insumos con dispersión (ver hoja Reporte)
A7: 01.01.02 | B7: Replanteo Y Nivelación | C7: m2 | D7: 1.4155223 | E7: 1.1585613 | F7: 0.97282133 | G7: ='APU Estándar'!F32 -> 1.5074793 | H7: 46084 | I7: 0.46 | J7: Tiene insumos con dispersión (ver hoja Reporte)
A8: 01.01.03 | B8: Instalaciones eléctricas provisionales | C8: Glb | D8: 0.92197056 | E8: 1.2042873 | F8: 0.31523201 | G8: ='APU Estándar'!F38 -> 300 | H8: 0/3 | I8: 2.82
A9: 01.01.04 | B9: Instalaciones hidrosanitarias provisionales | C9: Glb | D9: 300 | E9: 300 | F9: 300 | G9: ='APU Estándar'!F43 -> 300 | H9: 0/3 | I9: 0
A10: 01.01.05 | B10: Guachimanía de obra, baños, vestidores de obra y otros provisionales | C10: Glb | D10: 3.0946341 | E10: 2.4544619 | F10: 0.93983156 | G10: ='APU Estándar'!F75 -> 1282.3635 | H10: 46084 | I10: 2.29 | J10: Tiene insumos con dispersión (ver hoja Reporte)
A11: 01.01.08 | B11: Cerramiento provisional de zaram y pingos | C11: ml | D11: 4.4366229 | E11: 3.5902645 | F11: 3.092476 | G11: ='APU Estándar'!F91 -> 26.061316 | H11: 46084 | I11: 0.43 | J11: Tiene insumos con dispersión (ver hoja Reporte)
A12: 01.01.09 | B12: Desmontaje de guachimanía de obra, baños, vestidores de obra y otros provisionales | C12: Glb | F12: 89.29 | G12: ='APU Estándar'!F96 -> 89.29 | H12: 46025 | J12: Cobertura única · Tiene insumos con dispersión (ver hoja Reporte)
A13: 02. MOVIMIENTOS DE TIERRA
A14: 02.01.01 | B14: Excavación mecánica en banco para conformación de plataforma | C14: m3 | E14: 1.25 | F14: 1.07 | G14: ='APU Estándar'!F103 -> 1.16 | H14: 46056 | I14: 0.17
A15: 02.01.02 | B15: Transporte desalojo de material a botadero | C15: m3 | E15: 36.78 | F15: 3.79 | G15: ='APU Estándar'!F109 -> 20.285 | H15: 46056 | I15: 8.7 | J15: Tiene insumos con dispersión (ver hoja Reporte)
A16: 02.01.03 | B16: Relleno compactado | C16: m3 | D16: 3 | E16: 3 | F16: 2.65 | G16: ='APU Estándar'!F115 -> 2.8833333 | H16: 46084 | I16: 0.13
A17: 02.01.04 | B17: Desbroce de Capa Vegetal | C17: m2 | D17: 0.65 | E17: 0.65 | F17: 0.58 | G17: ='APU Estándar'!F121 -> 0.62666667 | H17: 46084 | I17: 0.12
A18: 02.01.05 | B18: Rasanteo Y Conformación Manual De Plataformas | C18: m2 | D18: 0.7 | E18: 0.7 | F18: 0.74052312 | G18: ='APU Estándar'!F129 -> 0.74052312 | H18: 46084 | I18: 0.06 | J18: Tiene insumos con dispersión (ver hoja Reporte)
A19: 02.01.06 | B19: Transporte de material para relleno | C19: m3 | D19: 3.92 | G19: ='APU Estándar'!F135 -> 3.92 | H19: 46025 | J19: Cobertura única · Tiene insumos con dispersión (ver hoja Reporte)
A20: 02.01.07 | B20: Pruebas de compactación en plataformas | C20: Glb | D20: 350 | E20: 350 | F20: 500 | G20: ='APU Estándar'!F141 -> 400 | H20: 46084 | I20: 0.43
A21: 02.02.01 | B21: Excavaciones Y Relleno Compactado Para Instalaciones Hidrosanitarias | C21: ml | E21: 3.9 | F21: 3.9 | G21: ='APU Estándar'!F147 -> 3.9 | H21: 46056 | I21: 0
A22: 02.02.02 | B22: Excavaciones Y Relleno Compactado Para Instalaciones Eléctricas | C22: ml | E22: 3.9 | G22: ='APU Estándar'!F153 -> 3.9 | H22: 46025 | J22: Cobertura única · Tiene insumos con dispersión (ver hoja Reporte)
A23: 02.02.03 | B23: Cajas De Revisión H= 1,50x1,00x1,00m | C23: Und | G23: ='APU Estándar'!F157 -> 0 | H23: 0/3
A24: 02.02.04 | B24: Excavaciones Para Plintos Y Cimientos ( Maquina Y Perfilado Manual) | C24: m3 | D24: 14.251992 | E24: 7.5 | F24: 11.365149 | G24: ='APU Estándar'!F165 -> 12.641903 | H24: 46084 | I24: 0.9
A25: 02.02.05 | B25: Relleno Compactado Con Material Local (Plintos Y Cimientos) | C25: m3 | D25: 15.329419 | E25: 13.622624 | F25: 10.157457 | G25: ='APU Estándar'!F175 -> 13.076102 | H25: 46084 | I25: 0.51 | J25: Tiene insumos con dispersión (ver hoja Reporte)
A26: 02.02.06 | B26: Perfilado de taludes Muros (Incluye plástico polietileno) | C26: m2 | F26: 3.4999173 | G26: ='APU Estándar'!F187 -> 3.4203637 | H26: 46025 | J26: Cobertura única · Tiene insumos con dispersión (ver hoja Reporte)
A27: 03. ESTRUCTURA
A28: 03.01.01 | B28: Malla De Refuerzo 6*15 | C28: m2 | D28: 3.2280692 | E28: 3.0403732 | F28: 2.7852166 | G28: ='APU Estándar'!F200 -> 3.0490068 | H28: 46084 | I28: 0.16 | J28: Tiene insumos con dispersión (ver hoja Reporte)
A29: 03.01.02 | B29: Hierro 8 Mm X 12 M | C29: Kg. | D29: 1.3875105 | G29: ='APU Estándar'!F208 -> 1.3875105 | H29: 46025 | J29: Cobertura única · Tiene insumos con dispersión (ver hoja Reporte)
A30: 03.01.03 | B30: Hierro 10 Mm X 12 M | C30: Kg. | D30: 1.3946658 | E30: 1.1817746 | F30: 1.1264966 | G30: ='APU Estándar'!F223 -> 1.2456833 | H30: 46084 | I30: 0.24 | J30: Tiene insumos con dispersión (ver hoja Reporte)
A31: 03.01.04 | B31: Hierro 12 Mm X 12 M | C31: Kg. | D31: 1.552589 | E31: 1.469208 | F31: 1.8292711 | G31: ='APU Estándar'!F238 -> 1.6140944 | H31: 46084 | I31: 0.25 | J31: Tiene insumos con dispersión (ver hoja Reporte)
A32: 03.01.05 | B32: Hierro 14 Mm X 12 M | C32: Kg. | D32: 1.2175225 | E32: 1.2472578 | F32: 0.41154082 | G32: ='APU Estándar'!F250 -> 1.2229676 | H32: 46084 | I32: 2.03 | J32: Tiene insumos con dispersión (ver hoja Reporte)
A33: 03.01.06 | B33: Hierro 16 Mm X 12 M | C33: Kg. | D33: 1.414114 | E33: 1.5286974 | F33: 1.9208546 | G33: ='APU Estándar'!F263 -> 1.6492449 | H33: 46084 | I33: 0.36 | J33: Tiene insumos con dispersión (ver hoja Reporte)
A34: 03.01.07 | B34: Hierro 18 Mm X 12 M | C34: Kg. | E34: 1.4083458 | F34: 1.4240207 | G34: ='APU Estándar'!F271 -> 1.4161791 | H34: 46056 | I34: 0.01
A35: 03.02.01 | B35: Plástico Polietileno 2 Capas | C35: m2 | D35: 0.84771182 | E35: 0.80298195 | F35: 0.53723371 | G35: ='APU Estándar'!F283 -> 1.1723939 | H35: 46084 | I35: 0.58 | J35: Tiene insumos con dispersión (ver hoja Reporte)
A36: 03.02.02 | B36: Contrapiso De Hormigón Planta Baja F'c=210 Kg/Cm² | C36: m2 | D36: 17.060077 | E36: 19.16252 | F36: 17.817665 | G36: ='APU Estándar'!F314 -> 19.648491 | H36: 46084 | I36: 0.12 | J36: Tiene insumos con dispersión (ver hoja Reporte)
A37: 03.02.03 | B37: Juntas de dilatación en contrapiso | C37: m | E37: 7.0347518 | G37: ='APU Estándar'!F322 -> 6.7753546 | H37: 46025 | J37: Cobertura única · Tiene insumos con dispersión (ver hoja Reporte)
A38: 03.03.01 | B38: Hormigón En Replantillo F'c=180kg/Cm² | C38: m3 | D38: 82.378475 | E38: 57.001845 | F38: 29.869281 | G38: ='APU Estándar'!F332 -> 60.760626 | H38: 46084 | I38: 1.76 | J38: Tiene insumos con dispersión (ver hoja Reporte)
A39: 03.03.02 | B39: Hormigón En Plintos F'c=210kg/Cm² | C39: m3 | D39: 113.62364 | E39: 113.786 | F39: 112.79382 | G39: ='APU Estándar'!F343 -> 113.40115 | H39: 46084 | I39: 0.01
A40: 03.03.03 | B40: Hormigón En Cadenas F'c=210kg/Cm² | C40: m3 | D40: 117.59149 | E40: 34.417333 | F40: 112.10639 | G40: ='APU Estándar'!F355 -> 116.40575 | H40: 46084 | I40: 2.42 | J40: Tiene insumos con dispersión (ver hoja Reporte)
A41: 03.03.04 | B41: Hormigón En Muros F'c=210kg/Cm² | C41: m3 | D41: 133.15651 | F41: 114.09981 | G41: ='APU Estándar'!F372 -> 94.736132 | H41: 46056 | I41: 0.17 | J41: Tiene insumos con dispersión (ver hoja Reporte)
A42: 03.03.05 | B42: Hormigón Premezclado En Columnas F'c=210kg/Cm² CABEZALES | C42: m3 | D42: 78.033077 | E42: 110.223 | F42: 139.11429 | G42: ='APU Estándar'!F388 -> 150.20853 | H42: 46084 | I42: 0.78 | J42: Tiene insumos con dispersión (ver hoja Reporte)
A43: 03.03.06 | B43: Hormigón Premezclado En Columnas F'c=210kg/Cm² COLUMNAS | C43: m3 | D43: 110.73528 | E43: 102.10379 | F43: 382.378 | G43: ='APU Estándar'!F406 -> 152.40665 | H43: 46084 | I43: 2.74 | J43: Tiene insumos con dispersión (ver hoja Reporte)
A44: 03.03.07 | B44: Hormigón Premezclado En Vigas F'c=210kg/Cm² | C44: m3 | D44: 125.76333 | E44: 116.94305 | G44: ='APU Estándar'!F429 -> 126.3839 | H44: 46056 | I44: 0.08 | J44: Tiene insumos con dispersión (ver hoja Reporte)
A45: 03.03.08 | B45: Hormigón En Losa De Entrepiso F'c=210kg/Cm² | C45: m3 | D45: 90.225789 | E45: 93.93239 | F45: 115.41274 | G45: ='APU Estándar'!F447 -> 103.28924 | H45: 46084 | I45: 0.28 | J45: Tiene insumos con dispersión (ver hoja Reporte)
A46: 03.03.09 | B46: Hormigón En Cubierta Plana F'c=210kg/Cm² | C46: m3 | D46: 103.11344 | E46: 68.681954 | G46: ='APU Estándar'!F467 -> 90.201551 | H46: 46056 | I46: 0.5 | J46: Tiene insumos con dispersión (ver hoja Reporte)
A47: 03.03.11 | B47: Hormigón en dintel descolgado perimetral | C47: ml | D47: 6.5793727 | E47: 4.25 | G47: ='APU Estándar'!F482 -> 6.5580859 | H47: 46056 | I47: 0.55 | J47: Tiene insumos con dispersión (ver hoja Reporte)
A48: 03.03.15 | B48: Pruebas de laboratorio | C48: Glb | D48: 60 | E48: 40 | F48: 80 | G48: ='APU Estándar'!F488 -> 60 | H48: 46084 | I48: 1
A49: 03.03.21 | B49: Hormigón en detalle tipo Vigueta | C49: m3 | E49: 58.989975 | G49: ='APU Estándar'!F498 -> 59.914443 | H49: 46025 | J49: Cobertura única · Tiene insumos con dispersión (ver hoja Reporte)
A50: 03.03.22 | B50: Hormigón de nivelación de placas metálicas | C50: m3 | E50: 15 | G50: ='APU Estándar'!F504 -> 15 | H50: 46025 | J50: Cobertura única · Tiene insumos con dispersión (ver hoja Reporte)
A51: 04. ENCOFRADOS
A52: 04.01.01 | B52: Encofrado y Desencofrado Columnas Rectangulares | C52: m2 | D52: 13.89 | E52: 9.93 | F52: 9.93 | G52: ='APU Estándar'!F510 -> 11.25 | H52: 46084 | I52: 0.4
A53: 04.01.01.01 | B53: Encofrado y Desencofrado Columnas Circulares | C53: m2 | D53: 25.09 | G53: ='APU Estándar'!F515 -> 25.09 | H53: 46025 | J53: Cobertura única · Tiene insumos con dispersión (ver hoja Reporte)
A54: 04.01.02 | B54: Encofrado y Desencofrado de Vigas | C54: m2 | D54: 25.87 | E54: 11.166285 | F54: 11.5 | G54: ='APU Estándar'!F523 -> 11.666108 | H54: 46084 | I54: 1.32 | J54: Tiene insumos con dispersión (ver hoja Reporte)
A55: 04.01.03 | B55: Encofrado y Desencofrado de Losa | C55: m2 | E55: 11.5 | G55: ='APU Estándar'!F528 -> 12.565 | H55: 46025 | J55: Cobertura única · Tiene insumos con dispersión (ver hoja Reporte)
A56: 04.01.05 | B56: Encofrado y Desencofrado Losa Perimetral | C56: ml | D56: 3.85 | E56: 3.88 | F56: 3.88 | G56: ='APU Estándar'!F533 -> 3.87 | H56: 46084 | I56: 0.01
A57: 04.01.06 | B57: Encofrado y Desencofrado Muros | C57: m2 | D57: 12.77 | F57: 9.8 | G57: ='APU Estándar'!F538 -> 11.285 | H57: 46056 | I57: 0.3
A58: 04.01.07 | B58: Apuntalamiento de losa deck metálico | C58: m2 | D58: 1.9 | E58: 1.36 | F58: 1.36 | G58: ='APU Estándar'!F543 -> 1.54 | H58: 46084 | I58: 0.4
A59: 04.01.08 | B59: Encofrado dintel descolgado perimetral | C59: ml | D59: 6.7875216 | E59: 34.416762 | F59: 6.5 | G59: ='APU Estándar'!F558 -> 31.842389 | H59: 46084 | I59: 4.29 | J59: Tiene insumos con dispersión (ver hoja Reporte)
A60: 05. MAMPOSTERÍA
A61: 05.01.01 | B61: Mampostería De Bloque E=20cm | C61: m2 | D61: 16.034281 | E61: 8.9156209 | F61: 12.327992 | G61: ='APU Estándar'!F576 -> 13.118032 | H61: 46084 | I61: 0.8 | J61: Tiene insumos con dispersión (ver hoja Reporte)
A62: 05.01.02 | B62: Mampostería De Bloque E=15 Cm | C62: m2 | D62: 13.507909 | E62: 11.479396 | F62: 10.466325 | G62: ='APU Estándar'!F594 -> 11.880469 | H62: 46084 | I62: 0.29 | J62: Tiene insumos con dispersión (ver hoja Reporte)
A63: 05.01.03 | B63: Mampostería De Bloque E=10 Cm | C63: m2 | D63: 12.834391 | E63: 10.445438 | F63: 13.674655 | G63: ='APU Estándar'!F610 -> 12.923072 | H63: 46084 | I63: 0.31 | J63: Tiene insumos con dispersión (ver hoja Reporte)
A64: 05.01.05 | B64: Dinteles De Hormigón F'c = 180 Kg/Cm2 | C64: m | D64: 21.224618 | E64: 12.424993 | F64: 23.190336 | G64: ='APU Estándar'!F646 -> 23.357449 | H64: 46084 | I64: 0.87 | J64: Tiene insumos con dispersión (ver hoja Reporte)
A65: 05.01.06 | B65: Arrostramiento Vertical de Mampostería | C65: ml | D65: 13.309729 | E65: 14.7984 | G65: ='APU Estándar'!F683 -> 16.547392 | H65: 46056 | I65: 0.11 | J65: Tiene insumos con dispersión (ver hoja Reporte)
A66: 05.01.07 | B66: Alfeizar En Ventana | C66: ml | D66: 14.397043 | E66: 15.246263 | G66: ='APU Estándar'!F708 -> 16.067098 | H66: 46056 | I66: 0.06 | J66: Tiene insumos con dispersión (ver hoja Reporte)
A67: 05.01.08 | B67: Alfeizar En Antepecho | C67: ml | E67: 2.8 | G67: ='APU Estándar'!F713 -> 2.8 | H67: 46025 | J67: Cobertura única · Tiene insumos con dispersión (ver hoja Reporte)
A68: 05.01.09 | B68: Bordillo De Terrazas | C68: ml | D68: 6.970625 | E68: 8.3483852 | F68: 7.4620174 | G68: ='APU Estándar'!F726 -> 8.012319 | H68: 46084 | I68: 0.2 | J68: Tiene insumos con dispersión (ver hoja Reporte)
A69: 05.01.10 | B69: Nicho Para Baños y lavavajillas | C69: Und | D69: 28.945 | E69: 28.158105 | F69: 31.96915 | G69: ='APU Estándar'!F738 -> 33.135479 | H69: 46084 | I69: 0.14 | J69: Tiene insumos con dispersión (ver hoja Reporte)
A70: 05.01.11 | B70: Ducha Rehundida | C70: m2 | D70: 17.453893 | E70: 17.334 | F70: 13.26 | G70: ='APU Estándar'!F746 -> 17.935867 | H70: 46084 | I70: 0.32 | J70: Tiene insumos con dispersión (ver hoja Reporte)
A71: 05.01.12 | B71: 05.01.14 Volumen para medidores (Volumen para medidores de agua y luz) | C71: Und. | F71: 142.1 | G71: ='APU Estándar'!F754 -> 0 | H71: 0/3 | J71: Tiene insumos con dispersión (ver hoja Reporte)
A72: 05.01.15 | B72: Forrado de columnas metálicas | C72: m2 | E72: 4.2180051 | F72: 5.3626911 | G72: ='APU Estándar'!F767 -> 5.5439144 | H72: 46056 | I72: 0.27 | J72: Tiene insumos con dispersión (ver hoja Reporte)
A73: 06. ENLUCIDOS
A74: 06.01.01 | B74: Enlucido De Fachada | C74: m2 | D74: 7.99 | E74: 6.8 | F74: 7.6 | G74: ='APU Estándar'!F773 -> 7.4633333 | H74: 46084 | I74: 0.18
A75: 06.01.03 | B75: Enlucido De Fajas Exteriores | C75: ml | D75: 3.4 | E75: 3.1 | G75: ='APU Estándar'!F778 -> 3.25 | H75: 46056 | I75: 0.1
A76: 06.01.04 | B76: Enlucido De Filos Exteriores | C76: ml | D76: 1.4 | E76: 1.1 | G76: ='APU Estándar'!F783 -> 0 | H76: 0/3 | I76: 0.27
A77: 06.01.05 | B77: Enlucido Vertical Interior | C77: m2 | D77: 5.02 | E77: 4.8 | F77: 4.85 | G77: ='APU Estándar'!F788 -> 4.89 | H77: 46084 | I77: 0.05
A78: 06.01.06 | B78: Enlucido De Fajas Interiores | C78: ml | D78: 3.1 | E78: 2.9 | G78: ='APU Estándar'!F793 -> 3 | H78: 46056 | I78: 0.07
A79: 06.01.07 | B79: Enlucido De Filos Interiores | C79: ml | D79: 1.6 | E79: 1.3 | G79: ='APU Estándar'!F798 -> 1.45 | H79: 46056 | I79: 0.23
A80: 06.01.08 | B80: Masillado De Piso A Máquina | C80: m2 | D80: 1.2214526 | E80: 1.1428648 | F80: 2.7693821 | G80: ='APU Estándar'!F815 -> 2.4681998 | H80: 46084 | I80: 1.42 | J80: Tiene insumos con dispersión (ver hoja Reporte)
A81: 06.01.09 | B81: Picado Y Corchado | C81: ml | D81: 2.9160509 | E81: 1.2208 | F81: 1.4102274 | G81: ='APU Estándar'!F833 -> 2.5235102 | H81: 46084 | I81: 1.39 | J81: Tiene insumos con dispersión (ver hoja Reporte)
A82: 06.01.10 | B82: Goterones - Medias Cañas | C82: ml | D82: 1.5 | E82: 1.26 | F82: 1.26 | G82: ='APU Estándar'!F838 -> 1.34 | H82: 46084 | I82: 0.19
A83: 06.01.13 | B83: Enlucido Exterior Terminado Hormigón Visto | C83: m2 | E83: 3.1 | F83: 4.8 | G83: ='APU Estándar'!F843 -> 3.95 | H83: 46056 | I83: 0.55
A84: 06.01.15 | B84: Masillado De Piso A Máquina Con Endurecedor | C84: m2 | D84: 5.4 | G84: ='APU Estándar'!F848 -> 5.4 | H84: 46025 | J84: Cobertura única · Tiene insumos con dispersión (ver hoja Reporte)
A85: 07. CUBIERTAS
A86: 07.01.05 | B86: Cubierta de fibrocemento (Incluye capa super K) | C86: m2 | E86: 44.839946 | F86: 47.898853 | G86: ='APU Estándar'!F869 -> 47.958537 | H86: 46056 | I86: 0.07 | J86: Tiene insumos con dispersión (ver hoja Reporte)
A87: 08. REVESTIMIENTOS PISOS, PAREDES
A88: 08.01.10 | B88: Plástico Negro Para Protección De Terminados | C88: m2 | E88: 3.3897417 | F88: 0.37686586 | G88: ='APU Estándar'!F884 -> 2.1253283 | H88: 46056 | I88: 7.99 | J88: Tiene insumos con dispersión (ver hoja Reporte)
A89: 13. VARIOS
A90: 13.01.02 | B90: Limpieza Provisional (Durante la obra Material Y Personal) | C90: Glb | D90: 250.295 | E90: 1092.47 | F90: 1123.0059 | G90: ='APU Estándar'!F917 -> 1152.1419 | H90: 46084 | I90: 3.49 | J90: Tiene insumos con dispersión (ver hoja Reporte)
A91: 13.01.03 | B91: Limpieza Y Desalojo De Escombros + tickets emgirs | C91: Viaje | D91: 50.505 | E91: 74.809524 | F91: 53.325996 | G91: ='APU Estándar'!F925 -> 55.107649 | H91: 46084 | I91: 0.48 | J91: Tiene insumos con dispersión (ver hoja Reporte)
A92: 13.01.04 | B92: Limpieza Final de la Obra previo a la Entrega | C92: m2 | G92: ='APU Estándar'!F936 -> 0 | H92: 0/3 | J92: Tiene insumos con dispersión (ver hoja Reporte)
A93: 13.01.05 | B93: Protección Personal | C93: Glb | G93: ='APU Estándar'!F947 -> 0 | H93: 0/3 | J93: Tiene insumos con dispersión (ver hoja Reporte)
A94: 13.01.09 | B94: Herramientas de obra | C94: Glb | D94: 0.1660205 | E94: 4.3005901 | F94: 1.8038942 | G94: ='APU Estándar'!F980 -> 5753.4684 | H94: 46056 | I94: 24.9 | J94: Tiene insumos con dispersión (ver hoja Reporte)
A95: 13.01.12 | B95: Guachimanía de obra | C95: Mes | D95: 172.5 | G95: ='APU Estándar'!F985 -> 0 | H95: 0/3 | J95: Tiene insumos con dispersión (ver hoja Reporte)
A96: 13.01.14 | B96: Rejilla Metálilca de 2" | C96: Und | E96: 107.1 | G96: ='APU Estándar'!F990 -> 0 | H96: 0/3 | J96: Tiene insumos con dispersión (ver hoja Reporte)
A97: 13.01.18 | B97: Rejilla con Trampa para Ducha | C97: Und | E97: 101.5 | G97: ='APU Estándar'!F995 -> 0 | H97: 0/3 | J97: Tiene insumos con dispersión (ver hoja Reporte)
A98: 14. SERVICIOS BASICOS EN FASE DE CONSTRUCCION
A99: 14.01.01 | B99: Servicio de Agua Potable | C99: mes | G99: ='APU Estándar'!F999 -> 0 | H99: 0/3
A100: 14.01.02 | B100: Servicio de Energía Eléctrica | C100: mes | D100: 29.3319 | E100: 148.3032 | F100: 48.92 | G100: ='APU Estándar'!F1008 -> 81.2138 | H100: 46084 | I100: 4.06 | J100: Tiene insumos con dispersión (ver hoja Reporte)
A101: 14.01.03 | B101: Servicio de Internet | C101: mes | D101: 35 | G101: ='APU Estándar'!F1013 -> 35 | H101: 46025 | J101: Cobertura única · Tiene insumos con dispersión (ver hoja Reporte)
...

Sheet BD Materiales
A1: BASE DE DATOS — MATERIALES
A2: Edite la columna D (PU ESTÁNDAR) — los APUs y el CU se recalculan automáticamente
A4: Código | B4: Descripción | C4: Unidad | D4: PU ESTÁNDAR | E4: PU BUENO FERRO | F4: PU PABLO ESPINOSA | G4: PU MUÑOZ FREILE | H4: Usos | I4: Método | J4: Observación
A5: MAT-0001 | B5: Aceite Havoline | C5: Uni. | D5: 6.25 | F5: 6.25 | H5: 1 | I5: único | J5: Cobertura única
A6: MAT-0002 | B6: Aceite Multiuso 3 en 1 | C6: Uni. | D6: 1.18 | G6: 1.18 | H6: 1 | I6: único | J6: Cobertura única
A7: MAT-0003 | B7: Adoquin Toledo 6cm Color 16X16 | C7: ml | D7: 15.56 | F7: 15.56 | H7: 2 | I7: promedio
A8: MAT-0004 | B8: Adoquin Toledo 6cm Color 16X24 (Adoquin Toledo 6cm Color 24X24) | C8: ml | D8: 15.56 | F8: 15.56 | H8: 2 | I8: promedio
A9: MAT-0005 | B9: Adoquin Toledo 6cm Color 24X24 | C9: ml | D9: 15.56 | F9: 15.56 | H9: 2 | I9: promedio
A10: MAT-0006 | B10: Alambre galvanizado N 14 | C10: rollo | D10: 82.9725 | E10: 82.9725 | H10: 4 | I10: promedio
A11: MAT-0007 | B11: Alambre galvanizado Nº 14 | C11: R-Alambre | D11: 96.23 | F11: 96.23 | H11: 1 | I11: único | J11: Cobertura única
A12: MAT-0008 | B12: Alambre galvanizado Nº 14 | C12: rollo | D12: 92.45 | F12: 92.45 | H12: 1 | I12: único | J12: Cobertura única
A13: MAT-0009 | B13: Alambre recocido N.18 (20kg) (Alambre recocido N.18 (20kg)) | C13: R-Alambre | D13: 31.17 | G13: 31.17 | H13: 1 | I13: promedio
A14: MAT-0010 | B14: Alambre recocido N.18 (20kg) (Alambre recocido N.18 (20kg)) | C14: rollo | D14: 31.8 | G14: 31.8 | H14: 1 | I14: único | J14: Cobertura única
A15: MAT-0011 | B15: Alambre recocido N18 (20kg) (Alambre recocido N18 (20kg)) | C15: Rr20Kg | D15: 32.625 | E15: 29.145 | F15: 34.495 | G15: 34.235 | H15: 4 | I15: promedio
A16: MAT-0012 | B16: Aldaba Galvanizada 2'' | C16: Uni. | D16: 0.675 | E16: 0.32 | F16: 1.03 | H16: 1 | I16: mediana | J16: Criterio pendiente — desv 222%
A17: MAT-0013 | B17: Alfombra atrapamugre | C17: m2 | D17: 17.32 | G17: 17.32 | H17: 1 | I17: único | J17: Cobertura única
A18: MAT-0014 | B18: Amoladora 9" DWE496-B3 Dewalt | C18: Uni. | D18: 137.955 | F18: 134.16 | G18: 141.75 | H18: 1 | I18: promedio
A19: MAT-0015 | B19: Arena Fina | D19: 9.43 | E19: 6.59 | G19: 12.27 | H19: 1 | I19: promedio
A20: MAT-0016 | B20: Arena Fina | C20: m3 | D20: 13.481309 | F20: 16.309593 | G20: 12.538547 | H20: 4 | I20: promedio
A21: MAT-0017 | B21: Arena Rosada | C21: m3 | D21: 13.250168 | E21: 13.116667 | F21: 12.163423 | G21: 13.866667 | H21: 12 | I21: promedio
A22: MAT-0018 | B22: Armellas (Par de Armellas) | C22: Uni. | D22: 0.55 | F22: 0.53 | G22: 0.57 | H22: 1 | I22: promedio
A23: MAT-0019 | B23: Balde de construccion caucho | C23: Uni. | D23: 1.5633333 | E23: 1.38 | F23: 1.39 | G23: 1.92 | H23: 1 | I23: promedio
A24: MAT-0020 | B24: Barra agricola de 14 libras | C24: Uni. | D24: 17.085 | F24: 16.95 | G24: 17.22 | H24: 1 | I24: promedio
A25: MAT-0021 | B25: Bisagra Negra 3" | C25: Uni. | D25: 0.61 | E25: 0.48 | F25: 0.74 | H25: 1 | I25: promedio
A26: MAT-0022 | B26: Bloque alivianado 10x20x40 | C26: Uni. | D26: 0.33433333 | E26: 0.34 | F26: 0.33 | G26: 0.333 | H26: 1 | I26: promedio
A27: MAT-0023 | B27: Bloque alivianado 15x20x40 | C27: Uni. | D27: 0.346 | E27: 0.35 | F27: 0.34 | G27: 0.344 | H27: 2 | I27: promedio
A28: MAT-0024 | B28: Bloque alivianado 20x40x20 | C28: Uni. | D28: 0.4434125 | E28: 0.4539 | F28: 0.42 | G28: 0.449875 | H28: 2 | I28: promedio
A29: MAT-0025 | B29: Bondex Plus 25kg | C29: Uni. | D29: 6.63 | E29: 6.63 | H29: 2 | I29: promedio
A30: MAT-0026 | B30: Bondex Premium 25kg | C30: Uni. | D30: 11.4725 | F30: 11.4725 | H30: 1 | I30: único | J30: Cobertura única
A31: MAT-0027 | B31: Bondex Standar 25Kg | C31: Uni. | D31: 4.17 | G31: 4.17 | H31: 1 | I31: único | J31: Cobertura única
A32: MAT-0028 | B32: Bordillo 100X25X8 Gris Natural | C32: ml | D32: 6.79 | F32: 6.79 | H32: 1 | I32: único | J32: Cobertura única
A33: MAT-0029 | B33: Broca Concreto 1/2" 12mm | C33: Uni. | D33: 4.57 | G33: 4.57 | H33: 1 | I33: único | J33: Cobertura única
A34: MAT-0030 | B34: Broca Concreto 1/2" 13mm | C34: Uni. | D34: 1.505 | F34: 1.505 | H34: 2 | I34: promedio
A35: MAT-0031 | B35: Broca Concreto 1/2X12cm | C35: Uni. | D35: 4.25 | E35: 4.25 | H35: 1 | I35: único | J35: Cobertura única
A36: MAT-0032 | B36: Broca Concreto 1/2X30cm | C36: Uni. | D36: 5.1 | E36: 5.0825 | G36: 3.495 | H36: 4 | I36: mediana | J36: Criterio pendiente — desv 170%
A37: MAT-0033 | B37: Broca Concreto 5/8X12cm | C37: Uni. | D37: 5.053 | E37: 5.053 | H37: 1 | I37: único | J37: Cobertura única
A38: MAT-0034 | B38: Broca Madera Titanio3/8" | C38: Uni. | D38: 1.02 | G38: 1.02 | H38: 2 | I38: promedio
A39: MAT-0035 | B39: Broca Metal Cobalto 5/32" | C39: Uni. | D39: 1.61 | G39: 1.61 | H39: 1 | I39: único | J39: Cobertura única
A40: MAT-0036 | B40: Brocha 3" | C40: Uni. | D40: 1.07 | F40: 1.07 | H40: 1 | I40: único | J40: Cobertura única
A41: MAT-0037 | B41: Brocha 3" | C41: Uni. | D41: 2.01 | F41: 2.01 | H41: 1 | I41: único | J41: Cobertura única
A42: MAT-0038 | B42: Brocha 4" | C42: Uni. | D42: 1.09 | E42: 1.09 | G42: 1.09 | H42: 1 | I42: promedio
A43: MAT-0039 | B43: Cable Gemelo Blanco 2X10 | C43: Rollo | D43: 50.155 | F43: 99.11 | G43: 1.2 | H43: 1 | I43: mediana (outlier detectado) | J43: Revisar — desv 8159%
A44: MAT-0040 | B44: Cabo Madera Zapapico | C44: Uni. | D44: 1.34 | F44: 1.34 | H44: 1 | I44: único | J44: Cobertura única
A45: MAT-0041 | B45: Cabo1/2 (Cabo 1/2) | C45: mts. | D45: 0.29 | F45: 0.29 | G45: 0.29 | H45: 1 | I45: promedio
A46: MAT-0042 | B46: Candado Viro Fai Anticizalla 70 | C46: Uni. | D46: 27.1 | G46: 27.1 | H46: 1 | I46: único | J46: Cobertura única
A47: MAT-0043 | B47: Caneca 20 litros s/tapa | C47: Uni. | D47: 2.39 | F47: 2.39 | H47: 1 | I47: único | J47: Cobertura única
A48: MAT-0044 | B48: Caneca 5GLN | C48: Uni. | D48: 3.6 | G48: 3.6 | H48: 1 | I48: único | J48: Cobertura única
A49: MAT-0045 | B49: Caoba Roja | C49: lb | D49: 0.517 | E49: 0.532 | F49: 0.5075 | G49: 0.54 | H49: 4 | I49: promedio
A50: MAT-0046 | B50: Carretilla Polvo Azul | C50: Uni. | D50: 1.131875 | G50: 1.131875 | H50: 2 | I50: promedio
A51: MAT-0047 | B51: Carretilla Ripio | C51: Uni. | D51: 1.134 | G51: 1.134 | H51: 1 | I51: único | J51: Cobertura única
A52: MAT-0048 | B52: Carretilla Truper 220kl tomate | C52: Uni. | D52: 60.465 | F52: 61.86 | G52: 59.07 | H52: 1 | I52: promedio
A53: MAT-0049 | B53: Cementina | C53: saco | D53: 1.636 | E53: 1.488 | F53: 1.47 | G53: 1.95 | H53: 1 | I53: promedio
A54: MAT-0050 | B54: Cemento Campeon | C54: qq | D54: 6.6975 | E54: 6.602 | F54: 6.795 | G54: 6.7266667 | H54: 5 | I54: promedio
A55: MAT-0051 | B55: Cemento Campeon | C55: saco | D55: 6.7118947 | E55: 6.6008571 | F55: 6.7916667 | G55: 6.7616667 | H55: 8 | I55: promedio
A56: MAT-0052 | B56: Cemento Campeon HS 50KG | C56: qq | D56: 6.7489473 | F56: 6.7437333 | G56: 6.7532922 | H56: 9 | I56: promedio
A57: MAT-0053 | B57: Cemento Campeón | C57: qq | D57: 6.7 | E57: 6.6422857 | F57: 5.9561111 | G57: 6.7275 | H57: 8 | I57: mediana | J57: Criterio pendiente — desv 252%
A58: MAT-0054 | B58: Cemento Campeón | C58: saco | D58: 6.6886667 | E58: 6.666 | F58: 6.7 | G58: 6.7 | H58: 2 | I58: promedio
A59: MAT-0055 | B59: Cemento | C59: qq | H59: 1 | I59: sin datos
A60: MAT-0056 | B60: Cepillo de acero 5f cromado | C60: Uni. | D60: 1.3 | F60: 1.45 | G60: 1.15 | H60: 2 | I60: promedio
A61: MAT-0057 | B61: Chapisco 25 kg | C61: Uni. | D61: 7.6570635 | E61: 7.4 | F61: 8.06 | G61: 7.3183929 | H61: 6 | I61: promedio
A62: MAT-0058 | B62: Cinta Masking | C62: Uni. | D62: 1.45 | E62: 1.58 | F62: 1.57 | G62: 1.2 | H62: 2 | I62: promedio
A63: MAT-0059 | B63: Cinta Peligro 200MT (Cinta Peligro Amarillo 200MT) | C63: Uni. | D63: 0.02 | G63: 0.02 | H63: 1 | I63: único | J63: Cobertura única
A64: MAT-0060 | B64: Cinta de Embalaje | C64: Uni. | D64: 0.645 | G64: 0.645 | H64: 2 | I64: promedio
A65: MAT-0061 | B65: Clavo Galvanizado 2 1/2" | C65: kg | H65: 1 | I65: sin datos
A66: MAT-0062 | B66: Clavo de acero blanco chino 1 | C66: Kg. | D66: 3.145 | E66: 3.145 | H66: 4 | I66: promedio
A67: MAT-0063 | B67: Clavos Zinc 2 1/2"x9 (Caja 20kg (Clavos Zinc 2 1/2"x9 (Caja 20kg)) | C67: Kg. | D67: 3.125 | F67: 3.04 | G67: 3.21 | H67: 1 | I67: promedio
A68: MAT-0064 | B68: Clavos de acero 1” (1/2 kilo) (Clavos de acero 1” (1/2 kilo)) | C68: Kg. | D68: 9.0133333 | F68: 9.08 | G68: 8.88 | H68: 2 | I68: promedio
A69: MAT-0065 | B69: Clavos de acero 2'' | C69: Kg. | D69: 3.245 | E69: 3.1425 | F69: 7.2 | H69: 4 | I69: mediana | J69: Criterio pendiente — desv 138%
A70: MAT-0066 | B70: Clavos de acero 2.1/2” (Clavos de acero 2.1/2” (1 kilo)) | C70: Kg. | D70: 3.94 | G70: 3.94 | H70: 2 | I70: promedio
A71: MAT-0067 | B71: Clavos de acero 2.1/2” Japones | C71: Kg. | D71: 8.82 | G71: 8.82 | H71: 1 | I71: único | J71: Cobertura única
A72: MAT-0068 | B72: Clavos de acero 21/2'' | C72: Kg. | D72: 3.5215 | E72: 3.16425 | F72: 3.6695 | G72: 3.94 | H72: 4 | I72: promedio
A73: MAT-0069 | B73: Clavos galvanizados 2 1/2" | C73: Kg. | D73: 1.84375 | F73: 1.87 | G73: 1.8175 | H73: 4 | I73: promedio
A74: MAT-0070 | B74: Clavos galvanizados 2 1/2'' | C74: Kg. | D74: 1.8223333 | E74: 1.6935556 | F74: 1.945 | G74: 1.956 | H74: 9 | I74: promedio
A75: MAT-0071 | B75: Clavos galvanizados 2" | C75: Kg. | D75: 2.0827778 | F75: 2.22 | G75: 1.9455556 | H75: 6 | I75: promedio
A76: MAT-0072 | B76: Clavos galvanizados 2'' | C76: Kg. | D76: 1.9257895 | E76: 1.7266667 | F76: 2.1471429 | G76: 2.0066667 | H76: 9 | I76: promedio
A77: MAT-0073 | B77: Clavos galvanizados 3" | C77: Kg. | D77: 2.415 | F77: 2.415 | H77: 2 | I77: promedio
A78: MAT-0074 | B78: Cloro | C78: gal | D78: 0.96 | E78: 0.96 | H78: 1 | I78: único | J78: Cobertura única
A79: MAT-0075 | B79: Codal de Aluminio | C79: Uni. | D79: 40.57 | F79: 40.57 | H79: 1 | I79: único | J79: Cobertura única
A80: MAT-0076 | B80: Costales o saquillos | C80: Uni. | D80: 0.3 | G80: 0.3 | H80: 3 | I80: promedio
A81: MAT-0077 | B81: Cuarton 6 x 4 de eucalipto | C81: Uni. | D81: 2.015 | E81: 2.015 | H81: 2 | I81: promedio
A82: MAT-0078 | B82: Cuartón 6 x 4 de eucalipto | C82: Uni. | D82: 2.15 | E82: 2.15 | G82: 2.15 | H82: 5 | I82: promedio
A83: MAT-0079 | B83: Desinfectante | C83: gal | D83: 4.56 | F83: 4.56 | G83: 4.56 | H83: 1 | I83: promedio
A84: MAT-0080 | B84: Destornillador Estrella 1/4"x5" | C84: Uni. | D84: 1.86 | G84: 1.86 | H84: 1 | I84: único | J84: Cobertura única
A85: MAT-0081 | B85: Detergente | C85: Kg. | D85: 14.475 | E85: 1.77 | G85: 27.18 | H85: 1 | I85: mediana (outlier detectado) | J85: Revisar — desv 1436%
A86: MAT-0082 | B86: Disco Corte Diamante 9" | C86: u | H86: 1 | I86: sin datos
A87: MAT-0083 | B87: Disco Corte Madera 7 | C87: Uni. | D87: 8.452 | E87: 9.1533333 | G87: 7.4 | H87: 3 | I87: promedio
A88: MAT-0084 | B88: Disco Corte Madera 9" (Sierra) (Disco Corte Madera 9" (Sierra)) | C88: Uni. | D88: 21.08 | F88: 21.08 | H88: 1 | I88: único | J88: Cobertura única
A89: MAT-0085 | B89: Disco de corte de diamante 7" | C89: Uni. | D89: 4.8216667 | G89: 4.8216667 | H89: 3 | I89: promedio
A90: MAT-0086 | B90: Disco de corte de diamante 9" | C90: Uni. | D90: 7.326 | E90: 7.2 | F90: 7.3575 | H90: 4 | I90: promedio
A91: MAT-0087 | B91: Disco de corte de hierro 9" (Me (Disco de corte de hierro 9" (Metal)) | C91: Uni. | D91: 2.4041667 | G91: 2.4041667 | H91: 2 | I91: promedio
A92: MAT-0088 | B92: Disco de corte metal 9" | C92: Uni. | D92: 2.5252632 | E92: 2.42375 | F92: 2.61 | G92: 2.586 | H92: 8 | I92: promedio
A93: MAT-0089 | B93: Disco diamante segmentado 9" | C93: Uni. | D93: 5.35 | E93: 5.375 | G93: 17.902 | H93: 8 | I93: mediana (outlier detectado) | J93: Revisar — desv 2786%
A94: MAT-0090 | B94: Enchufe blindado 3 patas | C94: Uni. | D94: 1.45 | G94: 1.45 | H94: 1 | I94: único | J94: Cobertura única
A95: MAT-0091 | B95: Escalera Pie de Gallo | C95: Uni. | D95: 74.81 | G95: 74.81 | H95: 1 | I95: único | J95: Cobertura única
A96: MAT-0092 | B96: Escoba Negra Industrial Grande (Escoba Negra Industrial Grande 40cm) | C96: Uni. | D96: 3.335 | E96: 3.33 | G96: 3.34 | H96: 1 | I96: promedio
A97: MAT-0093 | B97: Escoba de coco | C97: Uni. | D97: 2.455 | E97: 1.525 | F97: 2.89 | G97: 2.95 | H97: 1 | I97: promedio
A98: MAT-0094 | B98: Escobas Plastico Dura | C98: Uni. | D98: 1.99 | G98: 1.99 | H98: 1 | I98: único | J98: Cobertura única
A99: MAT-0095 | B99: Escobas Plastico Suave | C99: Uni. | D99: 1.9466667 | E99: 1.57 | F99: 2.13 | G99: 2.14 | H99: 1 | I99: promedio
A100: MAT-0096 | B100: Espatula stanley 3'' | C100: Uni. | D100: 1.67 | G100: 1.67 | H100: 1 | I100: único | J100: Cobertura única
A101: MAT-0097 | B101: Franela | C101: Uni. | D101: 1.18 | G101: 1.18 | H101: 1 | I101: único | J101: Cobertura única
...

Sheet BD Mano de Obra
A1: BASE DE DATOS — MANO DE OBRA
A2: Edite la columna D (PU ESTÁNDAR) — los APUs y el CU se recalculan automáticamente
A4: Código | B4: Descripción | C4: Unidad | D4: PU ESTÁNDAR | E4: PU BUENO FERRO | F4: PU PABLO ESPINOSA | G4: PU MUÑOZ FREILE | H4: Usos | I4: Método | J4: Observación
A5: MO-0001 | B5: Guachimanía de obra | C5: mes | D5: 172.5 | E5: 172.5 | H5: 1 | I5: único | J5: Cobertura única
A6: MO-0002 | B6: M, Plástico Negro Para Protección De Terminados | C6: m2 | D6: 0.36 | F6: 0.36 | H6: 1 | I6: único | J6: Cobertura única
A7: MO-0003 | B7: M. Acceso Peatonal (Obra Civil) | C7: m2 | D7: 7 | E7: 7 | G7: 7 | H7: 1 | I7: promedio
A8: MO-0004 | B8: M. Adoquín En Acceso Peatonal | C8: m2 | D8: 2.8 | F8: 2.8 | H8: 1 | I8: único | J8: Cobertura única
A9: MO-0005 | B9: M. Adoquín En Estacionamiento | C9: m2 | D9: 2.8 | F9: 2.8 | H9: 1 | I9: único | J9: Cobertura única
A10: MO-0006 | B10: M. Alfeizar En Antepecho | C10: ml | D10: 2.8 | F10: 2.8 | H10: 1 | I10: único | J10: Cobertura única
A11: MO-0007 | B11: M. Alfeizar En Ventana | C11: ml | D11: 9.45 | E11: 9.45 | F11: 9.45 | H11: 1 | I11: promedio
A12: MO-0008 | B12: M. Apuntalamiento de losa deck metálico | C12: m2 | D12: 1.54 | E12: 1.9 | F12: 1.36 | G12: 1.36 | H12: 1 | I12: promedio
A13: MO-0009 | B13: M. Arrostramiento Vertical de Mampostería | C13: ml | D13: 6.37 | E13: 6.37 | F13: 6.37 | H13: 1 | I13: promedio
A14: MO-0010 | B14: M. Bordillo De Terrazas | C14: ml | D14: 6.38 | E14: 6.38 | F14: 6.38 | G14: 6.38 | H14: 1 | I14: promedio
A15: MO-0011 | B15: M. Bordillo en estacionamiento (1,00x0,10x0,30m) | C15: ml | D15: 2.6 | F15: 2.6 | H15: 1 | I15: único | J15: Cobertura única
A16: MO-0012 | B16: M. Canal recolector aguas lluvias | C16: ml | D16: 15.8 | E16: 15.8 | F16: 15.8 | H16: 1 | I16: promedio
A17: MO-0013 | B17: M. Cerramiento provisional de zaram y pingos | C17: ml | D17: 2.14 | E17: 2.14 | F17: 2.14 | G17: 2.14 | H17: 1 | I17: promedio
A18: MO-0014 | B18: M. Conformación plataforma - Acceso Peatonal | C18: m2 | D18: 0.7 | E18: 0.7 | F18: 0.7 | G18: 0.7 | H18: 1 | I18: promedio
A19: MO-0015 | B19: M. Contrapiso De Hormigón Planta Baja F'c=210 Kg/Cm² | C19: m2 | D19: 7 | E19: 8 | F19: 6.5 | G19: 6.5 | H19: 1 | I19: promedio
A20: MO-0016 | B20: M. Desmontaje de guachimanía de obra, baños, vestidores de obra y otros provisionales | C20: Glb | D20: 89.29 | G20: 89.29 | H20: 1 | I20: único | J20: Cobertura única
A21: MO-0017 | B21: M. Dinteles De Hormigón F'c = 180 Kg/Cm2 | C21: m | D21: 6.370016 | E21: 6.37 | F21: 6.3700481 | G21: 6.37 | H21: 1 | I21: promedio
A22: MO-0018 | B22: M. Ducha Rehundida | C22: m2 | D22: 13.26 | E22: 13.26 | F22: 13.26 | G22: 13.26 | H22: 1 | I22: promedio
A23: MO-0019 | B23: M. Encofrado de gradas exteriores (Detalle para luces acceso peatonal) | C23: m2 | D23: 6.16 | E23: 6.16 | H23: 1 | I23: único | J23: Cobertura única
A24: MO-0020 | B24: M. Encofrado y Desencofrado Columnas Circulares | C24: m2 | D24: 25.09 | E24: 25.09 | H24: 1 | I24: único | J24: Cobertura única
A25: MO-0021 | B25: M. Encofrado y Desencofrado Columnas Rectangulares | C25: m2 | D25: 11.25 | E25: 13.89 | F25: 9.93 | G25: 9.93 | H25: 1 | I25: promedio
A26: MO-0022 | B26: M. Encofrado y Desencofrado Dintel Descolgado Perimetral | C26: ml | D26: 6.5 | E26: 6.5 | F26: 6.5 | G26: 6.5 | H26: 1 | I26: promedio
A27: MO-0023 | B27: M. Encofrado y Desencofrado Losa Perimetral | C27: ml | D27: 3.87 | E27: 3.85 | F27: 3.88 | G27: 3.88 | H27: 1 | I27: promedio
A28: MO-0024 | B28: M. Encofrado y Desencofrado Muros | C28: m2 | D28: 11.285 | E28: 12.77 | G28: 9.8 | H28: 1 | I28: promedio
A29: MO-0025 | B29: M. Encofrado y Desencofrado de Losa | C29: m2 | D29: 12.565 | E29: 13.63 | F29: 11.5 | H29: 1 | I29: promedio
A30: MO-0026 | B30: M. Encofrado y Desencofrado de Vigas | C30: m2 | D30: 11.5 | E30: 25.87 | F30: 11 | G30: 11.5 | H30: 1 | I30: mediana | J30: Criterio pendiente — desv 135%
A31: MO-0027 | B31: M. Enlucido De Fachada | C31: m2 | D31: 7.4633333 | E31: 7.99 | F31: 6.8 | G31: 7.6 | H31: 1 | I31: promedio
A32: MO-0028 | B32: M. Enlucido De Fajas Exteriores | C32: ml | D32: 3.25 | E32: 3.4 | F32: 3.1 | H32: 1 | I32: promedio
A33: MO-0029 | B33: M. Enlucido De Fajas Interiores | C33: ml | D33: 3 | E33: 3.1 | F33: 2.9 | H33: 1 | I33: promedio
A34: MO-0030 | B34: M. Enlucido De Filos Exteriores | C34: m2 | D34: 1.25 | E34: 1.4 | F34: 1.1 | H34: 1 | I34: promedio
A35: MO-0031 | B35: M. Enlucido De Filos Interiores | C35: ml | D35: 1.45 | E35: 1.6 | F35: 1.3 | H35: 1 | I35: promedio
A36: MO-0032 | B36: M. Enlucido Exterior Terminado Hormigón Visto | C36: m2 | D36: 3.95 | F36: 3.1 | G36: 4.8 | H36: 1 | I36: promedio
A37: MO-0033 | B37: M. Enlucido Vertical Interior | C37: m2 | D37: 4.89 | E37: 5.02 | F37: 4.8 | G37: 4.85 | H37: 1 | I37: promedio
A38: MO-0034 | B38: M. Excavaciones Para Plintos Y Cimientos ( Maquina Y Perfilado Manual) | C38: m3 | D38: 7.8333333 | E38: 7.5 | F38: 7.5 | G38: 8.5 | H38: 1 | I38: promedio
A39: MO-0035 | B39: M. Excavaciones Y Relleno Compactado Para Instalaciones Eléctricas | C39: ml | D39: 3.9 | F39: 3.9 | H39: 1 | I39: único | J39: Cobertura única
A40: MO-0036 | B40: M. Excavaciones Y Relleno Compactado Para Instalaciones Hidrosanitarias | C40: ml | D40: 3.9 | F40: 3.9 | G40: 3.9 | H40: 1 | I40: promedio
A41: MO-0037 | B41: M. Forrado de columnas metálicas | C41: m2 | D41: 3.8 | F41: 3.8 | G41: 3.8 | H41: 1 | I41: promedio
A42: MO-0038 | B42: M. Goterones - Medias Cañas | C42: ml | D42: 1.34 | E42: 1.5 | F42: 1.26 | G42: 1.26 | H42: 1 | I42: promedio
A43: MO-0039 | B43: M. Guachimanía de obra, baños, vestidores de obra y otros provisionales | C43: Glb | D43: 200 | E43: 200 | F43: 200 | G43: 200 | H43: 1 | I43: promedio
A44: MO-0040 | B44: M. Hierro 10 Mm X 12 M | C44: Kg. | D44: 0.32 | E44: 0.32 | F44: 0.32 | G44: 0.32 | H44: 1 | I44: promedio
A45: MO-0041 | B45: M. Hierro 12 Mm X 12 M | C45: Kg. | D45: 0.32 | E45: 0.32 | F45: 0.32 | G45: 0.32 | H45: 1 | I45: promedio
A46: MO-0042 | B46: M. Hierro 14 Mm X 12 M | C46: Kg. | D46: 0.32 | E46: 0.32 | F46: 0.32 | G46: 0.32 | H46: 1 | I46: promedio
A47: MO-0043 | B47: M. Hierro 16 Mm X 12 M | C47: Kg. | D47: 0.32 | E47: 0.32 | F47: 0.32 | G47: 0.32 | H47: 1 | I47: promedio
A48: MO-0044 | B48: M. Hierro 18 Mm X 12 M | C48: Kg. | D48: 0.32 | F48: 0.32 | G48: 0.32 | H48: 1 | I48: promedio
A49: MO-0045 | B49: M. Hierro 8 Mm X 12 M | C49: Kg. | D49: 0.32 | E49: 0.32 | H49: 1 | I49: único | J49: Cobertura única
A50: MO-0046 | B50: M. Hormigón En Cadenas F'c=210kg/Cm² | C50: m3 | D50: 33 | E50: 33 | F50: 33 | G50: 33 | H50: 1 | I50: promedio
A51: MO-0047 | B51: M. Hormigón En Cubierta Plana F'c=210kg/Cm² | C51: m3 | D51: 35 | E51: 37 | F51: 33 | H51: 1 | I51: promedio
A52: MO-0048 | B52: M. Hormigón En Escaleras F'c=210kg/Cm² (Acceso Peatonal) | C52: m3 | D52: 33 | E52: 33 | H52: 1 | I52: único | J52: Cobertura única
A53: MO-0049 | B53: M. Hormigón En Losa De Entrepiso F'c=210kg/Cm² | C53: m3 | D53: 34.333333 | E53: 37 | F53: 33 | G53: 33 | H53: 1 | I53: promedio
A54: MO-0050 | B54: M. Hormigón En Muros F'c=210kg/Cm² | C54: m3 | D54: 33 | E54: 33 | G54: 33 | H54: 1 | I54: promedio
A55: MO-0051 | B55: M. Hormigón En Plintos F'c=210kg/Cm² | C55: m3 | D55: 33 | E55: 33 | F55: 33 | G55: 33 | H55: 1 | I55: promedio
A56: MO-0052 | B56: M. Hormigón En Replantillo F'c=180kg/Cm² | C56: m3 | D56: 25 | E56: 25 | F56: 25 | G56: 25 | H56: 1 | I56: promedio
A57: MO-0053 | B57: M. Hormigón Premezclado En Columnas F'c=210kg/Cm² CABEZALES | C57: m3 | D57: 33 | E57: 33 | F57: 33 | G57: 33 | H57: 1 | I57: promedio
A58: MO-0054 | B58: M. Hormigón Premezclado En Columnas F'c=210kg/Cm² COLUMNAS | C58: m3 | D58: 33 | E58: 33 | F58: 33 | G58: 33 | H58: 1 | I58: promedio
A59: MO-0055 | B59: M. Hormigón Premezclado En Vigas F'c=210kg/Cm² | C59: m3 | D59: 33 | E59: 33 | F59: 33 | H59: 1 | I59: promedio
A60: MO-0056 | B60: M. Hormigón de nivelación de placas metálicas | C60: m3 | D60: 15 | F60: 15 | H60: 1 | I60: único | J60: Cobertura única
A61: MO-0057 | B61: M. Hormigón en detalle tipo Vigueta | C61: m3 | D61: 33 | F61: 33 | H61: 1 | I61: único | J61: Cobertura única
A62: MO-0058 | B62: M. Hormigón en dintel descolgado perimetral | C62: ml | D62: 4.25 | E62: 4.25 | F62: 4.25 | H62: 1 | I62: promedio
A63: MO-0059 | B63: M. Internet (Servicio de Internet) | C63: mes | D63: 35 | E63: 35 | H63: 1 | I63: único | J63: Cobertura única
A64: MO-0060 | B64: M. Juntas de dilatación en contrapiso | C64: m | D64: 3.4 | F64: 3.4 | H64: 1 | I64: único | J64: Cobertura única
A65: MO-0061 | B65: M. Limpieza Provisional (Durante la obra Material Y Personal) | C65: Glb | D65: 880 | E65: 202.61 | F65: 1026.32 | G65: 880 | H65: 1 | I65: mediana | J65: Criterio pendiente — desv 407%
A66: MO-0062 | B66: M. Malla De Refuerzo 6*15 (Acceso Peatonal) | C66: m2 | D66: 1.04 | E66: 1.04 | H66: 1 | I66: único | J66: Cobertura única
A67: MO-0063 | B67: M. Malla De Refuerzo 6*15 | C67: m2 | D67: 1.04 | E67: 1.04 | F67: 1.04 | G67: 1.04 | H67: 1 | I67: promedio
A68: MO-0064 | B68: M. Mamposteria de ladrillo visto una cara (Mamposteria de ladrillo visto) | C68: m2 | D68: 16.135 | E68: 17.27 | F68: 15 | H68: 1 | I68: promedio
A69: MO-0065 | B69: M. Mampostería De Bloque E=10 Cm | C69: m2 | D69: 5.84 | E69: 6.92 | F69: 5.3 | G69: 5.3 | H69: 1 | I69: promedio
A70: MO-0066 | B70: M. Mampostería De Bloque E=15 Cm | C70: m2 | D70: 5.84 | E70: 6.92 | F70: 5.3 | G70: 5.3 | H70: 1 | I70: promedio
A71: MO-0067 | B71: M. Mampostería De Bloque E=20cm | C71: m2 | D71: 6.1266667 | E71: 7.38 | F71: 5.5 | G71: 5.5 | H71: 1 | I71: promedio
A72: MO-0068 | B72: M. Masillado De Piso A Máquina Con Endurecedor | C72: m2 | D72: 5.4 | E72: 5.4 | H72: 1 | I72: único | J72: Cobertura única
A73: MO-0069 | B73: M. Masillado De Piso A Máquina | C73: m2 | D73: 1.1533333 | E73: 1.2 | F73: 1.13 | G73: 1.13 | H73: 1 | I73: promedio
A74: MO-0070 | B74: M. Nicho Para Baños y lavavajillas | C74: Und | D74: 25.333333 | E74: 24 | F74: 22 | G74: 30 | H74: 1 | I74: promedio
A75: MO-0071 | B75: M. Perfilado de taludes Muros | C75: m2 | D75: 1.86 | G75: 1.86 | H75: 1 | I75: único | J75: Cobertura única
A76: MO-0072 | B76: M. Picado Y Corchado | C76: ml | D76: 0.95 | E76: 0.95 | F76: 0.95 | G76: 0.95 | H76: 1 | I76: promedio
A77: MO-0073 | B77: M. Plástico Polietileno 2 Capas (Acceso peatonal) | C77: m2 | D77: 0.36 | E77: 0.36 | H77: 1 | I77: único | J77: Cobertura única
A78: MO-0074 | B78: M. Plástico Polietileno 2 Capas | C78: m2 | D78: 0.36 | E78: 0.36 | F78: 0.36 | G78: 0.36 | H78: 1 | I78: promedio
A79: MO-0075 | B79: M. Rasanteo Y Conformación Manual De Plataformas | C79: m2 | D79: 0.7 | E79: 0.7 | F79: 0.7 | G79: 0.7 | H79: 1 | I79: promedio
A80: MO-0076 | B80: M. Rasanteo y conformación de jardines | C80: m2 | D80: 0.7 | E80: 0.7 | F80: 0.7 | G80: 0.7 | H80: 1 | I80: promedio
A81: MO-0077 | B81: M. Rejilla con trampa para ducha | C81: ml | D81: 101.5 | F81: 101.5 | H81: 1 | I81: único | J81: Cobertura única
A82: MO-0078 | B82: M. Rejilla metálica de 2" | C82: ml | D82: 107.1 | F82: 107.1 | H82: 1 | I82: único | J82: Cobertura única
A83: MO-0079 | B83: M. Relleno Compactado Con Material Local (Plintos Y Cimientos) | C83: m3 | D83: 4.29 | E83: 4.29 | F83: 4.29 | G83: 4.29 | H83: 1 | I83: promedio
A84: MO-0080 | B84: M. Relleno compactado | C84: m3 | D84: 2.8833333 | E84: 3 | F84: 3 | G84: 2.65 | H84: 1 | I84: promedio
A85: MO-0081 | B85: M. Replanteo Acceso Peatonal | C85: m2 | D85: 0.72 | E85: 0.72 | F85: 0.72 | H85: 1 | I85: promedio
A86: MO-0082 | B86: M. Replanteo Plataforma Parqueadero | C86: m2 | D86: 0.74 | F86: 0.735 | G86: 0.75 | H86: 2 | I86: promedio
A87: MO-0083 | B87: M. Replanteo Topográfico Ejes Estructurales y movimiento tierras | C87: Glb | D87: 160 | E87: 240 | F87: 120 | G87: 120 | H87: 1 | I87: promedio
A88: MO-0084 | B88: M. Replanteo Y Nivelación | C88: m2 | D88: 0.77666667 | E88: 0.72 | F88: 0.72 | G88: 0.89 | H88: 1 | I88: promedio
A89: MO-0085 | B89: M. Suministro, tendido y compactación de subbase clase III e=20cm (Parqueadero) | C89: m2 | D89: 2 | F89: 2 | H89: 1 | I89: único | J89: Cobertura única
A90: MO-0086 | B90: M. Suministro, tendido y compactación de subbase clase III e=20cm | C90: m2 | D90: 2 | F90: 2 | H90: 1 | I90: único | J90: Cobertura única
A91: MO-0087 | B91: M. Volumen para medidores de ag (Volumen para medidores de agua y luz) | C91: Uni. | D91: 133.94 | G91: 133.94 | H91: 1 | I91: único | J91: Cobertura única
A92: MO-0088 | B92: M.Cisterna (Incluye impermeabilización) | C92: glb | H92: 1 | I92: sin datos
A93: MO-0089 | B93: M.Piscina (Obra Civil) | C93: glb | H93: 1 | I93: sin datos
A94: MO-0090 | D94: 300 | E94: 300 | F94: 300 | G94: 300 | H94: 4 | I94: promedio
A95: MO-0091 | C95: m2 | D95: 40.99 | F95: 40.99 | G95: 40.99 | H95: 1 | I95: promedio
A96: MO-0092 | C96: mes | H96: 1 | I96: sin datos
A97: MO-0093 | B97: M. Instalaciones eléctricas provisionales | C97: Glb | D97: 300 | E97: 300 | F97: 300 | G97: 300 | H97: 1 | I97: promedio
A98: MO-0094 | B98: M. Instalaciones hidrosanitarias provisionales | C98: Glb | D98: 300 | E98: 300 | F98: 300 | G98: 300 | H98: 1 | I98: promedio
A99: MO-0095 | B99: M. Cubierta de fibrocemento (Incluye capa super K) | C99: m2 | D99: 40.99 | F99: 40.99 | G99: 40.99 | H99: 1 | I99: promedio

Sheet BD Equipo
A1: BASE DE DATOS — EQUIPO
A2: Edite la columna D (PU ESTÁNDAR) — los APUs y el CU se recalculan automáticamente
A4: Código | B4: Descripción | C4: Unidad | D4: PU ESTÁNDAR | E4: PU BUENO FERRO | F4: PU PABLO ESPINOSA | G4: PU MUÑOZ FREILE | H4: Usos | I4: Método | J4: Observación
A5: EQ-0001 | B5: Alquiler Andamio | C5: Uni. | D5: 0.35957143 | E5: 0.35871429 | F5: 0.36 | G5: 0.36 | H5: 12 | I5: promedio
A6: EQ-0002 | B6: Alquiler Generador | C6: día | D6: 44.64 | G6: 44.64 | H6: 1 | I6: único | J6: Cobertura única
A7: EQ-0003 | B7: Alquiler Puntales | C7: Uni. | D7: 0.05 | G7: 0.05 | H7: 1 | I7: único | J7: Cobertura única
A8: EQ-0004 | B8: Alquiler Rodillo | C8: Dia | D8: 89.29 | G8: 89.29 | H8: 1 | I8: único | J8: Cobertura única
A9: EQ-0005 | B9: Alquiler Rotomartillo | C9: Uni. | D9: 31.25 | E9: 31.25 | G9: 31.25 | H9: 4 | I9: promedio
A10: EQ-0006 | B10: Alquiler andamio | C10: Uni. | D10: 0.36 | F10: 0.36 | H10: 3 | I10: promedio
A11: EQ-0007 | B11: Alquiler compactador sapo | C11: Uni. | D11: 25 | F11: 25 | G11: 25 | H11: 3 | I11: promedio
A12: EQ-0008 | B12: Alquiler compactador sapo | C12: día | D12: 25 | E12: 25 | F12: 25 | G12: 25 | H12: 1 | I12: promedio
A13: EQ-0009 | B13: Alquiler concretera | C13: día | D13: 31.25 | F13: 31.25 | G13: 31.25 | H13: 1 | I13: promedio
A14: EQ-0010 | B14: Alquiler de Elevador a gasolina | C14: día | D14: 35.71 | G14: 35.71 | H14: 1 | I14: único | J14: Cobertura única
A15: EQ-0011 | B15: Alquiler de Maquinaria (retroex (Alquiler de Maquinaria (retroexcavadora)) | C15: Hr, | D15: 22 | G15: 22 | H15: 1 | I15: único | J15: Cobertura única
A16: EQ-0012 | B16: Alquiler de Maquinaria (retroex (Alquiler de Maquinaria (retroexcavadora)) | C16: Hr. | D16: 22 | E16: 22 | G16: 22 | H16: 4 | I16: promedio
A17: EQ-0013 | B17: Alquiler de Tableros de madera | C17: Uni. | D17: 0.0892 | E17: 0.0892 | H17: 1 | I17: único | J17: Cobertura única
A18: EQ-0014 | B18: Alquiler de Tablones | C18: Uni. | D18: 0.089948261 | E18: 0.089801667 | F18: 0.09 | G18: 0.09 | H18: 14 | I18: promedio
A19: EQ-0015 | B19: Alquiler vibrador | C19: Uni. | D19: 17.86 | E19: 17.86 | F19: 17.86 | G19: 17.86 | H19: 9 | I19: promedio
A20: EQ-0016 | B20: Arnes de Seguridad + cuerda 3P. (Arnes de Seguridad + 3P Fijacion total) | C20: Uni. | D20: 49.88 | G20: 49.88 | H20: 1 | I20: único | J20: Cobertura única
A21: EQ-0017 | B21: Bomba Estacionaria | C21: m3 | D21: 8 | E21: 8 | F21: 8 | G21: 8 | H21: 10 | I21: promedio
A22: EQ-0018 | B22: Casco | C22: Uni. | D22: 4.13 | E22: 9.52 | F22: 4.13 | G22: 4.12 | H22: 1 | I22: mediana | J22: Criterio pendiente — desv 131%
A23: EQ-0019 | B23: Cinta amarilla Precaución 200MT | C23: mts. | D23: 0.0217 | E23: 0.0164 | F23: 0.0222 | G23: 0.0265 | H23: 1 | I23: promedio
A24: EQ-0020 | B24: Gafa Transparente Reforzada | C24: Uni. | D24: 1.15 | F24: 1.82 | G24: 0.48 | H24: 1 | I24: mediana | J24: Criterio pendiente — desv 279%
A25: EQ-0021 | B25: Guante de Cuero Operador | C25: Uni. | D25: 1.4566667 | E25: 1.43 | F25: 1.47 | G25: 1.47 | H25: 1 | I25: promedio
A26: EQ-0022 | B26: Guantes de Caucho | C26: pr | D26: 1.22 | F26: 1.16 | G26: 1.28 | H26: 1 | I26: promedio
A27: EQ-0023 | B27: Horas Maquinas Mini Cargadora | C27: Hr. | D27: 22.5 | E27: 20 | G27: 25 | H27: 1 | I27: promedio
A28: EQ-0024 | B28: Horas Maquinas Retroexcavadora | C28: Hr. | D28: 22.42875 | E28: 23.143333 | F28: 22 | G28: 22 | H28: 3 | I28: promedio
A29: EQ-0025 | B29: M. Desbroce de Capa Vegetal | C29: m2 | D29: 0.62666667 | E29: 0.65 | F29: 0.65 | G29: 0.58 | H29: 1 | I29: promedio
A30: EQ-0026 | B30: M. Excavación mecánica en banco para conformación de plataforma | C30: m3 | D30: 1.16 | F30: 1.25 | G30: 1.07 | H30: 1 | I30: promedio
A31: EQ-0027 | B31: M. Pruebas De Laboratorio | C31: Glb | D31: 60 | E31: 60 | F31: 40 | G31: 80 | H31: 1 | I31: promedio
A32: EQ-0028 | B32: M. Pruebas de compactación en plataformas | C32: Glb | D32: 400 | E32: 350 | F32: 350 | G32: 500 | H32: 1 | I32: promedio
A33: EQ-0029 | B33: M. Transporte de material para relleno | C33: m3 | D33: 3.92 | E33: 3.92 | H33: 1 | I33: único | J33: Cobertura única
A34: EQ-0030 | B34: M. Transporte desalojo de material a botadero | C34: m3 | D34: 20.285 | F34: 36.78 | G34: 3.79 | H34: 1 | I34: mediana (outlier detectado) | J34: Revisar — desv 870%
A35: EQ-0031 | B35: Mantenimiento Herramientas | C35: Glb | D35: 28.28 | E35: 24.77 | G35: 31.79 | H35: 1 | I35: promedio
A36: EQ-0032 | B36: Mascara Para Esmerilar Reforzad (ascara Para Esmerilar Reforzada) | C36: Uni. | D36: 4.13 | F36: 4.13 | H36: 1 | I36: único | J36: Cobertura única
A37: EQ-0033 | B37: Servicio mínimo de Bombeo | C37: m3 | D37: 8 | E37: 8 | H37: 3 | I37: promedio
A38: EQ-0034 | B38: Trans. Desalojo-Escombro Botade (Trans. Desalojo-Escombro Botadero fuera de obra) | C38: viaje | D38: 35 | G38: 35 | H38: 2 | I38: promedio
A39: EQ-0035 | B39: Transporte Adoquin | C39: Uni. | D39: 35 | F39: 35 | H39: 2 | I39: promedio
A40: EQ-0036 | B40: Transporte Limpieza Y Desalojo De Escombros + tickets emgirs | C40: Viaje | D40: 36.43 | E40: 39.29 | F40: 35 | G40: 35 | H40: 1 | I40: promedio
A41: EQ-0037 | B41: Transporte de Montacargas | C41: Uni. | D41: 70 | G41: 70 | H41: 1 | I41: único | J41: Cobertura única
A42: EQ-0038 | H42: 2 | I42: sin datos

Sheet BD Rendimientos
A1: BASE DE DATOS — RENDIMIENTOS (Cantidad de insumo por unidad de obra) | L1: Clave única
A2: Edite la columna G (RENDIMIENTO) — los APUs se recalculan automáticamente
A4: APU Código | B4: APU Descripción | C4: APU Unid. | D4: Sección | E4: Insumo | F4: Unid. | G4: RENDIMIENTO | H4: Cant BF | I4: Cant PE | J4: Cant MF | K4: Observación
A5: 01.01.01 | B5: Replanteo Topográfico Ejes Estructurales y movimiento tierras | C5: Glb | D5: MO | E5: M. Replanteo Topográfico Ejes Estructurales y movimiento tierras | F5: Glb | G5: 1 | H5: 1 | I5: 1 | J5: 1 | K5: MO principal (rend=1) | L5: 01.01.01|M. Replanteo Topográfico Ejes Estructurales y movimiento tierras|Glb|mano_obra
A6: 01.01.02 | B6: Replanteo Y Nivelación | C6: m2 | D6: MAT | E6: Alambre galvanizado N 14 | F6: rollo | G6: 0.0030732352 | H6: 1 | K6: cobertura única | L6: 01.01.02|Alambre galvanizado N 14|rollo|materiales
A7: 01.01.02 | B7: Replanteo Y Nivelación | C7: m2 | D7: MAT | E7: Broca Madera Titanio3/8" | F7: Uni. | G7: 0.0010507734 | J7: 1 | K7: cobertura única | L7: 01.01.02|Broca Madera Titanio3/8"|Uni.|materiales
A8: 01.01.02 | B8: Replanteo Y Nivelación | C8: m2 | D8: MAT | E8: Caoba Roja | F8: lb | G8: 0.017743166 | H8: 19.5 | I8: 4.42 | J8: 8.11 | K8: Rendimiento disperso | L8: 01.01.02|Caoba Roja|lb|materiales
A9: 01.01.02 | B9: Replanteo Y Nivelación | C9: m2 | D9: MAT | E9: Cementina | F9: saco | G9: 0.024467622 | H9: 7 | I9: 9 | J9: 15 | L9: 01.01.02|Cementina|saco|materiales
A10: 01.01.02 | B10: Replanteo Y Nivelación | C10: m2 | D10: MAT | E10: Clavos de acero 2'' | F10: Kg. | G10: 0.0046098528 | H10: 1.5 | K10: cobertura única | L10: 01.01.02|Clavos de acero 2''|Kg.|materiales
A11: 01.01.02 | B11: Replanteo Y Nivelación | C11: m2 | D11: MAT | E11: Clavos de acero 21/2'' | F11: Kg. | G11: 0.0040142909 | H11: 2 | I11: 1 | J11: 0.5 | K11: Rendimiento disperso | L11: 01.01.02|Clavos de acero 21/2''|Kg.|materiales
A12: 01.01.02 | B12: Replanteo Y Nivelación | C12: m2 | D12: MAT | E12: Clavos galvanizados 2'' | F12: Kg. | G12: 0.0093924525 | H12: 3.5 | I12: 2 | L12: 01.01.02|Clavos galvanizados 2''|Kg.|materiales
A13: 01.01.02 | B13: Replanteo Y Nivelación | C13: m2 | D13: MAT | E13: Clavos galvanizados 2 1/2'' | F13: Kg. | G13: 0.0062778171 | H13: 4 | J13: 0.25 | K13: Rendimiento disperso | L13: 01.01.02|Clavos galvanizados 2 1/2''|Kg.|materiales
A14: 01.01.02 | B14: Replanteo Y Nivelación | C14: m2 | D14: MAT | E14: Clavos galvanizados 3" | F14: Kg. | G14: 0.0040142909 | I14: 1 | K14: cobertura única | L14: 01.01.02|Clavos galvanizados 3"|Kg.|materiales
A15: 01.01.02 | B15: Replanteo Y Nivelación | C15: m2 | D15: MAT | E15: Cuartón 6 x 4 de eucalipto | F15: Uni. | G15: 0.013660054 | J15: 13 | K15: cobertura única | L15: 01.01.02|Cuartón 6 x 4 de eucalipto|Uni.|materiales
A16: 01.01.02 | B16: Replanteo Y Nivelación | C16: m2 | D16: MAT | E16: Manguera transparente | F16: ml | G16: 0.10035727 | I16: 25 | K16: cobertura única | L16: 01.01.02|Manguera transparente|ml|materiales
A17: 01.01.02 | B17: Replanteo Y Nivelación | C17: m2 | D17: MAT | E17: Pingos de 2.5 mts | F17: Uni. | G17: 0.040142909 | H17: 19 | I17: 10 | J17: 3 | K17: Rendimiento disperso | L17: 01.01.02|Pingos de 2.5 mts|Uni.|materiales
A18: 01.01.02 | B18: Replanteo Y Nivelación | C18: m2 | D18: MAT | E18: Pingos de 3 mts | F18: Uni. | G18: 0.022698388 | I18: 10 | J18: 5 | K18: Rendimiento disperso | L18: 01.01.02|Pingos de 3 mts|Uni.|materiales
A19: 01.01.02 | B19: Replanteo Y Nivelación | C19: m2 | D19: MAT | E19: Riel de eucalipto | F19: Uni. | G19: 0.069243217 | H19: 32 | I19: 10 | L19: 01.01.02|Riel de eucalipto|Uni.|materiales
A20: 01.01.02 | B20: Replanteo Y Nivelación | C20: m2 | D20: MAT | E20: Spray Rojo | F20: Uni. | G20: 0.0092197056 | H20: 3 | I20: 5 | J20: 2 | K20: Rendimiento disperso | L20: 01.01.02|Spray Rojo|Uni.|materiales
A21: 01.01.02 | B21: Replanteo Y Nivelación | C21: m2 | D21: MAT | E21: Tablas de Monte | F21: Uni. | G21: 0.030827778 | H21: 7 | I21: 10 | L21: 01.01.02|Tablas de Monte|Uni.|materiales
A22: 01.01.02 | B22: Replanteo Y Nivelación | C22: m2 | D22: MO | E22: M. Replanteo Y Nivelación | F22: m2 | G22: 1 | H22: 325.39 | I22: 249.11 | J22: 951.68 | K22: MO principal (rend=1) | L22: 01.01.02|M. Replanteo Y Nivelación|m2|mano_obra
A23: 01.01.05 | B23: Guachimanía de obra, baños, vestidores de obra y otros provisionales | C23: Glb | D23: MAT | E23: Alambre galvanizado N 14 | F23: rollo | G23: 1 | H23: 1 | K23: cobertura única | L23: 01.01.05|Alambre galvanizado N 14|rollo|materiales
A24: 01.01.05 | B24: Guachimanía de obra, baños, vestidores de obra y otros provisionales | C24: Glb | D24: MAT | E24: Aldaba Galvanizada 2'' | F24: Uni. | G24: 1.5 | H24: 1 | I24: 2 | L24: 01.01.05|Aldaba Galvanizada 2''|Uni.|materiales
A25: 01.01.05 | B25: Guachimanía de obra, baños, vestidores de obra y otros provisionales | C25: Glb | D25: MAT | E25: Armellas (Par de Armellas) | F25: Uni. | G25: 3 | I25: 2 | J25: 4 | L25: 01.01.05|Armellas (Par de Armellas)|Uni.|materiales
A26: 01.01.05 | B26: Guachimanía de obra, baños, vestidores de obra y otros provisionales | C26: Glb | D26: MAT | E26: Bisagra Negra 3" | F26: Uni. | G26: 6 | H26: 6 | I26: 6 | L26: 01.01.05|Bisagra Negra 3"|Uni.|materiales
A27: 01.01.05 | B27: Guachimanía de obra, baños, vestidores de obra y otros provisionales | C27: Glb | D27: MAT | E27: Bloque alivianado 15x20x40 | F27: Uni. | G27: 700 | H27: 700 | K27: cobertura única | L27: 01.01.05|Bloque alivianado 15x20x40|Uni.|materiales
A28: 01.01.05 | B28: Guachimanía de obra, baños, vestidores de obra y otros provisionales | C28: Glb | D28: MAT | E28: Candado Viro Fai Anticizalla 70 | F28: Uni. | G28: 1 | J28: 1 | K28: cobertura única | L28: 01.01.05|Candado Viro Fai Anticizalla 70|Uni.|materiales
A29: 01.01.05 | B29: Guachimanía de obra, baños, vestidores de obra y otros provisionales | C29: Glb | D29: MAT | E29: Cemento Campeón | F29: saco | G29: 3 | H29: 12 | I29: 3 | J29: 1 | K29: Rendimiento disperso | L29: 01.01.05|Cemento Campeón|saco|materiales
A30: 01.01.05 | B30: Guachimanía de obra, baños, vestidores de obra y otros provisionales | C30: Glb | D30: MAT | E30: Clavos de acero 2.1/2” (Clavos de acero 2.1/2” (1 kilo)) | F30: Kg. | G30: 0.5 | J30: 0.5 | K30: cobertura única | L30: 01.01.05|Clavos de acero 2.1/2” (Clavos de acero 2.1/2” (1 kilo))|Kg.|materiales
A31: 01.01.05 | B31: Guachimanía de obra, baños, vestidores de obra y otros provisionales | C31: Glb | D31: MAT | E31: Clavos galvanizados 2'' | F31: Kg. | G31: 2.3333333 | H31: 2.5 | I31: 1.5 | J31: 3 | L31: 01.01.05|Clavos galvanizados 2''|Kg.|materiales
A32: 01.01.05 | B32: Guachimanía de obra, baños, vestidores de obra y otros provisionales | C32: Glb | D32: MAT | E32: Clavos galvanizados 2 1/2'' | F32: Kg. | G32: 2.25 | H32: 2.5 | J32: 2 | L32: 01.01.05|Clavos galvanizados 2 1/2''|Kg.|materiales
A33: 01.01.05 | B33: Guachimanía de obra, baños, vestidores de obra y otros provisionales | C33: Glb | D33: MAT | E33: Clavos Zinc 2 1/2"x9 (Caja 20kg (Clavos Zinc 2 1/2"x9 (Caja 20kg)) | F33: Kg. | G33: 1.25 | I33: 0.5 | J33: 2 | K33: Rendimiento disperso | L33: 01.01.05|Clavos Zinc 2 1/2"x9 (Caja 20kg (Clavos Zinc 2 1/2"x9 (Caja 20kg))|Kg.|materiales
A34: 01.01.05 | B34: Guachimanía de obra, baños, vestidores de obra y otros provisionales | C34: Glb | D34: MAT | E34: Cuartón 6 x 4 de eucalipto | F34: Uni. | G34: 54 | J34: 54 | K34: cobertura única | L34: 01.01.05|Cuartón 6 x 4 de eucalipto|Uni.|materiales
A35: 01.01.05 | B35: Guachimanía de obra, baños, vestidores de obra y otros provisionales | C35: Glb | D35: MAT | E35: Disco diamante segmentado 9" | F35: Uni. | G35: 1 | H35: 1 | K35: cobertura única | L35: 01.01.05|Disco diamante segmentado 9"|Uni.|materiales
A36: 01.01.05 | B36: Guachimanía de obra, baños, vestidores de obra y otros provisionales | C36: Glb | D36: MAT | E36: Inodoro Guachimania | F36: Uni. | G36: 1 | I36: 1 | J36: 1 | L36: 01.01.05|Inodoro Guachimania|Uni.|materiales
A37: 01.01.05 | B37: Guachimanía de obra, baños, vestidores de obra y otros provisionales | C37: Glb | D37: MAT | E37: Lavabo Guachimania | F37: Uni. | G37: 1 | I37: 1 | J37: 1 | L37: 01.01.05|Lavabo Guachimania|Uni.|materiales
A38: 01.01.05 | B38: Guachimanía de obra, baños, vestidores de obra y otros provisionales | C38: Glb | D38: MAT | E38: Pingos de 2.5 mts | F38: Uni. | G38: 8.5 | I38: 6 | J38: 11 | L38: 01.01.05|Pingos de 2.5 mts|Uni.|materiales
A39: 01.01.05 | B39: Guachimanía de obra, baños, vestidores de obra y otros provisionales | C39: Glb | D39: MAT | E39: Pingos de 3 mts. | F39: Uni. | G39: 24 | J39: 24 | K39: cobertura única | L39: 01.01.05|Pingos de 3 mts.|Uni.|materiales
A40: 01.01.05 | B40: Guachimanía de obra, baños, vestidores de obra y otros provisionales | C40: Glb | D40: MAT | E40: Pingos de 4 mts. | F40: Uni. | G40: 4.5 | H40: 5 | J40: 4 | L40: 01.01.05|Pingos de 4 mts.|Uni.|materiales
A41: 01.01.05 | B41: Guachimanía de obra, baños, vestidores de obra y otros provisionales | C41: Glb | D41: MAT | E41: Pingos de 6 mts. | F41: Uni. | G41: 8.6666667 | H41: 10 | I41: 4 | J41: 12 | L41: 01.01.05|Pingos de 6 mts.|Uni.|materiales
A42: 01.01.05 | B42: Guachimanía de obra, baños, vestidores de obra y otros provisionales | C42: Glb | D42: MAT | E42: Plastico Negro 1.5 mts (Plastico Negro 1.5 mts (2.20 mts x kg) (45 kilos)) | F42: rollo | G42: 0.805 | I42: 1.2 | J42: 0.41 | L42: 01.01.05|Plastico Negro 1.5 mts (Plastico Negro 1.5 mts (2.20 mts x kg) (45 kilos))|rollo|materiales
A43: 01.01.05 | B43: Guachimanía de obra, baños, vestidores de obra y otros provisionales | C43: Glb | D43: MAT | E43: Riel de eucalipto | F43: Uni. | G43: 18 | H43: 18 | I43: 6 | J43: 23 | K43: Rendimiento disperso | L43: 01.01.05|Riel de eucalipto|Uni.|materiales
A44: 01.01.05 | B44: Guachimanía de obra, baños, vestidores de obra y otros provisionales | C44: Glb | D44: MAT | E44: Tablas de Monte | F44: Uni. | G44: 34.666667 | H44: 30 | I44: 32 | J44: 42 | L44: 01.01.05|Tablas de Monte|Uni.|materiales
A45: 01.01.05 | B45: Guachimanía de obra, baños, vestidores de obra y otros provisionales | C45: Glb | D45: MAT | E45: Tablón Rustico | F45: Uni. | G45: 2 | H45: 2 | K45: cobertura única | L45: 01.01.05|Tablón Rustico|Uni.|materiales
A46: 01.01.05 | B46: Guachimanía de obra, baños, vestidores de obra y otros provisionales | C46: Glb | D46: MAT | E46: Tela Arpillera Verde 1.90m (Tela Arpillera Verde 1.90m (Rollo 100m)) | F46: rollo | G46: 1.3 | H46: 1.3 | K46: cobertura única | L46: 01.01.05|Tela Arpillera Verde 1.90m (Tela Arpillera Verde 1.90m (Rollo 100m))|rollo|materiales
A47: 01.01.05 | B47: Guachimanía de obra, baños, vestidores de obra y otros provisionales | C47: Glb | D47: MAT | E47: Zinc 2.40mts x 0.80 cm Cal.0.20 | F47: Uni. | G47: 2 | H47: 2 | K47: cobertura única | L47: 01.01.05|Zinc 2.40mts x 0.80 cm Cal.0.20|Uni.|materiales
A48: 01.01.05 | B48: Guachimanía de obra, baños, vestidores de obra y otros provisionales | C48: Glb | D48: MAT | E48: Zinc 3.60mts x 0.8mts Cal.0.20 | F48: Uni. | G48: 14 | H48: 16 | I48: 12 | J48: 14 | L48: 01.01.05|Zinc 3.60mts x 0.8mts Cal.0.20|Uni.|materiales
A49: 01.01.05 | B49: Guachimanía de obra, baños, vestidores de obra y otros provisionales | C49: Glb | D49: MO | E49: M. Guachimanía de obra, baños, vestidores de obra y otros provisionales | F49: Glb | G49: 1 | H49: 1 | I49: 1 | J49: 1 | K49: MO principal (rend=1) | L49: 01.01.05|M. Guachimanía de obra, baños, vestidores de obra y otros provisionales|Glb|mano_obra
A50: 01.01.08 | B50: Cerramiento provisional de zaram y pingos | C50: ml | D50: MAT | E50: Cemento Campeon HS 50KG | F50: qq | G50: 0.0049920128 | J50: 1 | K50: cobertura única | L50: 01.01.08|Cemento Campeon HS 50KG|qq|materiales
A51: 01.01.08 | B51: Cerramiento provisional de zaram y pingos | C51: ml | D51: MAT | E51: Clavos galvanizados 2'' | F51: Kg. | G51: 0.030673839 | H51: 7.9 | I51: 0.5 | K51: Rendimiento disperso | L51: 01.01.08|Clavos galvanizados 2''|Kg.|materiales
A52: 01.01.08 | B52: Cerramiento provisional de zaram y pingos | C52: ml | D52: MAT | E52: Clavos galvanizados 2 1/2'' | F52: Kg. | G52: 0.010940919 | H52: 1.5 | I52: 5 | J52: 1.5 | K52: Rendimiento disperso | L52: 01.01.08|Clavos galvanizados 2 1/2''|Kg.|materiales
A53: 01.01.08 | B53: Cerramiento provisional de zaram y pingos | C53: ml | D53: MAT | E53: Cuartón 6 x 4 de eucalipto | F53: Uni. | G53: 0.38657914 | H53: 53 | K53: cobertura única | L53: 01.01.08|Cuartón 6 x 4 de eucalipto|Uni.|materiales
A54: 01.01.08 | B54: Cerramiento provisional de zaram y pingos | C54: ml | D54: MAT | E54: Pingos de 2.5 mts | F54: Uni. | G54: 0.16046681 | H54: 22 | I54: 35 | J54: 15 | K54: Rendimiento disperso | L54: 01.01.08|Pingos de 2.5 mts|Uni.|materiales
A55: 01.01.08 | B55: Cerramiento provisional de zaram y pingos | C55: ml | D55: MAT | E55: Pingos de 3 mts. | F55: Uni. | G55: 0.21479673 | H55: 50 | J55: 13 | K55: Rendimiento disperso | L55: 01.01.08|Pingos de 3 mts.|Uni.|materiales
A56: 01.01.08 | B56: Cerramiento provisional de zaram y pingos | C56: ml | D56: MAT | E56: Tela Arpillera Verde 1.90m (Tela Arpillera Verde 1.90m (Rollo 100m)) | F56: rollo | G56: 0.45183403 | H56: 0.7 | J56: 180 | K56: Rendimiento disperso | L56: 01.01.08|Tela Arpillera Verde 1.90m (Tela Arpillera Verde 1.90m (Rollo 100m))|rollo|materiales
A57: 01.01.08 | B57: Cerramiento provisional de zaram y pingos | C57: ml | D57: MAT | E57: Tela Verde UV 2.00 mts. (Tela Verde UV 2.00 mts) | F57: mts. | G57: 0.34944089 | J57: 70 | K57: cobertura única | L57: 01.01.08|Tela Verde UV 2.00 mts. (Tela Verde UV 2.00 mts)|mts.|materiales
A58: 01.01.08 | B58: Cerramiento provisional de zaram y pingos | C58: ml | D58: MAT | E58: Tela Zaran Verde 2.10m (Tela Zaran Verde 2.10m (Rollo 100m)) | F58: ml | G58: 1.1176514 | I58: 150 | K58: cobertura única | L58: 01.01.08|Tela Zaran Verde 2.10m (Tela Zaran Verde 2.10m (Rollo 100m))|ml|materiales
A59: 01.01.08 | B59: Cerramiento provisional de zaram y pingos | C59: ml | D59: MAT | E59: Tiras de 3x3 | F59: Uni. | G59: 0.27627159 | H59: 40 | I59: 35 | L59: 01.01.08|Tiras de 3x3|Uni.|materiales
A60: 01.01.08 | B60: Cerramiento provisional de zaram y pingos | C60: ml | D60: MO | E60: M. Cerramiento provisional de zaram y pingos | F60: ml | G60: 1 | H60: 137.1 | I60: 134.21 | J60: 200.32 | K60: MO principal (rend=1) | L60: 01.01.08|M. Cerramiento provisional de zaram y pingos|ml|mano_obra
A61: 01.01.09 | B61: Desmontaje de guachimanía de obra, baños, vestidores de obra y otros provisionales | C61: Glb | D61: MO | E61: M. Desmontaje de guachimanía de obra, baños, vestidores de obra y otros provisionales | F61: Glb | G61: 1 | J61: 1 | K61: cobertura única | L61: 01.01.09|M. Desmontaje de guachimanía de obra, baños, vestidores de obra y otros provisionales|Glb|mano_obra
A62: 02.01.01 | B62: Excavación mecánica en banco para conformación de plataforma | C62: m3 | D62: EQ | E62: M. Excavación mecánica en banco para conformación de plataforma | F62: m3 | G62: 1 | I62: 618 | J62: 3661.87 | L62: 02.01.01|M. Excavación mecánica en banco para conformación de plataforma|m3|equipo
A63: 02.01.02 | B63: Transporte desalojo de material a botadero | C63: m3 | D63: EQ | E63: M. Transporte desalojo de material a botadero | F63: m3 | G63: 1 | I63: 48.89 | J63: 912.76 | L63: 02.01.02|M. Transporte desalojo de material a botadero|m3|equipo
A64: 02.01.03 | B64: Relleno compactado | C64: m3 | D64: MO | E64: M. Relleno compactado | F64: m3 | G64: 1 | H64: 1029.59 | I64: 41.7 | J64: 2171.83 | K64: MO principal (rend=1) | L64: 02.01.03|M. Relleno compactado|m3|mano_obra
A65: 02.01.04 | B65: Desbroce de Capa Vegetal | C65: m2 | D65: EQ | E65: M. Desbroce de Capa Vegetal | F65: m2 | G65: 1 | H65: 1729.61 | I65: 892.62 | J65: 3141.25 | L65: 02.01.04|M. Desbroce de Capa Vegetal|m2|equipo
A66: 02.01.05 | B66: Rasanteo Y Conformación Manual De Plataformas | C66: m2 | D66: MO | E66: M. Rasanteo Y Conformación Manual De Plataformas | F66: m2 | G66: 1 | H66: 325.39 | I66: 206.5 | J66: 542.9 | K66: MO principal (rend=1) | L66: 02.01.05|M. Rasanteo Y Conformación Manual De Plataformas|m2|mano_obra
A67: 02.01.05 | B67: Rasanteo Y Conformación Manual De Plataformas | C67: m2 | D67: EQ | E67: Alquiler de Maquinaria (retroex (Alquiler de Maquinaria (retroexcavadora)) | F67: Hr, | G67: 0.0018419598 | J67: 1 | K67: cobertura única | L67: 02.01.05|Alquiler de Maquinaria (retroex (Alquiler de Maquinaria (retroexcavadora))|Hr,|equipo
A68: 02.01.06 | B68: Transporte de material para relleno | C68: m3 | D68: EQ | E68: M. Transporte de material para relleno | F68: m3 | G68: 1 | H68: 787.49 | K68: cobertura única | L68: 02.01.06|M. Transporte de material para relleno|m3|equipo
A69: 02.01.07 | B69: Pruebas de compactación en plataformas | C69: Glb | D69: EQ | E69: M. Pruebas de compactación en plataformas | F69: Glb | G69: 1 | H69: 1 | I69: 1 | J69: 1 | L69: 02.01.07|M. Pruebas de compactación en plataformas|Glb|equipo
A70: 02.02.01 | B70: Excavaciones Y Relleno Compactado Para Instalaciones Hidrosanitarias | C70: ml | D70: MO | E70: M. Excavaciones Y Relleno Compactado Para Instalaciones Hidrosanitarias | F70: ml | G70: 1 | I70: 37 | J70: 34.94 | K70: MO principal (rend=1) | L70: 02.02.01|M. Excavaciones Y Relleno Compactado Para Instalaciones Hidrosanitarias|ml|mano_obra
A71: 02.02.02 | B71: Excavaciones Y Relleno Compactado Para Instalaciones Eléctricas | C71: ml | D71: MO | E71: M. Excavaciones Y Relleno Compactado Para Instalaciones Eléctricas | F71: ml | G71: 1 | I71: 25 | K71: cobertura única | L71: 02.02.02|M. Excavaciones Y Relleno Compactado Para Instalaciones Eléctricas|ml|mano_obra
A72: 02.02.04 | B72: Excavaciones Para Plintos Y Cimientos ( Maquina Y Perfilado Manual) | C72: m3 | D72: MO | E72: M. Excavaciones Para Plintos Y Cimientos ( Maquina Y Perfilado Manual) | F72: m3 | G72: 1 | H72: 76.57 | I72: 61.92 | J72: 253.39 | K72: MO principal (rend=1) | L72: 02.02.04|M. Excavaciones Para Plintos Y Cimientos ( Maquina Y Perfilado Manual)|m3|mano_obra
A73: 02.02.04 | B73: Excavaciones Para Plintos Y Cimientos ( Maquina Y Perfilado Manual) | C73: m3 | D73: EQ | E73: Alquiler de Maquinaria (retroex (Alquiler de Maquinaria (retroexcavadora)) | F73: Hr. | G73: 0.21857137 | H73: 23.5 | J73: 33 | L73: 02.02.04|Alquiler de Maquinaria (retroex (Alquiler de Maquinaria (retroexcavadora))|Hr.|equipo
A74: 02.02.05 | B74: Relleno Compactado Con Material Local (Plintos Y Cimientos) | C74: m3 | D74: MAT | E74: Gasolina Extra | F74: gal | G74: 0.31120332 | H74: 17.25 | I74: 12 | J74: 20.48 | K74: Rendimiento disperso | L74: 02.02.05|Gasolina Extra|gal|materiales
A75: 02.02.05 | B75: Relleno Compactado Con Material Local (Plintos Y Cimientos) | C75: m3 | D75: MO | E75: M. Relleno Compactado Con Material Local (Plintos Y Cimientos) | F75: m3 | G75: 1 | H75: 55.43 | I75: 28.2 | J75: 144.88 | K75: MO principal (rend=1) | L75: 02.02.05|M. Relleno Compactado Con Material Local (Plintos Y Cimientos)|m3|mano_obra
A76: 02.02.05 | B76: Relleno Compactado Con Material Local (Plintos Y Cimientos) | C76: m3 | D76: EQ | E76: Alquiler compactador sapo | F76: día | G76: 0.32480507 | H76: 23 | I76: 9.5 | J76: 32.25 | L76: 02.02.05|Alquiler compactador sapo|día|equipo
A77: 02.02.06 | B77: Perfilado de taludes Muros (Incluye plástico polietileno) | C77: m2 | D77: MAT | E77: Clavos galvanizados 2 1/2" | F77: Kg. | G77: 0.0082703214 | J77: 1.75 | K77: cobertura única | L77: 02.02.06|Clavos galvanizados 2 1/2"|Kg.|materiales
A78: 02.02.06 | B78: Perfilado de taludes Muros (Incluye plástico polietileno) | C78: m2 | D78: MAT | E78: Clavos galvanizados 2" | F78: Kg. | G78: 0.002362949 | J78: 0.5 | K78: cobertura única | L78: 02.02.06|Clavos galvanizados 2"|Kg.|materiales
A79: 02.02.06 | B79: Perfilado de taludes Muros (Incluye plástico polietileno) | C79: m2 | D79: MAT | E79: Plastico Negro 1.5 mts (Plastico Negro 1.5 mts (1.98mts x kg) (50.50 kilos)) | F79: rollo | G79: 0.015075614 | J79: 3.19 | K79: cobertura única | L79: 02.02.06|Plastico Negro 1.5 mts (Plastico Negro 1.5 mts (1.98mts x kg) (50.50 kilos))|rollo|materiales
A80: 02.02.06 | B80: Perfilado de taludes Muros (Incluye plástico polietileno) | C80: m2 | D80: MO | E80: M. Perfilado de taludes Muros | F80: m2 | G80: 1 | J80: 211.6 | K80: cobertura única | L80: 02.02.06|M. Perfilado de taludes Muros|m2|mano_obra
A81: 02.02.06 | B81: Perfilado de taludes Muros (Incluye plástico polietileno) | C81: m2 | D81: EQ | E81: Alquiler de Maquinaria (retroex (Alquiler de Maquinaria (retroexcavadora)) | F81: Hr. | G81: 0.02362949 | J81: 5 | K81: cobertura única | L81: 02.02.06|Alquiler de Maquinaria (retroex (Alquiler de Maquinaria (retroexcavadora))|Hr.|equipo
A82: 03.01.01 | B82: Malla De Refuerzo 6*15 | C82: m2 | D82: MAT | E82: Disco de corte metal 9" | F82: Uni. | G82: 0.001494798 | H82: 2 | I82: 1 | J82: 3 | L82: 03.01.01|Disco de corte metal 9"|Uni.|materiales
A83: 03.01.01 | B83: Malla De Refuerzo 6*15 | C83: m2 | D83: MAT | E83: Malla Armex Elect.6mmx15x15R188 (Malla Armex Elect.6mmx15x15 R188) | F83: Uni. | G83: 0.038971414 | H83: 42 | I83: 34 | J83: 85 | L83: 03.01.01|Malla Armex Elect.6mmx15x15R188 (Malla Armex Elect.6mmx15x15 R188)|Uni.|materiales
A84: 03.01.01 | B84: Malla De Refuerzo 6*15 | C84: m2 | D84: MAT | E84: Tiza Industrial | F84: Uni. | G84: 0.0011285281 | H84: 1 | K84: cobertura única | L84: 03.01.01|Tiza Industrial|Uni.|materiales
A85: 03.01.01 | B85: Malla De Refuerzo 6*15 | C85: m2 | D85: MO | E85: M. Malla De Refuerzo 6*15 | F85: m2 | G85: 1 | H85: 886.11 | I85: 884.29 | J85: 2736.01 | K85: MO principal (rend=1) | L85: 03.01.01|M. Malla De Refuerzo 6*15|m2|mano_obra
A86: 03.01.01 | B86: Malla De Refuerzo 6*15 | C86: m2 | D86: EQ | E86: Transporte de Montacargas | F86: Uni. | G86: 0.00036549574 | J86: 1 | K86: cobertura única | L86: 03.01.01|Transporte de Montacargas|Uni.|equipo
A87: 03.01.02 | B87: Hierro 8 Mm X 12 M | C87: Kg. | D87: MAT | E87: Varilla Hierro D=08mmx12m | F87: Uni. | G87: 0.21097046 | H87: 19 | K87: cobertura única | L87: 03.01.02|Varilla Hierro D=08mmx12m|Uni.|materiales
A88: 03.01.02 | B88: Hierro 8 Mm X 12 M | C88: Kg. | D88: MO | E88: M. Hierro 8 Mm X 12 M | F88: Kg. | G88: 1 | H88: 90.06 | K88: cobertura única | L88: 03.01.02|M. Hierro 8 Mm X 12 M|Kg.|mano_obra
A89: 03.01.03 | B89: Hierro 10 Mm X 12 M | C89: Kg. | D89: MAT | E89: Alambre recocido N18 (20kg) (Alambre recocido N18 (20kg)) | F89: Rr20Kg | G89: 0.00028697942 | H89: 2 | I89: 2 | J89: 1 | L89: 03.01.03|Alambre recocido N18 (20kg) (Alambre recocido N18 (20kg))|Rr20Kg|materiales
A90: 03.01.03 | B90: Hierro 10 Mm X 12 M | C90: Kg. | D90: MAT | E90: Disco de corte metal 9" | F90: Uni. | G90: 0.0033967692 | H90: 23 | I90: 18 | J90: 6 | K90: Rendimiento disperso | L90: 03.01.03|Disco de corte metal 9"|Uni.|materiales
A91: 03.01.03 | B91: Hierro 10 Mm X 12 M | C91: Kg. | D91: MAT | E91: Sierra Sanflex Hoja | F91: Uni. | G91: 0.00055226129 | H91: 1 | I91: 3 | J91: 3 | K91: Rendimiento disperso | L91: 03.01.03|Sierra Sanflex Hoja|Uni.|materiales
A92: 03.01.03 | B92: Hierro 10 Mm X 12 M | C92: Kg. | D92: MAT | E92: Tiza Industrial | F92: Uni. | G92: 0.0011850124 | H92: 10 | I92: 8 | J92: 3 | L92: 03.01.03|Tiza Industrial|Uni.|materiales
A93: 03.01.03 | B93: Hierro 10 Mm X 12 M | C93: Kg. | D93: MAT | E93: Varilla Hierro D=10mmx12m | F93: Uni. | G93: 0.11049233 | H93: 902.66763 | I93: 539 | J93: 518 | L93: 03.01.03|Varilla Hierro D=10mmx12m|Uni.|materiales
A94: 03.01.03 | B94: Hierro 10 Mm X 12 M | C94: Kg. | D94: MO | E94: M. Hierro 10 Mm X 12 M | F94: Kg. | G94: 1 | H94: 6771.14 | I94: 5242.74 | J94: 5432.2113 | K94: MO principal (rend=1) | L94: 03.01.03|M. Hierro 10 Mm X 12 M|Kg.|mano_obra
A95: 03.01.03 | B95: Hierro 10 Mm X 12 M | C95: Kg. | D95: EQ | E95: Alquiler Andamio | F95: Uni. | G95: 0.0036817419 | J95: 20 | K95: cobertura única | L95: 03.01.03|Alquiler Andamio|Uni.|equipo
A96: 03.01.03 | B96: Hierro 10 Mm X 12 M | C96: Kg. | D96: EQ | E96: Alquiler de Tablones | F96: Uni. | G96: 0.0036817419 | J96: 20 | K96: cobertura única | L96: 03.01.03|Alquiler de Tablones|Uni.|equipo
A97: 03.01.04 | B97: Hierro 12 Mm X 12 M | C97: Kg. | D97: MAT | E97: Alambre recocido N18 (20kg) (Alambre recocido N18 (20kg)) | F97: Rr20Kg | G97: 0.0017819361 | H97: 9 | I97: 6 | J97: 5 | L97: 03.01.04|Alambre recocido N18 (20kg) (Alambre recocido N18 (20kg))|Rr20Kg|materiales
A98: 03.01.04 | B98: Hierro 12 Mm X 12 M | C98: Kg. | D98: MAT | E98: Disco de corte metal 9" | F98: Uni. | G98: 0.0061830217 | H98: 25 | I98: 22 | J98: 22 | L98: 03.01.04|Disco de corte metal 9"|Uni.|materiales
A99: 03.01.04 | B99: Hierro 12 Mm X 12 M | C99: Kg. | D99: MAT | E99: Sierra Sanflex Hoja | F99: Uni. | G99: 0.00065838419 | H99: 1 | I99: 2 | J99: 3 | K99: Rendimiento disperso | L99: 03.01.04|Sierra Sanflex Hoja|Uni.|materiales
A100: 03.01.04 | B100: Hierro 12 Mm X 12 M | C100: Kg. | D100: MAT | E100: Tiza Industrial | F100: Uni. | G100: 0.0068343245 | H100: 15 | I100: 29 | J100: 30 | L100: 03.01.04|Tiza Industrial|Uni.|materiales
A101: 03.01.04 | B101: Hierro 12 Mm X 12 M | C101: Kg. | D101: MAT | E101: Varilla Hierro D=12mmx12m | F101: Uni. | G101: 0.10337703 | H101: 430 | I101: 249 | J101: 550 | L101: 03.01.04|Varilla Hierro D=12mmx12m|Uni.|materiales
...

Sheet Historial Conversación
A4: # | B4: Actor / Fase | C4: Contenido
A5: 1 | B5: 👤 Usuario | C5: Analiza este archivo que es un análisis de precios unitarios.
A6: 2 | B6: 🤖 Claude — Análisis inicial | C6: Revisé la estructura del archivo "006. Cuadro Comparativo APUs": • 2,263 filas · 17 encabezados de capítulo · 106 APUs • 3 columnas de oferentes (BUENO FERRO, PABLO ESPINOSA, MUÑOZ FREILE) con Cantidad / P.Unitario / Total • Cada APU desagregado en MATERIALES / MANO DE OBRA / EQUIPO + filas TOTAL y COSTO UNITARIO APU Totales iniciales (USD): - PABLO ESPINOSA: $90,847 · 86 rubros cotizados - BUENO FERRO: $114,712 · 75 rubros - MUÑOZ FREILE: $176,923 · 70 rubros Hallazgos: - Muchos #¡DIV/0! por rubros no cotizados - Diferencias grandes en cantidades del mismo rubro (ej. excavación 0/618/3,662 m³) - Valores atípicos en precios unitarios (ej. Cemento $1.94 vs $6.70) - Capítulo 07 Cubiertas y 16 Obras Especiales no cotizados por BUENO FERRO
A7: 3 | B7: 👤 Usuario — Aclaración clave | C7: "Estos son costos de obras, no son proveedores sino el nombre de las obras. El objeto de este análisis es para crear un estándar de precios unitarios."
A8: 4 | B8: 🤖 Claude — Cambio de enfoque | C8: Reinterpretación: los 3 "oferentes" son 3 obras ya ejecutadas (BUENO FERRO, PABLO ESPINOSA, MUÑOZ FREILE) y el objetivo es construir un estándar de precios unitarios. Eso explica: - Las cantidades distintas (obras de distintos tamaños) - Los #¡DIV/0! (cada obra tuvo alcances diferentes) - La columna Q "Cantidad x Unidad" como consolidación Propuse 3 métodos: promedio simple, promedio ponderado, o mediana. Y 3 niveles de detalle: CU total, desagregado por M/MO/E, o desagregado por insumo.
A9: 5 | B9: 👤 Usuario — Decisión de alcance | C9: "Quiero que analices cada uno y que me crees después de tu análisis una propuesta de APUs que sea bien pensada." Nivel: desagregado por Materiales / MO / Equipo.
A10: 6 | B10: 🤖 Claude — Plan de 4 fases | C10: Fase 1: Extraer estructura de los 106 APUs Fase 2: Analizar rubro por rubro aplicando criterio Fase 3: Construir hoja "APU Estándar" desagregada con colores (única / dispersión / válido) Fase 4: Hoja resumen comparativa Pregunté 2 decisiones previas: - Rubros con 1 sola obra: "Incluirlos usando el dato disponible pero resaltados con un color" - Valores dispares >30%: "Señalarlos y pedir confirmación caso por caso"
A11: 7 | B11: 🤖 Claude — Fase 1 Extracción | C11: Extraje estructura completa en blob JSON: - 106 APUs con capítulo/subcapítulo/código/descripción/unidad - 689 líneas de insumos: 494 materiales + 96 mano de obra + 99 equipo - Totales y CU observados por obra
A12: 8 | B12: 🤖 Claude — Fase 2 Detección anomalías | C12: Clasifiqué todas las anomalías de precio: - Cat A (desv > 500%, 5 casos): errores de unidad obvios — descarte automático del outlier - Cat B (100-500%, 17 casos): requieren criterio técnico - Cat C (<100%, 33 casos): variación normal de mercado 28 rubros con cobertura única (1 sola obra los ejecutó). 364 insumos cotizados por 1 sola obra.
A13: 9 | B13: 👤 Usuario — Decisión operativa | C13: "Quisiera que estos casos los dejemos resaltados para realizar un análisis con mis ingenieros. Crea un reporte adicional en otra hoja para verlos."
A14: 10 | B14: 🤖 Claude — Reglas aplicadas | C14: Reglas automáticas: - 1 sola obra → uso ese valor, marco amarillo (cobertura única) - Desv <30% → promedio simple - Desv 30-100% → promedio simple - Desv 100-500% → mediana + marco naranja + agrego al Reporte - Desv >500% → asumo error de unidad, uso mayor o mediana + marca roja Hojas creadas: - "Reporte Decisiones Pendientes" con 28 casos para ingenieros - "APU Estándar" (1,263 filas) con los 106 APUs desagregados - "Resumen CU" con CU por obra + CU Estándar propuesto
A15: 11 | B15: 👤 Usuario — Iteración importante | C15: "Creo que además deberías crear una hoja solo de materiales donde colocamos el precio detallado de estos y con eso tenemos la composición de los APUs atada a esa hoja, con el fin de que si cambio el precio de los materiales los APUs se calculan automáticamente."
A16: 12 | B16: 🤖 Claude — Rediseño a modelo dinámico | C16: Decisiones tomadas: - 3 hojas separadas: BD Materiales, BD Mano de Obra, BD Equipo - Insumos consolidados (1 sola fila por insumo único, 1 PU estándar) - Crear también BD Rendimientos editable Arquitectura: BD Materiales ──┐ BD Mano de Obra ─┼──► APU Estándar ──► Resumen CU BD Equipo ──────┤ (fórmulas VLOOKUP) BD Rendimientos ─┘ Reescribí todas las celdas de APU Estándar con fórmulas: - Cantidad/Rendimiento = INDEX+MATCH a BD Rendimientos (clave única APU+Insumo+Unidad+Sección) - P.Unit = INDEX+MATCH a BD correspondiente por nombre de insumo - Subtotal = D*E - CU APU = SUMA de subtotales Consolidación: - 210 materiales únicos en BD Materiales - 95 ítems en BD Mano de Obra (92 + 3 reconstruidos) - 38 equipos en BD Equipo - 685 relaciones APU↔Insumo en BD Rendimientos
... A19: 15 | B19: 🤖 Claude — Esta hoja | C19: Creada la hoja "Historial Conversación" con este registro completo del proceso, decisiones tomadas y estado final del modelo.
B21: RESUMEN EJECUTIVO FINAL
B23: Hojas operativas del sistema:
B24: • BD Materiales | C24: 210 materiales con PU estándar · Editar columna D
B25: • BD Mano de Obra | C25: 95 ítems con PU estándar · Editar columna D
B26: • BD Equipo | C26: 38 equipos con PU estándar · Editar columna D
B27: • BD Rendimientos | C27: 685+ relaciones APU↔Insumo · Editar columna G
B28: • APU Estándar | C28: 106 APUs desagregados con fórmulas dinámicas (solo lectura)
B29: • Resumen CU | C29: Comparativo CU por obra vs CU Estándar (solo lectura)
B30: • Reporte Decisiones Pendientes | C30: 28 casos de dispersión para revisar con ingenieros
B31: • 006. Cuadro Comparativo APUs | C31: Fuente original (intacta)
B33: Código de colores aplicado:
B34: 🟡 Amarillo claro | C34: Insumo/rubro cotizado por 1 sola obra (cobertura única)
B35: 🟠 Naranja claro | C35: Insumo con dispersión >30% entre obras (revisar)
B36: 🔴 Rojo claro | C36: Rubro sin datos en ninguna obra — requiere cotización
B37: 🟢 Verde claro | C37: Celda editable en las BDs (columna D en precios, G en rendimientos)
B39: Flujo recomendado de uso:
B40: 1 | C40: Revisar Reporte Decisiones Pendientes con ingenieros y decidir valores para los 28 casos
B41: 2 | C41: Ajustar PU en BD Materiales / BD Mano de Obra / BD Equipo según decisiones
B42: 3 | C42: Afinar rendimientos en BD Rendimientos si hay dispersión
B43: 4 | C43: Validar resultados en Resumen CU
B44: 5 | C44: Usar CU Estándar como referencia para futuras licitaciones

Sheet APUs_Maestro
A1: apu_codigo | B1: capitulo | C1: descripcion | D1: unidad | E1: cu_estandar | F1: cu_bf | G1: cu_pe | H1: cu_mf | I1: items_count | J1: has_materiales | K1: has_mano_obra | L1: has_equipo
A2: 01.01.01 | B2: 1 | C2: Replanteo Topográfico Ejes Estructurales y movimiento tierras | D2: Glb | E2: 160 | F2: 0.73757645 | G2: 0.48171491 | H2: 0.1260928 | I2: 1 | J2: 0 | K2: 1 | L2: 1
A3: 01.01.02 | B3: 1 | C3: Replanteo Y Nivelación | D3: m2 | E3: 1.5074793 | F3: 1.4155223 | G3: 1.1585613 | H3: 0.97282133 | I3: 17 | J3: 1 | K3: 1 | L3: 0
A4: 01.01.03 | B4: 1 | C4: Instalaciones eléctricas provisionales | D4: Glb | E4: 300 | F4: 0.92197056 | G4: 1.2042873 | H4: 0.31523201 | I4: 1 | J4: 0 | K4: 1 | L4: 1
A5: 01.01.04 | B5: 1 | C5: Instalaciones hidrosanitarias provisionales | D5: Glb | E5: 300 | F5: 300 | G5: 300 | H5: 300 | I5: 1 | J5: 0 | K5: 1 | L5: 0
A6: 01.01.05 | B6: 1 | C6: Guachimanía de obra, baños, vestidores de obra y otros provisionales | D6: Glb | E6: 1282.3635 | F6: 3.0946341 | G6: 2.4544619 | H6: 0.93983156 | I6: 27 | J6: 1 | K6: 1 | L6: 0
A7: 01.01.08 | B7: 1 | C7: Cerramiento provisional de zaram y pingos | D7: ml | E7: 26.061316 | F7: 4.4366229 | G7: 3.5902645 | H7: 3.092476 | I7: 11 | J7: 1 | K7: 1 | L7: 0
A8: 01.01.09 | B8: 1 | C8: Desmontaje de guachimanía de obra, baños, vestidores de obra y otros provisionales | D8: Glb | E8: 89.29 | H8: 89.29 | I8: 1 | J8: 0 | K8: 1 | L8: 0
A9: 02.01.01 | B9: 2 | C9: Excavación mecánica en banco para conformación de plataforma | D9: m3 | E9: 1.16 | G9: 1.25 | H9: 1.07 | I9: 1 | J9: 0 | K9: 0 | L9: 1
A10: 02.01.02 | B10: 2 | C10: Transporte desalojo de material a botadero | D10: m3 | E10: 20.285 | G10: 36.78 | H10: 3.79 | I10: 1 | J10: 0 | K10: 0 | L10: 1
A11: 02.01.03 | B11: 2 | C11: Relleno compactado | D11: m3 | E11: 2.8833333 | F11: 3 | G11: 3 | H11: 2.65 | I11: 1 | J11: 0 | K11: 1 | L11: 0
A12: 02.01.04 | B12: 2 | C12: Desbroce de Capa Vegetal | D12: m2 | E12: 0.62666667 | F12: 0.65 | G12: 0.65 | H12: 0.58 | I12: 1 | J12: 0 | K12: 0 | L12: 1
A13: 02.01.05 | B13: 2 | C13: Rasanteo Y Conformación Manual De Plataformas | D13: m2 | E13: 0.74052312 | F13: 0.7 | G13: 0.7 | H13: 0.74052312 | I13: 2 | J13: 0 | K13: 1 | L13: 1
A14: 02.01.06 | B14: 2 | C14: Transporte de material para relleno | D14: m3 | E14: 3.92 | F14: 3.92 | I14: 1 | J14: 0 | K14: 0 | L14: 1
A15: 02.01.07 | B15: 2 | C15: Pruebas de compactación en plataformas | D15: Glb | E15: 400 | F15: 350 | G15: 350 | H15: 500 | I15: 1 | J15: 0 | K15: 0 | L15: 1
A16: 02.02.01 | B16: 2 | C16: Excavaciones Y Relleno Compactado Para Instalaciones Hidrosanitarias | D16: ml | E16: 3.9 | G16: 3.9 | H16: 3.9 | I16: 1 | J16: 0 | K16: 1 | L16: 0
A17: 02.02.02 | B17: 2 | C17: Excavaciones Y Relleno Compactado Para Instalaciones Eléctricas | D17: ml | E17: 3.9 | G17: 3.9 | I17: 1 | J17: 0 | K17: 1 | L17: 0
A18: 02.02.04 | B18: 2 | C18: Excavaciones Para Plintos Y Cimientos ( Maquina Y Perfilado Manual) | D18: m3 | E18: 12.641903 | F18: 14.251992 | G18: 7.5 | H18: 11.365149 | I18: 2 | J18: 0 | K18: 1 | L18: 1
A19: 02.02.05 | B19: 2 | C19: Relleno Compactado Con Material Local (Plintos Y Cimientos) | D19: m3 | E19: 13.076102 | F19: 15.329419 | G19: 13.622624 | H19: 10.157457 | I19: 3 | J19: 1 | K19: 1 | L19: 1
A20: 02.02.06 | B20: 2 | C20: Perfilado de taludes Muros (Incluye plástico polietileno) | D20: m2 | E20: 3.4203637 | H20: 3.4999173 | I20: 5 | J20: 1 | K20: 1 | L20: 1
A21: 03.01.01 | B21: 3 | C21: Malla De Refuerzo 6*15 | D21: m2 | E21: 3.0490068 | F21: 3.2280692 | G21: 3.0403732 | H21: 2.7852166 | I21: 5 | J21: 1 | K21: 1 | L21: 1
A22: 03.01.02 | B22: 3 | C22: Hierro 8 Mm X 12 M | D22: Kg. | E22: 1.3875105 | F22: 1.3875105 | I22: 2 | J22: 1 | K22: 1 | L22: 0
A23: 03.01.03 | B23: 3 | C23: Hierro 10 Mm X 12 M | D23: Kg. | E23: 1.2456833 | F23: 1.3946658 | G23: 1.1817746 | H23: 1.1264966 | I23: 8 | J23: 1 | K23: 1 | L23: 1
A24: 03.01.04 | B24: 3 | C24: Hierro 12 Mm X 12 M | D24: Kg. | E24: 1.6140944 | F24: 1.552589 | G24: 1.469208 | H24: 1.8292711 | I24: 8 | J24: 1 | K24: 1 | L24: 1
A25: 03.01.05 | B25: 3 | C25: Hierro 14 Mm X 12 M | D25: Kg. | E25: 1.2229676 | F25: 1.2175225 | G25: 1.2472578 | H25: 0.41154082 | I25: 6 | J25: 1 | K25: 1 | L25: 0
A26: 03.01.06 | B26: 3 | C26: Hierro 16 Mm X 12 M | D26: Kg. | E26: 1.6492449 | F26: 1.414114 | G26: 1.5286974 | H26: 1.9208546 | I26: 7 | J26: 1 | K26: 1 | L26: 0
A27: 03.01.07 | B27: 3 | C27: Hierro 18 Mm X 12 M | D27: Kg. | E27: 1.4161791 | G27: 1.4083458 | H27: 1.4240207 | I27: 2 | J27: 1 | K27: 1 | L27: 0
A28: 03.02.01 | B28: 3 | C28: Plástico Polietileno 2 Capas | D28: m2 | E28: 1.1723939 | F28: 0.84771182 | G28: 0.80298195 | H28: 0.53723371 | I28: 6 | J28: 1 | K28: 1 | L28: 0
A29: 03.02.02 | B29: 3 | C29: Contrapiso De Hormigón Planta Baja F'c=210 Kg/Cm² | D29: m2 | E29: 19.648491 | F29: 17.060077 | G29: 19.16252 | H29: 17.817665 | I29: 24 | J29: 1 | K29: 1 | L29: 1
A30: 03.02.03 | B30: 3 | C30: Juntas de dilatación en contrapiso | D30: m | E30: 6.7753546 | G30: 7.0347518 | I30: 2 | J30: 1 | K30: 1 | L30: 0
A31: 03.03.01 | B31: 3 | C31: Hormigón En Replantillo F'c=180kg/Cm² | D31: m3 | E31: 60.760626 | F31: 82.378475 | G31: 57.001845 | H31: 29.869281 | I31: 4 | J31: 1 | K31: 1 | L31: 0
A32: 03.03.02 | B32: 3 | C32: Hormigón En Plintos F'c=210kg/Cm² | D32: m3 | E32: 113.40115 | F32: 113.62364 | G32: 113.786 | H32: 112.79382 | I32: 4 | J32: 1 | K32: 1 | L32: 1
A33: 03.03.03 | B33: 3 | C33: Hormigón En Cadenas F'c=210kg/Cm² | D33: m3 | E33: 116.40575 | F33: 117.59149 | G33: 34.417333 | H33: 112.10639 | I33: 5 | J33: 1 | K33: 1 | L33: 1
A34: 03.03.04 | B34: 3 | C34: Hormigón En Muros F'c=210kg/Cm² | D34: m3 | E34: 94.736132 | F34: 133.15651 | H34: 114.09981 | I34: 10 | J34: 1 | K34: 1 | L34: 1
A35: 03.03.05 | B35: 3 | C35: Hormigón Premezclado En Columnas F'c=210kg/Cm² CABEZALES | D35: m3 | E35: 150.20853 | F35: 78.033077 | G35: 110.223 | H35: 139.11429 | I35: 9 | J35: 1 | K35: 1 | L35: 1
A36: 03.03.06 | B36: 3 | C36: Hormigón Premezclado En Columnas F'c=210kg/Cm² COLUMNAS | D36: m3 | E36: 152.40665 | F36: 110.73528 | G36: 102.10379 | H36: 382.378 | I36: 11 | J36: 1 | K36: 1 | L36: 1
A37: 03.03.07 | B37: 3 | C37: Hormigón Premezclado En Vigas F'c=210kg/Cm² | D37: m3 | E37: 126.3839 | F37: 125.76333 | G37: 116.94305 | I37: 16 | J37: 1 | K37: 1 | L37: 1
A38: 03.03.08 | B38: 3 | C38: Hormigón En Losa De Entrepiso F'c=210kg/Cm² | D38: m3 | E38: 103.28924 | F38: 90.225789 | G38: 93.93239 | H38: 115.41274 | I38: 11 | J38: 1 | K38: 1 | L38: 1
A39: 03.03.09 | B39: 3 | C39: Hormigón En Cubierta Plana F'c=210kg/Cm² | D39: m3 | E39: 90.201551 | F39: 103.11344 | G39: 68.681954 | I39: 13 | J39: 1 | K39: 1 | L39: 1
A40: 03.03.11 | B40: 3 | C40: Hormigón en dintel descolgado perimetral | D40: ml | E40: 6.5580859 | F40: 6.5793727 | G40: 4.25 | I40: 8 | J40: 1 | K40: 1 | L40: 1
A41: 03.03.15 | B41: 3 | C41: Pruebas de laboratorio | D41: Glb | E41: 60 | F41: 60 | G41: 40 | H41: 80 | I41: 1 | J41: 0 | K41: 0 | L41: 1
A42: 03.03.21 | B42: 3 | C42: Hormigón en detalle tipo Vigueta | D42: m3 | E42: 59.914443 | G42: 58.989975 | I42: 4 | J42: 1 | K42: 1 | L42: 0
A43: 03.03.22 | B43: 3 | C43: Hormigón de nivelación de placas metálicas | D43: m3 | E43: 15 | G43: 15 | I43: 1 | J43: 0 | K43: 1 | L43: 0
A44: 04.01.01 | B44: 4 | C44: Encofrado y Desencofrado Columnas Rectangulares | D44: m2 | E44: 11.25 | F44: 13.89 | G44: 9.93 | H44: 9.93 | I44: 1 | J44: 0 | K44: 1 | L44: 0
A45: 04.01.02 | B45: 4 | C45: Encofrado y Desencofrado de Vigas | D45: m2 | E45: 11.666108 | F45: 25.87 | G45: 11.166285 | H45: 11.5 | I45: 3 | J45: 0 | K45: 1 | L45: 1
A46: 04.01.03 | B46: 4 | C46: Encofrado y Desencofrado de Losa | D46: m2 | E46: 12.565 | G46: 11.5 | I46: 1 | J46: 0 | K46: 1 | L46: 0
A47: 04.01.05 | B47: 4 | C47: Encofrado y Desencofrado Losa Perimetral | D47: ml | E47: 3.87 | F47: 3.85 | G47: 3.88 | H47: 3.88 | I47: 1 | J47: 0 | K47: 1 | L47: 0
A48: 04.01.06 | B48: 4 | C48: Encofrado y Desencofrado Muros | D48: m2 | E48: 11.285 | F48: 12.77 | H48: 9.8 | I48: 1 | J48: 0 | K48: 1 | L48: 0
A49: 04.01.07 | B49: 4 | C49: Apuntalamiento de losa deck metálico | D49: m2 | E49: 1.54 | F49: 1.9 | G49: 1.36 | H49: 1.36 | I49: 1 | J49: 0 | K49: 1 | L49: 0
A50: 04.01.08 | B50: 4 | C50: Encofrado dintel descolgado perimetral | D50: ml | E50: 31.842389 | F50: 6.7875216 | G50: 34.416762 | H50: 6.5 | I50: 9 | J50: 1 | K50: 1 | L50: 1
A51: 05.01.01 | B51: 5 | C51: Mampostería De Bloque E=20cm | D51: m2 | E51: 13.118032 | F51: 16.034281 | G51: 8.9156209 | H51: 12.327992 | I51: 11 | J51: 1 | K51: 1 | L51: 1
A52: 05.01.02 | B52: 5 | C52: Mampostería De Bloque E=15 Cm | D52: m2 | E52: 11.880469 | F52: 13.507909 | G52: 11.479396 | H52: 10.466325 | I52: 12 | J52: 1 | K52: 1 | L52: 1
A53: 05.01.03 | B53: 5 | C53: Mampostería De Bloque E=10 Cm | D53: m2 | E53: 12.923072 | F53: 12.834391 | G53: 10.445438 | H53: 13.674655 | I53: 10 | J53: 1 | K53: 1 | L53: 1
A54: 05.01.05 | B54: 5 | C54: Dinteles De Hormigón F'c = 180 Kg/Cm2 | D54: m | E54: 23.357449 | F54: 21.224618 | G54: 12.424993 | H54: 23.190336 | I54: 30 | J54: 1 | K54: 1 | L54: 1
A55: 05.01.06 | B55: 5 | C55: Arrostramiento Vertical de Mampostería | D55: ml | E55: 16.547392 | F55: 13.309729 | G55: 14.7984 | I55: 31 | J55: 1 | K55: 1 | L55: 1
A56: 05.01.07 | B56: 5 | C56: Alfeizar En Ventana | D56: ml | E56: 16.067098 | F56: 14.397043 | G56: 15.246263 | I56: 19 | J56: 1 | K56: 1 | L56: 1
A57: 05.01.08 | B57: 5 | C57: Alfeizar En Antepecho | D57: ml | E57: 2.8 | G57: 2.8 | I57: 1 | J57: 0 | K57: 1 | L57: 0
A58: 05.01.09 | B58: 5 | C58: Bordillo De Terrazas | D58: ml | E58: 8.012319 | F58: 6.970625 | G58: 8.3483852 | H58: 7.4620174 | I58: 8 | J58: 1 | K58: 1 | L58: 0
A59: 05.01.10 | B59: 5 | C59: Nicho Para Baños y lavavajillas | D59: Und | E59: 33.135479 | F59: 28.945 | G59: 28.158105 | H59: 31.96915 | I59: 6 | J59: 1 | K59: 1 | L59: 0
A60: 05.01.11 | B60: 5 | C60: Ducha Rehundida | D60: m2 | E60: 17.935867 | F60: 17.453893 | G60: 17.334 | H60: 13.26 | I60: 3 | J60: 1 | K60: 1 | L60: 0
A61: 05.01.15 | B61: 5 | C61: Forrado de columnas metálicas | D61: m2 | E61: 5.5439144 | G61: 4.2180051 | H61: 5.3626911 | I61: 8 | J61: 1 | K61: 1 | L61: 0
A62: 06.01.01 | B62: 6 | C62: Enlucido De Fachada | D62: m2 | E62: 7.4633333 | F62: 7.99 | G62: 6.8 | H62: 7.6 | I62: 1 | J62: 0 | K62: 1 | L62: 0
A63: 06.01.03 | B63: 6 | C63: Enlucido De Fajas Exteriores | D63: ml | E63: 3.25 | F63: 3.4 | G63: 3.1 | I63: 1 | J63: 0 | K63: 1 | L63: 0
A64: 06.01.05 | B64: 6 | C64: Enlucido Vertical Interior | D64: m2 | E64: 4.89 | F64: 5.02 | G64: 4.8 | H64: 4.85 | I64: 1 | J64: 0 | K64: 1 | L64: 0
A65: 06.01.06 | B65: 6 | C65: Enlucido De Fajas Interiores | D65: ml | E65: 3 | F65: 3.1 | G65: 2.9 | I65: 1 | J65: 0 | K65: 1 | L65: 0
A66: 06.01.07 | B66: 6 | C66: Enlucido De Filos Interiores | D66: ml | E66: 1.45 | F66: 1.6 | G66: 1.3 | I66: 1 | J66: 0 | K66: 1 | L66: 0
A67: 06.01.08 | B67: 6 | C67: Masillado De Piso A Máquina | D67: m2 | E67: 2.4681998 | F67: 1.2214526 | G67: 1.1428648 | H67: 2.7693821 | I67: 11 | J67: 1 | K67: 1 | L67: 1
A68: 06.01.09 | B68: 6 | C68: Picado Y Corchado | D68: ml | E68: 2.5235102 | F68: 2.9160509 | G68: 1.2208 | H68: 1.4102274 | I68: 13 | J68: 1 | K68: 1 | L68: 0
A69: 06.01.10 | B69: 6 | C69: Goterones - Medias Cañas | D69: ml | E69: 1.34 | F69: 1.5 | G69: 1.26 | H69: 1.26 | I69: 1 | J69: 0 | K69: 1 | L69: 0
A70: 06.01.13 | B70: 6 | C70: Enlucido Exterior Terminado Hormigón Visto | D70: m2 | E70: 3.95 | G70: 3.1 | H70: 4.8 | I70: 1 | J70: 0 | K70: 1 | L70: 0
A71: 06.01.15 | B71: 6 | C71: Masillado De Piso A Máquina Con Endurecedor | D71: m2 | E71: 5.4 | F71: 5.4 | I71: 1 | J71: 0 | K71: 1 | L71: 0
A72: 07.01.05 | B72: 7 | C72: Cubierta de fibrocemento (Incluye capa super K) | D72: m2 | E72: 47.958537 | G72: 44.839946 | H72: 47.898853 | I72: 13 | J72: 1 | K72: 1 | L72: 1
A73: 08.01.10 | B73: 8 | C73: Plástico Negro Para Protección De Terminados | D73: m2 | E73: 2.1253283 | G73: 3.3897417 | H73: 0.37686586 | I73: 9 | J73: 1 | K73: 1 | L73: 0
A74: 13.01.02 | B74: 13 | C74: Limpieza Provisional (Durante la obra Material Y Personal) | D74: Glb | E74: 1152.1419 | F74: 250.295 | G74: 1092.47 | H74: 1123.0059 | I74: 26 | J74: 1 | K74: 1 | L74: 1
A75: 13.01.03 | B75: 13 | C75: Limpieza Y Desalojo De Escombros + tickets emgirs | D75: Viaje | E75: 55.107649 | F75: 50.505 | G75: 74.809524 | H75: 53.325996 | I75: 3 | J75: 1 | K75: 0 | L75: 1
A76: 13.01.09 | B76: 13 | C76: Herramientas de obra | D76: Glb | E76: 5753.4684 | F76: 0.1660205 | G76: 4.3005901 | H76: 1.8038942 | I76: 27 | J76: 1 | K76: 1 | L76: 1
A77: 14.01.02 | B77: 14 | C77: Servicio de Energía Eléctrica | D77: mes | E77: 81.2138 | F77: 29.3319 | G77: 148.3032 | H77: 48.92 | I77: 3 | J77: 1 | K77: 1 | L77: 1
A78: 14.01.03 | B78: 14 | C78: Servicio de Internet | D78: mes | E78: 35 | F78: 35 | I78: 1 | J78: 0 | K78: 1 | L78: 0
A79: 15.01.01 | B79: 15 | C79: Rasanteo y conformación de jardines | D79: m2 | E79: 1.2113176 | F79: 1.7516971 | G79: 1.2015432 | H79: 0.81157499 | I79: 2 | J79: 0 | K79: 1 | L79: 1
A80: 15.01.04 | B80: 15 | C80: Replanteo (Acceso Peatonal) | D80: m2 | E80: 0.87293124 | F80: 0.72 | G80: 0.88888112 | I80: 2 | J80: 1 | K80: 1 | L80: 0
A81: 15.01.05 | B81: 15 | C81: Conformación plataforma (Acceso Peatonal) | D81: m2 | E81: 6.9309391 | F81: 0.7 | G81: 6.3472727 | H81: 1.3339744 | I81: 6 | J81: 1 | K81: 1 | L81: 0
A82: 15.01.06 | B82: 15 | C82: Acceso Peatonal (Obra Civil) | D82: m2 | E82: 26.669532 | F82: 7 | H82: 27.347596 | I82: 14 | J82: 1 | K82: 1 | L82: 1
A83: 15.01.07 | B83: 15 | C83: Plástico Polietileno 2 Capas (Acceso peatonal) | D83: m2 | E83: 2.1601727 | F83: 0.36 | H83: 1.6128205 | I83: 6 | J83: 1 | K83: 1 | L83: 0
A84: 15.01.08 | B84: 15 | C84: Malla De Refuerzo 6*15 (Acceso Peatonal) | D84: m2 | E84: 5.3298004 | F84: 3.8348718 | H84: 3.1921474 | I84: 4 | J84: 1 | K84: 1 | L84: 0
A85: 15.01.10 | B85: 15 | C85: Hormigón En Escaleras F'c=180kg/Cm² (Acceso Peatonal) | D85: m3 | E85: 136.76249 | F85: 135.36229 | I85: 8 | J85: 1 | K85: 1 | L85: 1
A86: 15.01.11 | B86: 15 | C86: Suministro, tendido y compactación de subbase clase III e=20cm (Acceso Peatonal) | D86: m2 | E86: 2 | G86: 2 | I86: 1 | J86: 0 | K86: 1 | L86: 0
A87: 15.01.12 | B87: 15 | C87: Adoquín En Acceso Peatonal | D87: m2 | E87: 12.410565 | G87: 12.445928 | I87: 7 | J87: 1 | K87: 1 | L87: 1
A88: 15.01.13 | B88: 15 | C88: Replanteo Plataforma Parqueadero | D88: m2 | E88: 0.8060744 | G88: 0.78755983 | I88: 3 | J88: 1 | K88: 1 | L88: 0
A89: 15.01.14 | B89: 15 | C89: Conformación Manual De Plataforma Parqueadero | D89: m2 | E89: 0.74 | G89: 0.75 | H89: 0.75 | I89: 1 | J89: 0 | K89: 1 | L89: 0
A90: 15.01.20 | B90: 15 | C90: Suministro, tendido y compactación de subbase clase III e=20cm (Parqueadero) | D90: m2 | E90: 5.2426648 | G90: 5.3287415 | I90: 4 | J90: 1 | K90: 1 | L90: 1
A91: 15.01.21 | B91: 15 | C91: Adoquín En Estacionamiento | D91: m2 | E91: 19.592938 | G91: 19.6289 | I91: 7 | J91: 1 | K91: 1 | L91: 1
A92: 15.01.22 | B92: 15 | C92: Bordillo en estacionamiento (1,00x0,10x0,30m) | D92: ml | E92: 7.4927851 | G92: 7.5286173 | I92: 4 | J92: 1 | K92: 1 | L92: 0
A93: 15.01.23 | B93: 15 | C93: Canal recolector aguas lluvias | D93: ml | E93: 18.873224 | F93: 15.8 | G93: 15.8 | I93: 9 | J93: 1 | K93: 1 | L93: 0
A94: 16.01.01 | B94: 16 | C94: Mampostería de ladrillo visto (Mampostería de ladrillo visto) | D94: m2 | E94: 28.790532 | G94: 27.907639 | I94: 10 | J94: 1 | K94: 1 | L94: 1

Sheet APUs_Items
A1: apu_codigo | B1: seccion | C1: insumo | D1: unidad | E1: cantidad_rendimiento | F1: pu | G1: subtotal
A2: 01.01.01 | B2: MANO DE OBRA | C2: M. Replanteo Topográfico Ejes Estructurales y movimiento tierras | D2: Glb | E2: 1 | F2: 160 | G2: 160
A3: 01.01.02 | B3: MATERIALES | C3: Alambre galvanizado N 14 | D3: rollo | E3: 0.0030732352 | F3: 82.9725 | G3: 0.25499401
A4: 01.01.02 | B4: MATERIALES | C4: Broca Madera Titanio3/8" | D4: Uni. | E4: 0.0010507734 | F4: 1.02 | G4: 0.0010717888
A5: 01.01.02 | B5: MATERIALES | C5: Caoba Roja | D5: lb | E5: 0.017743166 | F5: 0.517 | G5: 0.0091732167
A6: 01.01.02 | B6: MATERIALES | C6: Cementina | D6: saco | E6: 0.024467622 | F6: 1.636 | G6: 0.040029029
A7: 01.01.02 | B7: MATERIALES | C7: Clavos de acero 2'' | D7: Kg. | E7: 0.0046098528 | F7: 3.245 | G7: 0.014958972
A8: 01.01.02 | B8: MATERIALES | C8: Clavos de acero 21/2'' | D8: Kg. | E8: 0.0040142909 | F8: 3.5215 | G8: 0.014136325
A9: 01.01.02 | B9: MATERIALES | C9: Clavos galvanizados 2'' | D9: Kg. | E9: 0.0093924525 | F9: 1.9257895 | G9: 0.018087886
A10: 01.01.02 | B10: MATERIALES | C10: Clavos galvanizados 2 1/2'' | D10: Kg. | E10: 0.0062778171 | F10: 1.8223333 | G10: 0.011440275
A11: 01.01.02 | B11: MATERIALES | C11: Clavos galvanizados 3" | D11: Kg. | E11: 0.0040142909 | F11: 2.415 | G11: 0.0096945125
A12: 01.01.02 | B12: MATERIALES | C12: Cuartón 6 x 4 de eucalipto | D12: Uni. | E12: 0.013660054 | F12: 2.15 | G12: 0.029369116
A13: 01.01.02 | B13: MATERIALES | C13: Manguera transparente | D13: ml | E13: 0.10035727 | F13: 0.4 | G13: 0.040142909
... A605: 16.01.01 | B605: EQUIPO | C605: Alquiler de Tablones | D605: Uni. | E605: 1.7025538 | F605: 0.089948261 | G605: 0.15314176

Sheet README_Sistema
A1: README — ESTÁNDAR DE APUs PARA SISTEMA DE PRESUPUESTACIÓN
A3: Fuente: | B3: Análisis comparativo de 3 obras ejecutadas (BUENO FERRO · PABLO ESPINOSA · MUÑOZ FREILE)
A4: Estado: | B4: 93 APUs limpios con CU > 0 (excluidos 11 sin datos, 1 sin código válido)
A5: Moneda: | B5: USD
A7: ═══ HOJAS PARA CONSUMIR DESDE CLAUDE CODE ═══
A9: 📄 APUs_Maestro | B9: 1 fila por APU. Tabla Excel: tbl_apus_maestro
A10: 📄 APUs_Items | B10: 1 fila por insumo. Tabla Excel: tbl_apus_items
A12: Relación: | B12: APUs_Maestro.apu_codigo 1:N APUs_Items.apu_codigo (FK)
A14: ═══ ESQUEMA: APUs_Maestro ═══
A15: Columna | B15: Tipo / Descripción
A16: apu_codigo | B16: STRING · PK · formato 'NN.NN.NN' (ej: 03.02.02)
A17: capitulo | B17: STRING · primer segmento del código (01-17)
A18: descripcion | B18: STRING · descripción técnica del rubro
A19: unidad | B19: STRING · unidad de medida (m2, m3, ml, Glb, kg, etc.)
A20: cu_estandar | B20: FLOAT · Costo Unitario estándar propuesto (USD)
A21: cu_bf | B21: FLOAT · CU observado en obra BUENO FERRO (0 si no ejecutó)
A22: cu_pe | B22: FLOAT · CU observado en obra PABLO ESPINOSA
A23: cu_mf | B23: FLOAT · CU observado en obra MUÑOZ FREILE
A24: items_count | B24: INT · número de insumos que componen el APU
A25: has_materiales | B25: INT · 1 si tiene sección MATERIALES, 0 si no
A26: has_mano_obra | B26: INT · 1 si tiene sección MANO DE OBRA, 0 si no
A27: has_equipo | B27: INT · 1 si tiene sección EQUIPO, 0 si no
A29: ═══ ESQUEMA: APUs_Items ═══
A30: Columna | B30: Tipo / Descripción
A31: apu_codigo | B31: STRING · FK → APUs_Maestro.apu_codigo
A32: seccion | B32: ENUM · 'MATERIALES' | 'MANO DE OBRA' | 'EQUIPO'
A33: insumo | B33: STRING · descripción del insumo (nombre natural, puede unirse con BD Materiales/MO/Equipo)
A34: unidad | B34: STRING · unidad del insumo
A35: cantidad_rendimiento | B35: FLOAT · cantidad del insumo por unidad del APU (rendimiento)
A36: pu | B36: FLOAT · precio unitario del insumo (USD)
A37: subtotal | B37: FLOAT · cantidad_rendimiento × pu (USD)
A39: ═══ INVARIANTES VERIFICADOS ═══
B40: • SUM(subtotal) por apu_codigo ≈ cu_estandar
B41: • Todo apu_codigo en APUs_Items existe en APUs_Maestro
B42: • cu_estandar > 0 para todos los 93 registros
B43: • No hay valores nulos en columnas clave (apu_codigo, descripcion, unidad, cu_estandar)
A45: ═══ EJEMPLO DE LECTURA EN PYTHON ═══
B46: import pandas as pd
B47: apus = pd.read_excel('archivo.xlsb', sheet_name='APUs_Maestro')
B48: items = pd.read_excel('archivo.xlsb', sheet_name='APUs_Items')
B50: # Reconstruir APU completo:
B51: detalle = items[items.apu_codigo == '03.02.02']
B52: cu = detalle.subtotal.sum() # ≈ apus[apus.apu_codigo=='03.02.02'].cu_estandar
A54: ═══ NOTAS PARA EL SISTEMA DE PRESUPUESTACIÓN ═══
B55: • Para un presupuesto: usuario elige apu_codigo + ingresa 'cantidad'
B56: • Costo del rubro = cantidad × cu_estandar
B57: • Total presupuesto = SUM(costo_rubro)
B58: • Si quieres escalar precios, aplicar factor sobre 'pu' en APUs_Items y recalcular cu_estandar
B59: • Los insumos en APUs_Items se pueden unir por nombre con las hojas BD Materiales / BD Mano de Obra / BD Equipo del libro fuente
